Workbook

Sheet README
A1: KYC / AML Compliance Operations Simulation
A2: An Excel-only (formula-driven, no macros, no code) portfolio project for a Client Data / KYC Analyst role.
A4: IMPORTANT
A5: All clients, transactions and amounts are SYNTHETIC (invented). Thresholds, country scores and rules are illustrative and not legal advice. This is a self-built simulation to show method and skills, not real work history.
A7: PURPOSE
A8: Simulates the day-to-day work of a KYC quality reviewer: check client records for completeness and errors, monitor transactions against red flags, assess CTR obligations, reconcile two data sources, escalate with a written risk summary, and resolve client-facing issues within SLA.
A10: SHEET GUIDE
A11: Dashboard | B11: KPIs and charts across every process, all formula-driven.
A12: Assumptions | B12: Thresholds, risk-scoring tables, review cycles and SLAs (blue = editable inputs). Change a value and every sheet recalculates.
A13: Client_Master | B13: KYC records for 40 clients + automated checks: document completeness, risk score vs assigned rating, periodic review due dates, duplicates, date logic and blank fields.
A14: Transactions | B14: Cash and wire activity with helper columns: near-threshold flag, daily cash aggregation, country risk, KYC status.
A15: CTR_Log | B15: Daily cash aggregation per client and direction, CTR required test, filing deadline and timeliness tracking.
A16: Alert_Monitoring | B16: Six scenario rules (R1-R6) per client, with an ESCALATE / Analyst Review / No Action disposition.
A17: Escalation_Matrix | B17: Escalation levels, owners, SLAs and documentation requirements.
A18: Escalation_Log | B18: 10 cases with analyst-written risk summaries, SLA tracking and outcomes.
A19: Recon_Client | B19: CRM vs Core Banking client data reconciliation (name, country, rating, missing records, active accounts with incomplete KYC).
A20: Recon_Txn | B20: Ledger vs bank statement reconciliation with a control-total proof that every difference is explained.
A21: Customer_Issues | B21: 14 client/internal tickets with priority, SLA tracking and resolution notes.
A22: Src_CoreBanking / Src_BankStatement | B22: Source extracts used by the reconciliations.
A24: COLOUR LEGEND
A25: Navy header | B25: Raw data / manual input columns (safe to edit).
A26: Grey header | B26: Formula columns - do not overwrite.
A27: Red / amber / green cells | B27: Conditional formatting: red = exception or breach, amber = attention, green = OK.
A29: PLANTED SCENARIOS (what a reviewer should find)
A30: CTR aggregation | B30: C005: two same-day deposits ($6,200 + $5,100) aggregate above $10,000. C012: single $14,500 deposit. C008: three large deposits, one CTR not filed by the deadline.
A31: Structuring | B31: C019: four deposits of $9,200-$9,800 in five days, each under the threshold.
A32: High-risk jurisdiction | B32: C027: $105,000 wired to Myanmar; client under-rated.
A33: PEP / pass-through | B33: C015: PEP with $240,000 of wires. C022: $250,000 in, $246,500 out within three days.
A34: Sanctions / onboarding | B34: C036: unresolved potential match. C038: wire received before KYC completion.
A35: Data breaks | B35: Name, country and rating mismatches; client missing from core banking; account with no KYC record (C041); duplicate client record; date logic error; 3 amount breaks, 2 missing and 1 duplicate in the bank statement.
A37: HOW TO USE
A38: 1 | B38: Open Dashboard for the overall picture, then follow each exception to its sheet.
A39: 2 | B39: Change a threshold in Assumptions (e.g. CTR threshold) and watch CTR flags, alerts and the dashboard update.
A40: 3 | B40: Add a row to Client_Master or Transactions and copy the grey formula cells down to test a new case.

Sheet Dashboard
A1: KYC / AML Compliance Operations - Dashboard
A2: ="As of "&TEXT(Assumptions!B4,"dd-mmm-yyyy")&" | Synthetic data - for portfolio demonstration only" -> As of 26-Oct-2026 | Synthetic data - for portfolio demonstration only
A4: 1. KYC FILE HEALTH
A5: Total client records | B5: =COUNTA(Client_Master!A2:A41) -> 40
A6: Complete KYC files | B6: =COUNTIF(Client_Master!R2:R41,"Complete") -> 35
A7: % files complete | B7: =B6/B5 -> 0.875
A8: Records missing one or more documents | B8: =COUNTIF(Client_Master!P2:P41,">0") -> 4
A9: Periodic reviews overdue | B9: =COUNTIF(Client_Master!AA2:AA41,"Overdue") -> 6
A10: Periodic reviews due within 60 days | B10: =COUNTIF(Client_Master!AA2:AA41,"Due within 60 days") -> 2
A11: Risk rating mismatches (under/over-rated) | B11: =COUNTIF(Client_Master!X2:X41,"Under-rated")+COUNTIF(Client_Master!X2:X41,"Over-rated") -> 4
A12: PEP clients | B12: =COUNTIF(Client_Master!N2:N41,"Y") -> 2
A13: Records with at least one DQ exception | B13: =COUNTIF(Client_Master!AE2:AE41,">0") -> 16
A14: Transactions on accounts with incomplete / no KYC | B14: =COUNTIF(Transactions!O2:O114,"<>Complete") -> 14
A16: 2. RISK RATING DISTRIBUTION (assigned)
A17: High | B17: =COUNTIF(Client_Master!H2:H41,"High") -> 2
A18: Medium | B18: =COUNTIF(Client_Master!H2:H41,"Medium") -> 7
A19: Low | B19: =COUNTIF(Client_Master!H2:H41,"Low") -> 31
A21: 3. CTR REPORTING
A22: Client-days requiring a CTR | B22: =COUNTIF(CTR_Log!F2:F21,"YES") -> 5
A23: Total cash value covered by CTRs (USD) | B23: =SUMIFS(CTR_Log!D2:D21,CTR_Log!F2:F21,"YES")+SUMIFS(CTR_Log!E2:E21,CTR_Log!F2:F21,"YES") -> 110800
A24: Filed on time | B24: =COUNTIF(CTR_Log!L2:L21,"On time") -> 3
A25: Pending - within deadline | B25: =COUNTIF(CTR_Log!L2:L21,"Pending*") -> 1
A26: Late / not filed (exceptions) | B26: =COUNTIF(CTR_Log!L2:L21,"LATE*")+COUNTIF(CTR_Log!L2:L21,"Late") -> 1
A27: Near-threshold cash transactions (structuring watch) | B27: =COUNTIF(Transactions!K2:K114,"Y") -> 4
A29: 4. TRANSACTION MONITORING
A30: Clients monitored | B30: =COUNTA(Alert_Monitoring!A2:A41) -> 40
A31: Disposition: ESCALATE | B31: =COUNTIF(Alert_Monitoring!R2:R41,"ESCALATE") -> 4
A32: Disposition: Analyst Review | B32: =COUNTIF(Alert_Monitoring!R2:R41,"Analyst Review") -> 2
A33: Disposition: No Action | B33: =COUNTIF(Alert_Monitoring!R2:R41,"No Action") -> 34
A35: 5. ESCALATIONS
A36: Cases logged | B36: =COUNTA(Escalation_Log!A2:A11) -> 10
A37: Open cases | B37: =COUNTIF(Escalation_Log!K2:K11,"Open") -> 8
A38: Closed cases | B38: =COUNTIF(Escalation_Log!K2:K11,"Closed") -> 2
A39: SLA breached | B39: =COUNTIF(Escalation_Log!M2:M11,"SLA Breached") -> 1
A41: 6. DATA RECONCILIATION
A42: Client recon: reconciled | B42: =COUNTIF(Recon_Client!M2:M42,"Reconciled") -> 35
A43: Client recon: field breaks | B43: =COUNTIF(Recon_Client!M2:M42,"Break*") -> 4
A44: Client recon: missing in CRM / Core | B44: =COUNTIF(Recon_Client!M2:M42,"Missing*") -> 2
A45: Active accounts with incomplete / no KYC | B45: =COUNTIF(Recon_Client!N2:N42,"Active*") -> 6
A46: Txn recon: Matched | B46: =COUNTIF(Recon_Txn!E2:E115,"Matched") -> 107
A47: Txn recon: Amount Break | B47: =COUNTIF(Recon_Txn!E2:E115,"Amount Break") -> 3
A48: Txn recon: Missing in Statement | B48: =COUNTIF(Recon_Txn!E2:E115,"Missing in Statement") -> 2
A49: Txn recon: Missing in Ledger | B49: =COUNTIF(Recon_Txn!E2:E115,"Missing in Ledger") -> 1
A50: Txn recon: Duplicate in Statement | B50: =COUNTIF(Recon_Txn!E2:E115,"Duplicate in Statement") -> 1
A51: Unexplained control-total difference (USD) | B51: =Recon_Txn!L6 -> 0
A53: 7. CUSTOMER ISSUES
A54: Issues logged | B54: =COUNTA(Customer_Issues!A2:A15) -> 14
A55: Open issues | B55: =COUNTIF(Customer_Issues!K2:K15,"Open") -> 9
A56: Issues within SLA (% of all logged) | B56: =COUNTIF(Customer_Issues!N2:N15,"Within SLA")/COUNTA(Customer_Issues!A2:A15) -> 0.78571429
A57: SLA breached | B57: =COUNTIF(Customer_Issues!N2:N15,"SLA Breached") -> 3

Sheet Assumptions
A1: Assumptions & Reference Tables
A2: Blue values are inputs - change them and every sheet recalculates. All thresholds are ILLUSTRATIVE; replace with your firm/regulator values.
A3: Parameter | B3: Value | C3: Note / Basis
A4: As-of (review) date | B4: 46321 | C4: Fixed date so results are reproducible. Replace with =TODAY() for live use.
A5: CTR threshold (USD) | B5: 10000 | C5: US BSA: cash transactions MORE than $10,000 in one business day, aggregated per person, per direction. Edit for other regimes.
A6: Structuring band - lower bound (USD) | B6: 8000 | C6: Cash amounts from this value up to the CTR threshold are treated as "near-threshold".
A7: Min near-threshold cash txns to alert | B7: 3 | C7: Rule R1: number of near-threshold cash transactions in the window.
A8: Cash vs profile multiple | B8: 2 | C8: Rule R2: alert when actual cash > expected cash x this multiple.
A9: Monitoring window (months) | B9: 2 | C9: Transactions cover Sep-Oct 2026. Expected cash is scaled by this.
A10: CTR filing deadline (calendar days) | B10: 15 | C10: US FinCEN CTR: file within 15 calendar days of the transaction.
A11: PEP activity review threshold (USD) | B11: 100000 | C11: Rule R4: PEP with total wire value at/above this is escalated.
A12: Pass-through tolerance (+/-) | B12: 0.05 | C12: Rule R5: outbound within +/-5% of inbound.
A13: Pass-through minimum value (USD) | B13: 100000 | C13: Rule R5: both inbound and outbound wires at least this size.
A14: High risk - minimum score | B14: 6 | C14: Score >= this = High.
A15: Medium risk - minimum score | B15: 3 | C15: Score >= this (and below High) = Medium.
A16: PEP score weight | B16: 3 | C16: Added to risk score when client is a PEP.
A19: Reference tables (risk scoring, review cycles, SLAs)
A21: Country | B21: Risk Score (0-3) | C21: Basis (illustrative - not an official list) | E21: Industry | F21: Risk Score | H21: Entity Type | I21: Risk Score | K21: Risk Rating | L21: Review Cycle (Years) | N21: Issue Priority | O21: SLA (business days)
A22: United States | B22: 0 | C22: Lower risk | E22: Software/IT | F22: 0 | H22: Corporate | I22: 0 | K22: High | L22: 1 | N22: High | O22: 2
A23: United Kingdom | B23: 0 | C23: Lower risk | E23: Manufacturing | F23: 0 | H23: Individual | I23: 0 | K23: Medium | L23: 2 | N23: Medium | O23: 5
A24: India | B24: 0 | C24: Lower risk | E24: Healthcare | F24: 0 | H24: Partnership | I24: 1 | K24: Low | L24: 3 | N24: Low | O24: 10
A25: Singapore | B25: 0 | C25: Lower risk | E25: Consulting | F25: 1 | H25: Trust | I25: 1
A26: Germany | B26: 0 | C26: Lower risk | E26: Retail | F26: 1
A27: Switzerland | B27: 0 | C27: Lower risk | E27: Logistics & Shipping | F27: 1
A28: Japan | B28: 0 | C28: Lower risk | E28: Real Estate | F28: 2
A29: Canada | B29: 0 | C29: Lower risk | E29: Import/Export Trading | F29: 2
A30: Hong Kong | B30: 1 | C30: Medium - monitor | E30: Restaurants & Hospitality | F30: 2
A31: United Arab Emirates | B31: 1 | C31: Medium - monitor | E31: Charity/NGO | F31: 2
A32: Cyprus | B32: 1 | C32: Medium - monitor | E32: Used Vehicle Dealers | F32: 2
A33: Turkey | B33: 1 | C33: Medium - monitor | E33: Jewelry & Precious Metals | F33: 3
A34: Panama | B34: 2 | C34: Elevated risk | E34: Money Services Business | F34: 3
A35: Cayman Islands | B35: 2 | C35: Elevated risk | E35: Casinos & Gaming | F35: 3
A36: Nigeria | B36: 2 | C36: Elevated risk
A37: Myanmar | B37: 3 | C37: High risk / call for action
A38: Iran | B38: 3 | C38: High risk / call for action
A39: North Korea | B39: 3 | C39: High risk / call for action
A41: Risk score = Country + Industry + Entity type + (PEP weight if PEP). Rating: High / Medium / Low per thresholds above.

Sheet Client_Master
A1: Client ID | B1: Legal Name | C1: Entity Type | D1: Country | E1: Industry | F1: Onboarding Date | G1: Last KYC Review | H1: Assigned Risk Rating | I1: CIP Verified (Y/N) | J1: UBO Identified (Y/N) | K1: Address Proof (Y/N) | L1: Source of Funds (Y/N) | M1: Sanctions Screening | N1: PEP (Y/N) | O1: Expected Monthly Cash (USD) | P1: Docs Missing (of 4) | Q1: Blank Mandatory Fields | R1: File Status | S1: Country Score | T1: Industry Score | U1: Entity Score | V1: Risk Score | W1: Calculated Rating | X1: Rating Check | Y1: Review Cycle (Yrs) | Z1: Next Review Due | AA1: Review Status | AB1: Days Overdue | AC1: Duplicate Check | AD1: Date Logic Check | AE1: DQ Exception Count
A2: C001 | B2: Aurora Software Solutions Pvt Ltd | C2: Corporate | D2: India | E2: Software/IT | F2: 45326 | G2: 46160 | H2: Low | I2: Y | J2: Y | K2: Y | L2: Y | M2: Clear | N2: N | O2: 0 | P2: =4-COUNTIF(I2:L2,"Y") -> 0 | Q2: =COUNTBLANK(A2:O2) -> 0 | R2: =IF(P2>0,"Incomplete - Docs",IF(M2<>"Clear","Incomplete - Screening","Complete")) -> Complete | S2: =IFERROR(INDEX(Assumptions!$B$22:$B$39,MATCH(D2,Assumptions!$A$22:$A$39,0)),0) -> 0 | T2: =IFERROR(INDEX(Assumptions!$F$22:$F$35,MATCH(E2,Assumptions!$E$22:$E$35,0)),0) -> 0 | U2: =IFERROR(INDEX(Assumptions!$I$22:$I$25,MATCH(C2,Assumptions!$H$22:$H$25,0)),0) -> 0 | V2: =S2+T2+U2+IF(N2="Y",Assumptions!$B$16,0) -> 0 | W2: =IF(V2>=Assumptions!$B$14,"High",IF(V2>=Assumptions!$B$15,"Medium","Low")) -> Low | X2: =IF(H2=W2,"OK",IF(((H2="High")*3+(H2="Medium")*2+(H2="Low"))<((W2="High")*3+(W2="Medium")*2+(W2="Low")),"Under-rated","Over-rated")) -> OK | Y2: =INDEX(Assumptions!$L$22:$L$24,MATCH(H2,Assumptions!$K$22:$K$24,0)) -> 3 | Z2: =EDATE(G2,12*Y2) -> 47256 | AA2: =IF(Z2<Assumptions!$B$4,"Overdue",IF(Z2<=Assumptions!$B$4+60,"Due within 60 days","Current")) -> Current | AB2: =MAX(0,Assumptions!$B$4-Z2) -> 0 | AC2: =IF(COUNTIF($B$2:$B$41,B2)>1,"Duplicate","OK") -> OK | AD2: =IF(G2<F2,"Review before onboarding",IF(F2>Assumptions!$B$4,"Future onboarding","OK")) -> OK | AE2: =(P2>0)+(Q2>0)+(X2<>"OK")+(AC2<>"OK")+(AD2<>"OK")+(AA2="Overdue") -> 0
A3: C002 | B3: Nordic Precision Manufacturing GmbH | C3: Corporate | D3: Germany | E3: Manufacturing | F3: 44539 | G3: 45767 | H3: Low | I3: Y | J3: Y | K3: Y | L3: Y | M3: Clear | N3: N | O3: 0 | P3: =4-COUNTIF(I3:L3,"Y") -> 0 | Q3: =COUNTBLANK(A3:O3) -> 0 | R3: =IF(P3>0,"Incomplete - Docs",IF(M3<>"Clear","Incomplete - Screening","Complete")) -> Complete | S3: =IFERROR(INDEX(Assumptions!$B$22:$B$39,MATCH(D3,Assumptions!$A$22:$A$39,0)),0) -> 0 | T3: =IFERROR(INDEX(Assumptions!$F$22:$F$35,MATCH(E3,Assumptions!$E$22:$E$35,0)),0) -> 0 | U3: =IFERROR(INDEX(Assumptions!$I$22:$I$25,MATCH(C3,Assumptions!$H$22:$H$25,0)),0) -> 0 | V3: =S3+T3+U3+IF(N3="Y",Assumptions!$B$16,0) -> 0 | W3: =IF(V3>=Assumptions!$B$14,"High",IF(V3>=Assumptions!$B$15,"Medium","Low")) -> Low | X3: =IF(H3=W3,"OK",IF(((H3="High")*3+(H3="Medium")*2+(H3="Low"))<((W3="High")*3+(W3="Medium")*2+(W3="Low")),"Under-rated","Over-rated")) -> OK | Y3: =INDEX(Assumptions!$L$22:$L$24,MATCH(H3,Assumptions!$K$22:$K$24,0)) -> 3 | Z3: =EDATE(G3,12*Y3) -> 46863 | AA3: =IF(Z3<Assumptions!$B$4,"Overdue",IF(Z3<=Assumptions!$B$4+60,"Due within 60 days","Current")) -> Current | AB3: =MAX(0,Assumptions!$B$4-Z3) -> 0 | AC3: =IF(COUNTIF($B$2:$B$41,B3)>1,"Duplicate","OK") -> OK | AD3: =IF(G3<F3,"Review before onboarding",IF(F3>Assumptions!$B$4,"Future onboarding","OK")) -> OK | AE3: =(P3>0)+(Q3>0)+(X3<>"OK")+(AC3<>"OK")+(AD3<>"OK")+(AA3="Overdue") -> 0
A4: C003 | B4: Lotus Healthcare Systems Ltd | C4: Corporate | D4: India | E4: Healthcare | F4: 45229 | G4: 45619 | H4: Low | I4: Y | J4: Y | K4: Y | L4: Y | M4: Clear | N4: N | O4: 0 | P4: =4-COUNTIF(I4:L4,"Y") -> 0 | Q4: =COUNTBLANK(A4:O4) -> 0 | R4: =IF(P4>0,"Incomplete - Docs",IF(M4<>"Clear","Incomplete - Screening","Complete")) -> Complete | S4: =IFERROR(INDEX(Assumptions!$B$22:$B$39,MATCH(D4,Assumptions!$A$22:$A$39,0)),0) -> 0 | T4: =IFERROR(INDEX(Assumptions!$F$22:$F$35,MATCH(E4,Assumptions!$E$22:$E$35,0)),0) -> 0 | U4: =IFERROR(INDEX(Assumptions!$I$22:$I$25,MATCH(C4,Assumptions!$H$22:$H$25,0)),0) -> 0 | V4: =S4+T4+U4+IF(N4="Y",Assumptions!$B$16,0) -> 0 | W4: =IF(V4>=Assumptions!$B$14,"High",IF(V4>=Assumptions!$B$15,"Medium","Low")) -> Low | X4: =IF(H4=W4,"OK",IF(((H4="High")*3+(H4="Medium")*2+(H4="Low"))<((W4="High")*3+(W4="Medium")*2+(W4="Low")),"Under-rated","Over-rated")) -> OK | Y4: =INDEX(Assumptions!$L$22:$L$24,MATCH(H4,Assumptions!$K$22:$K$24,0)) -> 3 | Z4: =EDATE(G4,12*Y4) -> 46714 | AA4: =IF(Z4<Assumptions!$B$4,"Overdue",IF(Z4<=Assumptions!$B$4+60,"Due within 60 days","Current")) -> Current | AB4: =MAX(0,Assumptions!$B$4-Z4) -> 0 | AC4: =IF(COUNTIF($B$2:$B$41,B4)>1,"Duplicate","OK") -> OK | AD4: =IF(G4<F4,"Review before onboarding",IF(F4>Assumptions!$B$4,"Future onboarding","OK")) -> OK | AE4: =(P4>0)+(Q4>0)+(X4<>"OK")+(AC4<>"OK")+(AD4<>"OK")+(AA4="Overdue") -> 0
A5: C004 | B5: Thames Consulting Partners LLP | C5: Partnership | D5: United Kingdom | E5: Consulting | F5: 44739 | G5: 45376 | H5: Low | I5: Y | J5: Y | K5: Y | L5: Y | M5: Clear | N5: N | O5: 0 | P5: =4-COUNTIF(I5:L5,"Y") -> 0 | Q5: =COUNTBLANK(A5:O5) -> 0 | R5: =IF(P5>0,"Incomplete - Docs",IF(M5<>"Clear","Incomplete - Screening","Complete")) -> Complete | S5: =IFERROR(INDEX(Assumptions!$B$22:$B$39,MATCH(D5,Assumptions!$A$22:$A$39,0)),0) -> 0 | T5: =IFERROR(INDEX(Assumptions!$F$22:$F$35,MATCH(E5,Assumptions!$E$22:$E$35,0)),0) -> 1 | U5: =IFERROR(INDEX(Assumptions!$I$22:$I$25,MATCH(C5,Assumptions!$H$22:$H$25,0)),0) -> 1 | V5: =S5+T5+U5+IF(N5="Y",Assumptions!$B$16,0) -> 2 | W5: =IF(V5>=Assumptions!$B$14,"High",IF(V5>=Assumptions!$B$15,"Medium","Low")) -> Low | X5: =IF(H5=W5,"OK",IF(((H5="High")*3+(H5="Medium")*2+(H5="Low"))<((W5="High")*3+(W5="Medium")*2+(W5="Low")),"Under-rated","Over-rated")) -> OK | Y5: =INDEX(Assumptions!$L$22:$L$24,MATCH(H5,Assumptions!$K$22:$K$24,0)) -> 3 | Z5: =EDATE(G5,12*Y5) -> 46471 | AA5: =IF(Z5<Assumptions!$B$4,"Overdue",IF(Z5<=Assumptions!$B$4+60,"Due within 60 days","Current")) -> Current | AB5: =MAX(0,Assumptions!$B$4-Z5) -> 0 | AC5: =IF(COUNTIF($B$2:$B$41,B5)>1,"Duplicate","OK") -> OK | AD5: =IF(G5<F5,"Review before onboarding",IF(F5>Assumptions!$B$4,"Future onboarding","OK")) -> OK | AE5: =(P5>0)+(Q5>0)+(X5<>"OK")+(AC5<>"OK")+(AD5<>"OK")+(AA5="Overdue") -> 0
A6: C005 | B6: Spice Route Restaurants Group Inc | C6: Corporate | D6: United States | E6: Restaurants & Hospitality | F6: 43955 | G6: 45365 | H6: Low | I6: Y | J6: Y | K6: Y | L6: Y | M6: Clear | N6: N | O6: 40000 | P6: =4-COUNTIF(I6:L6,"Y") -> 0 | Q6: =COUNTBLANK(A6:O6) -> 0 | R6: =IF(P6>0,"Incomplete - Docs",IF(M6<>"Clear","Incomplete - Screening","Complete")) -> Complete | S6: =IFERROR(INDEX(Assumptions!$B$22:$B$39,MATCH(D6,Assumptions!$A$22:$A$39,0)),0) -> 0 | T6: =IFERROR(INDEX(Assumptions!$F$22:$F$35,MATCH(E6,Assumptions!$E$22:$E$35,0)),0) -> 2 | U6: =IFERROR(INDEX(Assumptions!$I$22:$I$25,MATCH(C6,Assumptions!$H$22:$H$25,0)),0) -> 0 | V6: =S6+T6+U6+IF(N6="Y",Assumptions!$B$16,0) -> 2 | W6: =IF(V6>=Assumptions!$B$14,"High",IF(V6>=Assumptions!$B$15,"Medium","Low")) -> Low | X6: =IF(H6=W6,"OK",IF(((H6="High")*3+(H6="Medium")*2+(H6="Low"))<((W6="High")*3+(W6="Medium")*2+(W6="Low")),"Under-rated","Over-rated")) -> OK | Y6: =INDEX(Assumptions!$L$22:$L$24,MATCH(H6,Assumptions!$K$22:$K$24,0)) -> 3 | Z6: =EDATE(G6,12*Y6) -> 46460 | AA6: =IF(Z6<Assumptions!$B$4,"Overdue",IF(Z6<=Assumptions!$B$4+60,"Due within 60 days","Current")) -> Current | AB6: =MAX(0,Assumptions!$B$4-Z6) -> 0 | AC6: =IF(COUNTIF($B$2:$B$41,B6)>1,"Duplicate","OK") -> OK | AD6: =IF(G6<F6,"Review before onboarding",IF(F6>Assumptions!$B$4,"Future onboarding","OK")) -> OK | AE6: =(P6>0)+(Q6>0)+(X6<>"OK")+(AC6<>"OK")+(AD6<>"OK")+(AA6="Overdue") -> 0
A7: C006 | B7: Meridian Textile Exports Pvt Ltd | C7: Corporate | D7: India | E7: Import/Export Trading | F7: 44326 | G7: 45645 | H7: Low | I7: Y | J7: Y | K7: Y | L7: Y | M7: Clear | N7: N | O7: 0 | P7: =4-COUNTIF(I7:L7,"Y") -> 0 | Q7: =COUNTBLANK(A7:O7) -> 0 | R7: =IF(P7>0,"Incomplete - Docs",IF(M7<>"Clear","Incomplete - Screening","Complete")) -> Complete | S7: =IFERROR(INDEX(Assumptions!$B$22:$B$39,MATCH(D7,Assumptions!$A$22:$A$39,0)),0) -> 0 | T7: =IFERROR(INDEX(Assumptions!$F$22:$F$35,MATCH(E7,Assumptions!$E$22:$E$35,0)),0) -> 2 | U7: =IFERROR(INDEX(Assumptions!$I$22:$I$25,MATCH(C7,Assumptions!$H$22:$H$25,0)),0) -> 0 | V7: =S7+T7+U7+IF(N7="Y",Assumptions!$B$16,0) -> 2 | W7: =IF(V7>=Assumptions!$B$14,"High",IF(V7>=Assumptions!$B$15,"Medium","Low")) -> Low | X7: =IF(H7=W7,"OK",IF(((H7="High")*3+(H7="Medium")*2+(H7="Low"))<((W7="High")*3+(W7="Medium")*2+(W7="Low")),"Under-rated","Over-rated")) -> OK | Y7: =INDEX(Assumptions!$L$22:$L$24,MATCH(H7,Assumptions!$K$22:$K$24,0)) -> 3 | Z7: =EDATE(G7,12*Y7) -> 46740 | AA7: =IF(Z7<Assumptions!$B$4,"Overdue",IF(Z7<=Assumptions!$B$4+60,"Due within 60 days","Current")) -> Current | AB7: =MAX(0,Assumptions!$B$4-Z7) -> 0 | AC7: =IF(COUNTIF($B$2:$B$41,B7)>1,"Duplicate","OK") -> Duplicate | AD7: =IF(G7<F7,"Review before onboarding",IF(F7>Assumptions!$B$4,"Future onboarding","OK")) -> OK | AE7: =(P7>0)+(Q7>0)+(X7<>"OK")+(AC7<>"OK")+(AD7<>"OK")+(AA7="Overdue") -> 1
A8: C007 | B8: Alpine Logistics AG | C8: Corporate | D8: Switzerland | E8: Logistics & Shipping | F8: 43483 | G8: 45267 | H8: Low | I8: Y | J8: Y | K8: Y | L8: Y | M8: Clear | N8: N | O8: 0 | P8: =4-COUNTIF(I8:L8,"Y") -> 0 | Q8: =COUNTBLANK(A8:O8) -> 0 | R8: =IF(P8>0,"Incomplete - Docs",IF(M8<>"Clear","Incomplete - Screening","Complete")) -> Complete | S8: =IFERROR(INDEX(Assumptions!$B$22:$B$39,MATCH(D8,Assumptions!$A$22:$A$39,0)),0) -> 0 | T8: =IFERROR(INDEX(Assumptions!$F$22:$F$35,MATCH(E8,Assumptions!$E$22:$E$35,0)),0) -> 1 | U8: =IFERROR(INDEX(Assumptions!$I$22:$I$25,MATCH(C8,Assumptions!$H$22:$H$25,0)),0) -> 0 | V8: =S8+T8+U8+IF(N8="Y",Assumptions!$B$16,0) -> 1 | W8: =IF(V8>=Assumptions!$B$14,"High",IF(V8>=Assumptions!$B$15,"Medium","Low")) -> Low | X8: =IF(H8=W8,"OK",IF(((H8="High")*3+(H8="Medium")*2+(H8="Low"))<((W8="High")*3+(W8="Medium")*2+(W8="Low")),"Under-rated","Over-rated")) -> OK | Y8: =INDEX(Assumptions!$L$22:$L$24,MATCH(H8,Assumptions!$K$22:$K$24,0)) -> 3 | Z8: =EDATE(G8,12*Y8) -> 46363 | AA8: =IF(Z8<Assumptions!$B$4,"Overdue",IF(Z8<=Assumptions!$B$4+60,"Due within 60 days","Current")) -> Due within 60 days | AB8: =MAX(0,Assumptions!$B$4-Z8) -> 0 | AC8: =IF(COUNTIF($B$2:$B$41,B8)>1,"Duplicate","OK") -> OK | AD8: =IF(G8<F8,"Review before onboarding",IF(F8>Assumptions!$B$4,"Future onboarding","OK")) -> OK | AE8: =(P8>0)+(Q8>0)+(X8<>"OK")+(AC8<>"OK")+(AD8<>"OK")+(AA8="Overdue") -> 0
A9: C008 | B9: Golden Crest Jewellers LLC | C9: Corporate | D9: United Arab Emirates | E9: Jewelry & Precious Metals | F9: 44394 | G9: 45695 | H9: Low | I9: Y | J9: Y | K9: Y | L9: Y | M9: Clear | N9: N | O9: 20000 | P9: =4-COUNTIF(I9:L9,"Y") -> 0 | Q9: =COUNTBLANK(A9:O9) -> 0 | R9: =IF(P9>0,"Incomplete - Docs",IF(M9<>"Clear","Incomplete - Screening","Complete")) -> Complete | S9: =IFERROR(INDEX(Assumptions!$B$22:$B$39,MATCH(D9,Assumptions!$A$22:$A$39,0)),0) -> 1 | T9: =IFERROR(INDEX(Assumptions!$F$22:$F$35,MATCH(E9,Assumptions!$E$22:$E$35,0)),0) -> 3 | U9: =IFERROR(INDEX(Assumptions!$I$22:$I$25,MATCH(C9,Assumptions!$H$22:$H$25,0)),0) -> 0 | V9: =S9+T9+U9+IF(N9="Y",Assumptions!$B$16,0) -> 4 | W9: =IF(V9>=Assumptions!$B$14,"High",IF(V9>=Assumptions!$B$15,"Medium","Low")) -> Medium | X9: =IF(H9=W9,"OK",IF(((H9="High")*3+(H9="Medium")*2+(H9="Low"))<((W9="High")*3+(W9="Medium")*2+(W9="Low")),"Under-rated","Over-rated")) -> Under-rated | Y9: =INDEX(Assumptions!$L$22:$L$24,MATCH(H9,Assumptions!$K$22:$K$24,0)) -> 3 | Z9: =EDATE(G9,12*Y9) -> 46790 | AA9: =IF(Z9<Assumptions!$B$4,"Overdue",IF(Z9<=Assumptions!$B$4+60,"Due within 60 days","Current")) -> Current | AB9: =MAX(0,Assumptions!$B$4-Z9) -> 0 | AC9: =IF(COUNTIF($B$2:$B$41,B9)>1,"Duplicate","OK") -> OK | AD9: =IF(G9<F9,"Review before onboarding",IF(F9>Assumptions!$B$4,"Future onboarding","OK")) -> OK | AE9: =(P9>0)+(Q9>0)+(X9<>"OK")+(AC9<>"OK")+(AD9<>"OK")+(AA9="Overdue") -> 1
A10: C009 | B10: Pinnacle Realty Developers Ltd | C10: Corporate | D10: Singapore | E10: Real Estate | F10: 44061 | G10: 45779 | H10: Medium | I10: Y | J10: Y | K10: Y | L10: Y | M10: Clear | N10: N | O10: 0 | P10: =4-COUNTIF(I10:L10,"Y") -> 0 | Q10: =COUNTBLANK(A10:O10) -> 0 | R10: =IF(P10>0,"Incomplete - Docs",IF(M10<>"Clear","Incomplete - Screening","Complete")) -> Complete | S10: =IFERROR(INDEX(Assumptions!$B$22:$B$39,MATCH(D10,Assumptions!$A$22:$A$39,0)),0) -> 0 | T10: =IFERROR(INDEX(Assumptions!$F$22:$F$35,MATCH(E10,Assumptions!$E$22:$E$35,0)),0) -> 2 | U10: =IFERROR(INDEX(Assumptions!$I$22:$I$25,MATCH(C10,Assumptions!$H$22:$H$25,0)),0) -> 0 | V10: =S10+T10+U10+IF(N10="Y",Assumptions!$B$16,0) -> 2 | W10: =IF(V10>=Assumptions!$B$14,"High",IF(V10>=Assumptions!$B$15,"Medium","Low")) -> Low | X10: =IF(H10=W10,"OK",IF(((H10="High")*3+(H10="Medium")*2+(H10="Low"))<((W10="High")*3+(W10="Medium")*2+(W10="Low")),"Under-rated","Over-rated")) -> Over-rated | Y10: =INDEX(Assumptions!$L$22:$L$24,MATCH(H10,Assumptions!$K$22:$K$24,0)) -> 2 | Z10: =EDATE(G10,12*Y10) -> 46509 | AA10: =IF(Z10<Assumptions!$B$4,"Overdue",IF(Z10<=Assumptions!$B$4+60,"Due within 60 days","Current")) -> Current | AB10: =MAX(0,Assumptions!$B$4-Z10) -> 0 | AC10: =IF(COUNTIF($B$2:$B$41,B10)>1,"Duplicate","OK") -> OK | AD10: =IF(G10<F10,"Review before onboarding",IF(F10>Assumptions!$B$4,"Future onboarding","OK")) -> OK | AE10: =(P10>0)+(Q10>0)+(X10<>"OK")+(AC10<>"OK")+(AD10<>"OK")+(AA10="Overdue") -> 1
A11: C010 | B11: Harbour Point Trading Co | C11: Corporate | D11: Hong Kong | E11: Import/Export Trading | F11: 45159 | G11: 45830 | H11: Medium | I11: Y | J11: Y | K11: Y | L11: Y | M11: Clear | N11: N | O11: 0 | P11: =4-COUNTIF(I11:L11,"Y") -> 0 | Q11: =COUNTBLANK(A11:O11) -> 0 | R11: =IF(P11>0,"Incomplete - Docs",IF(M11<>"Clear","Incomplete - Screening","Complete")) -> Complete | S11: =IFERROR(INDEX(Assumptions!$B$22:$B$39,MATCH(D11,Assumptions!$A$22:$A$39,0)),0) -> 1 | T11: =IFERROR(INDEX(Assumptions!$F$22:$F$35,MATCH(E11,Assumptions!$E$22:$E$35,0)),0) -> 2 | U11: =IFERROR(INDEX(Assumptions!$I$22:$I$25,MATCH(C11,Assumptions!$H$22:$H$25,0)),0) -> 0 | V11: =S11+T11+U11+IF(N11="Y",Assumptions!$B$16,0) -> 3 | W11: =IF(V11>=Assumptions!$B$14,"High",IF(V11>=Assumptions!$B$15,"Medium","Low")) -> Medium | X11: =IF(H11=W11,"OK",IF(((H11="High")*3+(H11="Medium")*2+(H11="Low"))<((W11="High")*3+(W11="Medium")*2+(W11="Low")),"Under-rated","Over-rated")) -> OK | Y11: =INDEX(Assumptions!$L$22:$L$24,MATCH(H11,Assumptions!$K$22:$K$24,0)) -> 2 | Z11: =EDATE(G11,12*Y11) -> 46560 | AA11: =IF(Z11<Assumptions!$B$4,"Overdue",IF(Z11<=Assumptions!$B$4+60,"Due within 60 days","Current")) -> Current | AB11: =MAX(0,Assumptions!$B$4-Z11) -> 0 | AC11: =IF(COUNTIF($B$2:$B$41,B11)>1,"Duplicate","OK") -> OK | AD11: =IF(G11<F11,"Review before onboarding",IF(F11>Assumptions!$B$4,"Future onboarding","OK")) -> OK | AE11: =(P11>0)+(Q11>0)+(X11<>"OK")+(AC11<>"OK")+(AD11<>"OK")+(AA11="Overdue") -> 0
A12: C011 | B12: Coral Reef Gaming Ltd | C12: Corporate | D12: Cayman Islands | E12: Casinos & Gaming | F12: 44124 | G12: 45561 | H12: Medium | I12: Y | J12: Y | K12: Y | L12: Y | M12: Clear | N12: N | O12: 0 | P12: =4-COUNTIF(I12:L12,"Y") -> 0 | Q12: =COUNTBLANK(A12:O12) -> 0 | R12: =IF(P12>0,"Incomplete - Docs",IF(M12<>"Clear","Incomplete - Screening","Complete")) -> Complete | S12: =IFERROR(INDEX(Assumptions!$B$22:$B$39,MATCH(D12,Assumptions!$A$22:$A$39,0)),0) -> 2 | T12: =IFERROR(INDEX(Assumptions!$F$22:$F$35,MATCH(E12,Assumptions!$E$22:$E$35,0)),0) -> 3 | U12: =IFERROR(INDEX(Assumptions!$I$22:$I$25,MATCH(C12,Assumptions!$H$22:$H$25,0)),0) -> 0 | V12: =S12+T12+U12+IF(N12="Y",Assumptions!$B$16,0) -> 5 | W12: =IF(V12>=Assumptions!$B$14,"High",IF(V12>=Assumptions!$B$15,"Medium","Low")) -> Medium | X12: =IF(H12=W12,"OK",IF(((H12="High")*3+(H12="Medium")*2+(H12="Low"))<((W12="High")*3+(W12="Medium")*2+(W12="Low")),"Under-rated","Over-rated")) -> OK | Y12: =INDEX(Assumptions!$L$22:$L$24,MATCH(H12,Assumptions!$K$22:$K$24,0)) -> 2 | Z12: =EDATE(G12,12*Y12) -> 46291 | AA12: =IF(Z12<Assumptions!$B$4,"Overdue",IF(Z12<=Assumptions!$B$4+60,"Due within 60 days","Current")) -> Overdue | AB12: =MAX(0,Assumptions!$B$4-Z12) -> 30 | AC12: =IF(COUNTIF($B$2:$B$41,B12)>1,"Duplicate","OK") -> OK | AD12: =IF(G12<F12,"Review before onboarding",IF(F12>Assumptions!$B$4,"Future onboarding","OK")) -> OK | AE12: =(P12>0)+(Q12>0)+(X12<>"OK")+(AC12<>"OK")+(AD12<>"OK")+(AA12="Overdue") -> 1
A13: C012 | B13: Brightline Retail Holdings Inc | C13: Corporate | D13: United States | E13: Retail | F13: 45793 | G13: 46199 | H13: Low | I13: Y | J13: Y | K13: Y | L13: Y | M13: Clear | N13: N | O13: 45000 | P13: =4-COUNTIF(I13:L13,"Y") -> 0 | Q13: =COUNTBLANK(A13:O13) -> 0 | R13: =IF(P13>0,"Incomplete - Docs",IF(M13<>"Clear","Incomplete - Screening","Complete")) -> Complete | S13: =IFERROR(INDEX(Assumptions!$B$22:$B$39,MATCH(D13,Assumptions!$A$22:$A$39,0)),0) -> 0 | T13: =IFERROR(INDEX(Assumptions!$F$22:$F$35,MATCH(E13,Assumptions!$E$22:$E$35,0)),0) -> 1 | U13: =IFERROR(INDEX(Assumptions!$I$22:$I$25,MATCH(C13,Assumptions!$H$22:$H$25,0)),0) -> 0 | V13: =S13+T13+U13+IF(N13="Y",Assumptions!$B$16,0) -> 1 | W13: =IF(V13>=Assumptions!$B$14,"High",IF(V13>=Assumptions!$B$15,"Medium","Low")) -> Low | X13: =IF(H13=W13,"OK",IF(((H13="High")*3+(H13="Medium")*2+(H13="Low"))<((W13="High")*3+(W13="Medium")*2+(W13="Low")),"Under-rated","Over-rated")) -> OK | Y13: =INDEX(Assumptions!$L$22:$L$24,MATCH(H13,Assumptions!$K$22:$K$24,0)) -> 3 | Z13: =EDATE(G13,12*Y13) -> 47295 | AA13: =IF(Z13<Assumptions!$B$4,"Overdue",IF(Z13<=Assumptions!$B$4+60,"Due within 60 days","Current")) -> Current | AB13: =MAX(0,Assumptions!$B$4-Z13) -> 0 | AC13: =IF(COUNTIF($B$2:$B$41,B13)>1,"Duplicate","OK") -> OK | AD13: =IF(G13<F13,"Review before onboarding",IF(F13>Assumptions!$B$4,"Future onboarding","OK")) -> OK | AE13: =(P13>0)+(Q13>0)+(X13<>"OK")+(AC13<>"OK")+(AD13<>"OK")+(AA13="Overdue") -> 0
... A24: C023 | B24: Cedar Hill Property Holdings Ltd | C24: Corporate | D24: United Kingdom | E24: Real Estate | F24: 44899 | G24: 45262 | H24: Low | I24: Y | J24: Y | K24: Y | L24: Y | M24: Clear | N24: N | O24: 0 | P24: =4-COUNTIF(I24:L24,"Y") -> 0 | Q24: =COUNTBLANK(A24:O24) -> 0 | R24: =IF(P24>0,"Incomplete - Docs",IF(M24<>"Clear","Incomplete - Screening","Complete")) -> Complete | S24: =IFERROR(INDEX(Assumptions!$B$22:$B$39,MATCH(D24,Assumptions!$A$22:$A$39,0)),0) -> 0 | T24: =IFERROR(INDEX(Assumptions!$F$22:$F$35,MATCH(E24,Assumptions!$E$22:$E$35,0)),0) -> 2 | U24: =IFERROR(INDEX(Assumptions!$I$22:$I$25,MATCH(C24,Assumptions!$H$22:$H$25,0)),0) -> 0 | V24: =S24+T24+U24+IF(N24="Y",Assumptions!$B$16,0) -> 2 | W24: =IF(V24>=Assumptions!$B$14,"High",IF(V24>=Assumptions!$B$15,"Medium","Low")) -> Low | X24: =IF(H24=W24,"OK",IF(((H24="High")*3+(H24="Medium")*2+(H24="Low"))<((W24="High")*3+(W24="Medium")*2+(W24="Low")),"Under-rated","Over-rated")) -> OK | Y24: =INDEX(Assumptions!$L$22:$L$24,MATCH(H24,Assumptions!$K$22:$K$24,0)) -> 3 | Z24: =EDATE(G24,12*Y24) -> 46358 | AA24: =IF(Z24<Assumptions!$B$4,"Overdue",IF(Z24<=Assumptions!$B$4+60,"Due within 60 days","Current")) -> Due within 60 days | AB24: =MAX(0,Assumptions!$B$4-Z24) -> 0 | AC24: =IF(COUNTIF($B$2:$B$41,B24)>1,"Duplicate","OK") -> OK | AD24: =IF(G24<F24,"Review before onboarding",IF(F24>Assumptions!$B$4,"Future onboarding","OK")) -> OK | AE24: =(P24>0)+(Q24>0)+(X24<>"OK")+(AC24<>"OK")+(AD24<>"OK")+(AA24="Overdue") -> 0
A25: C024 | B25: Sunrise Auto Traders LLC | C25: Corporate | D25: United States | F25: 44430 | G25: 45711 | H25: Low | I25: Y | J25: Y | K25: Y | L25: N | M25: Clear | N25: N | O25: 30000 | P25: =4-COUNTIF(I25:L25,"Y") -> 1 | Q25: =COUNTBLANK(A25:O25) -> 1 | R25: =IF(P25>0,"Incomplete - Docs",IF(M25<>"Clear","Incomplete - Screening","Complete")) -> Incomplete - Docs | S25: =IFERROR(INDEX(Assumptions!$B$22:$B$39,MATCH(D25,Assumptions!$A$22:$A$39,0)),0) -> 0 | T25: =IFERROR(INDEX(Assumptions!$F$22:$F$35,MATCH(E25,Assumptions!$E$22:$E$35,0)),0) -> 0 | U25: =IFERROR(INDEX(Assumptions!$I$22:$I$25,MATCH(C25,Assumptions!$H$22:$H$25,0)),0) -> 0 | V25: =S25+T25+U25+IF(N25="Y",Assumptions!$B$16,0) -> 0 | W25: =IF(V25>=Assumptions!$B$14,"High",IF(V25>=Assumptions!$B$15,"Medium","Low")) -> Low | X25: =IF(H25=W25,"OK",IF(((H25="High")*3+(H25="Medium")*2+(H25="Low"))<((W25="High")*3+(W25="Medium")*2+(W25="Low")),"Under-rated","Over-rated")) -> OK | Y25: =INDEX(Assumptions!$L$22:$L$24,MATCH(H25,Assumptions!$K$22:$K$24,0)) -> 3 | Z25: =EDATE(G25,12*Y25) -> 46806 | AA25: =IF(Z25<Assumptions!$B$4,"Overdue",IF(Z25<=Assumptions!$B$4+60,"Due within 60 days","Current")) -> Current | AB25: =MAX(0,Assumptions!$B$4-Z25) -> 0 | AC25: =IF(COUNTIF($B$2:$B$41,B25)>1,"Duplicate","OK") -> OK | AD25: =IF(G25<F25,"Review before onboarding",IF(F25>Assumptions!$B$4,"Future onboarding","OK")) -> OK | AE25: =(P25>0)+(Q25>0)+(X25<>"OK")+(AC25<>"OK")+(AD25<>"OK")+(AA25="Overdue") -> 2
A26: C025 | B26: Crescent Remit Services LLP | C26: Partnership | D26: Nigeria | E26: Money Services Business | F26: 45438 | G26: 46207 | H26: High | I26: Y | J26: Y | K26: Y | L26: Y | M26: Clear | N26: N | O26: 0 | P26: =4-COUNTIF(I26:L26,"Y") -> 0 | Q26: =COUNTBLANK(A26:O26) -> 0 | R26: =IF(P26>0,"Incomplete - Docs",IF(M26<>"Clear","Incomplete - Screening","Complete")) -> Complete | S26: =IFERROR(INDEX(Assumptions!$B$22:$B$39,MATCH(D26,Assumptions!$A$22:$A$39,0)),0) -> 2 | T26: =IFERROR(INDEX(Assumptions!$F$22:$F$35,MATCH(E26,Assumptions!$E$22:$E$35,0)),0) -> 3 | U26: =IFERROR(INDEX(Assumptions!$I$22:$I$25,MATCH(C26,Assumptions!$H$22:$H$25,0)),0) -> 1 | V26: =S26+T26+U26+IF(N26="Y",Assumptions!$B$16,0) -> 6 | W26: =IF(V26>=Assumptions!$B$14,"High",IF(V26>=Assumptions!$B$15,"Medium","Low")) -> High | X26: =IF(H26=W26,"OK",IF(((H26="High")*3+(H26="Medium")*2+(H26="Low"))<((W26="High")*3+(W26="Medium")*2+(W26="Low")),"Under-rated","Over-rated")) -> OK | Y26: =INDEX(Assumptions!$L$22:$L$24,MATCH(H26,Assumptions!$K$22:$K$24,0)) -> 1 | Z26: =EDATE(G26,12*Y26) -> 46572 | AA26: =IF(Z26<Assumptions!$B$4,"Overdue",IF(Z26<=Assumptions!$B$4+60,"Due within 60 days","Current")) -> Current | AB26: =MAX(0,Assumptions!$B$4-Z26) -> 0 | AC26: =IF(COUNTIF($B$2:$B$41,B26)>1,"Duplicate","OK") -> OK | AD26: =IF(G26<F26,"Review before onboarding",IF(F26>Assumptions!$B$4,"Future onboarding","OK")) -> OK | AE26: =(P26>0)+(Q26>0)+(X26<>"OK")+(AC26<>"OK")+(AD26<>"OK")+(AA26="Overdue") -> 0
A27: C026 | B27: Palm Bay Casino Resorts | C27: Partnership | D27: Panama | E27: Casinos & Gaming | F27: 44976 | G27: 45444 | H27: Medium | I27: Y | J27: Y | K27: Y | L27: Y | M27: Clear | N27: N | O27: 0 | P27: =4-COUNTIF(I27:L27,"Y") -> 0 | Q27: =COUNTBLANK(A27:O27) -> 0 | R27: =IF(P27>0,"Incomplete - Docs",IF(M27<>"Clear","Incomplete - Screening","Complete")) -> Complete | S27: =IFERROR(INDEX(Assumptions!$B$22:$B$39,MATCH(D27,Assumptions!$A$22:$A$39,0)),0) -> 2 | T27: =IFERROR(INDEX(Assumptions!$F$22:$F$35,MATCH(E27,Assumptions!$E$22:$E$35,0)),0) -> 3 | U27: =IFERROR(INDEX(Assumptions!$I$22:$I$25,MATCH(C27,Assumptions!$H$22:$H$25,0)),0) -> 1 | V27: =S27+T27+U27+IF(N27="Y",Assumptions!$B$16,0) -> 6 | W27: =IF(V27>=Assumptions!$B$14,"High",IF(V27>=Assumptions!$B$15,"Medium","Low")) -> High | X27: =IF(H27=W27,"OK",IF(((H27="High")*3+(H27="Medium")*2+(H27="Low"))<((W27="High")*3+(W27="Medium")*2+(W27="Low")),"Under-rated","Over-rated")) -> Under-rated | Y27: =INDEX(Assumptions!$L$22:$L$24,MATCH(H27,Assumptions!$K$22:$K$24,0)) -> 2 | Z27: =EDATE(G27,12*Y27) -> 46174 | AA27: =IF(Z27<Assumptions!$B$4,"Overdue",IF(Z27<=Assumptions!$B$4+60,"Due within 60 days","Current")) -> Overdue | AB27: =MAX(0,Assumptions!$B$4-Z27) -> 147 | AC27: =IF(COUNTIF($B$2:$B$41,B27)>1,"Duplicate","OK") -> OK | AD27: =IF(G27<F27,"Review before onboarding",IF(F27>Assumptions!$B$4,"Future onboarding","OK")) -> OK | AE27: =(P27>0)+(Q27>0)+(X27<>"OK")+(AC27<>"OK")+(AD27<>"OK")+(AA27="Overdue") -> 2
A28: C027 | B28: Irrawaddy Trade Links Ltd | C28: Corporate | D28: Hong Kong | E28: Import/Export Trading | F28: 43884 | G28: 45384 | H28: Low | I28: Y | J28: Y | K28: Y | L28: Y | M28: Clear | N28: N | O28: 0 | P28: =4-COUNTIF(I28:L28,"Y") -> 0 | Q28: =COUNTBLANK(A28:O28) -> 0 | R28: =IF(P28>0,"Incomplete - Docs",IF(M28<>"Clear","Incomplete - Screening","Complete")) -> Complete | S28: =IFERROR(INDEX(Assumptions!$B$22:$B$39,MATCH(D28,Assumptions!$A$22:$A$39,0)),0) -> 1 | T28: =IFERROR(INDEX(Assumptions!$F$22:$F$35,MATCH(E28,Assumptions!$E$22:$E$35,0)),0) -> 2 | U28: =IFERROR(INDEX(Assumptions!$I$22:$I$25,MATCH(C28,Assumptions!$H$22:$H$25,0)),0) -> 0 | V28: =S28+T28+U28+IF(N28="Y",Assumptions!$B$16,0) -> 3 | W28: =IF(V28>=Assumptions!$B$14,"High",IF(V28>=Assumptions!$B$15,"Medium","Low")) -> Medium | X28: =IF(H28=W28,"OK",IF(((H28="High")*3+(H28="Medium")*2+(H28="Low"))<((W28="High")*3+(W28="Medium")*2+(W28="Low")),"Under-rated","Over-rated")) -> Under-rated | Y28: =INDEX(Assumptions!$L$22:$L$24,MATCH(H28,Assumptions!$K$22:$K$24,0)) -> 3 | Z28: =EDATE(G28,12*Y28) -> 46479 | AA28: =IF(Z28<Assumptions!$B$4,"Overdue",IF(Z28<=Assumptions!$B$4+60,"Due within 60 days","Current")) -> Current | AB28: =MAX(0,Assumptions!$B$4-Z28) -> 0 | AC28: =IF(COUNTIF($B$2:$B$41,B28)>1,"Duplicate","OK") -> OK | AD28: =IF(G28<F28,"Review before onboarding",IF(F28>Assumptions!$B$4,"Future onboarding","OK")) -> OK | AE28: =(P28>0)+(Q28>0)+(X28<>"OK")+(AC28<>"OK")+(AD28<>"OK")+(AA28="Overdue") -> 1
A29: C028 | B29: Zurich Wealth Advisory AG | C29: Corporate | D29: Switzerland | E29: Consulting | F29: 43914 | G29: 45561 | H29: Low | I29: Y | J29: Y | K29: Y | L29: Y | M29: Clear | N29: N | O29: 0 | P29: =4-COUNTIF(I29:L29,"Y") -> 0 | Q29: =COUNTBLANK(A29:O29) -> 0 | R29: =IF(P29>0,"Incomplete - Docs",IF(M29<>"Clear","Incomplete - Screening","Complete")) -> Complete | S29: =IFERROR(INDEX(Assumptions!$B$22:$B$39,MATCH(D29,Assumptions!$A$22:$A$39,0)),0) -> 0 | T29: =IFERROR(INDEX(Assumptions!$F$22:$F$35,MATCH(E29,Assumptions!$E$22:$E$35,0)),0) -> 1 | U29: =IFERROR(INDEX(Assumptions!$I$22:$I$25,MATCH(C29,Assumptions!$H$22:$H$25,0)),0) -> 0 | V29: =S29+T29+U29+IF(N29="Y",Assumptions!$B$16,0) -> 1 | W29: =IF(V29>=Assumptions!$B$14,"High",IF(V29>=Assumptions!$B$15,"Medium","Low")) -> Low | X29: =IF(H29=W29,"OK",IF(((H29="High")*3+(H29="Medium")*2+(H29="Low"))<((W29="High")*3+(W29="Medium")*2+(W29="Low")),"Under-rated","Over-rated")) -> OK | Y29: =INDEX(Assumptions!$L$22:$L$24,MATCH(H29,Assumptions!$K$22:$K$24,0)) -> 3 | Z29: =EDATE(G29,12*Y29) -> 46656 | AA29: =IF(Z29<Assumptions!$B$4,"Overdue",IF(Z29<=Assumptions!$B$4+60,"Due within 60 days","Current")) -> Current | AB29: =MAX(0,Assumptions!$B$4-Z29) -> 0 | AC29: =IF(COUNTIF($B$2:$B$41,B29)>1,"Duplicate","OK") -> OK | AD29: =IF(G29<F29,"Review before onboarding",IF(F29>Assumptions!$B$4,"Future onboarding","OK")) -> OK | AE29: =(P29>0)+(Q29>0)+(X29<>"OK")+(AC29<>"OK")+(AD29<>"OK")+(AA29="Overdue") -> 0
A30: C029 | B30: The Halvorsen Family Trust | C30: Trust | D30: Switzerland | E30: Real Estate | F30: 45322 | G30: 46134 | H30: High | I30: Y | J30: Y | K30: Y | L30: Y | M30: Clear | N30: Y | O30: 0 | P30: =4-COUNTIF(I30:L30,"Y") -> 0 | Q30: =COUNTBLANK(A30:O30) -> 0 | R30: =IF(P30>0,"Incomplete - Docs",IF(M30<>"Clear","Incomplete - Screening","Complete")) -> Complete | S30: =IFERROR(INDEX(Assumptions!$B$22:$B$39,MATCH(D30,Assumptions!$A$22:$A$39,0)),0) -> 0 | T30: =IFERROR(INDEX(Assumptions!$F$22:$F$35,MATCH(E30,Assumptions!$E$22:$E$35,0)),0) -> 2 | U30: =IFERROR(INDEX(Assumptions!$I$22:$I$25,MATCH(C30,Assumptions!$H$22:$H$25,0)),0) -> 1 | V30: =S30+T30+U30+IF(N30="Y",Assumptions!$B$16,0) -> 6 | W30: =IF(V30>=Assumptions!$B$14,"High",IF(V30>=Assumptions!$B$15,"Medium","Low")) -> High | X30: =IF(H30=W30,"OK",IF(((H30="High")*3+(H30="Medium")*2+(H30="Low"))<((W30="High")*3+(W30="Medium")*2+(W30="Low")),"Under-rated","Over-rated")) -> OK | Y30: =INDEX(Assumptions!$L$22:$L$24,MATCH(H30,Assumptions!$K$22:$K$24,0)) -> 1 | Z30: =EDATE(G30,12*Y30) -> 46499 | AA30: =IF(Z30<Assumptions!$B$4,"Overdue",IF(Z30<=Assumptions!$B$4+60,"Due within 60 days","Current")) -> Current | AB30: =MAX(0,Assumptions!$B$4-Z30) -> 0 | AC30: =IF(COUNTIF($B$2:$B$41,B30)>1,"Duplicate","OK") -> OK | AD30: =IF(G30<F30,"Review before onboarding",IF(F30>Assumptions!$B$4,"Future onboarding","OK")) -> OK | AE30: =(P30>0)+(Q30>0)+(X30<>"OK")+(AC30<>"OK")+(AD30<>"OK")+(AA30="Overdue") -> 0
A31: C030 | B31: Delta Cloud Systems Pvt Ltd | C31: Corporate | D31: India | E31: Software/IT | F31: 44621 | G31: 46256 | H31: Low | I31: Y | J31: Y | K31: Y | L31: Y | M31: Clear | N31: N | O31: 0 | P31: =4-COUNTIF(I31:L31,"Y") -> 0 | Q31: =COUNTBLANK(A31:O31) -> 0 | R31: =IF(P31>0,"Incomplete - Docs",IF(M31<>"Clear","Incomplete - Screening","Complete")) -> Complete | S31: =IFERROR(INDEX(Assumptions!$B$22:$B$39,MATCH(D31,Assumptions!$A$22:$A$39,0)),0) -> 0 | T31: =IFERROR(INDEX(Assumptions!$F$22:$F$35,MATCH(E31,Assumptions!$E$22:$E$35,0)),0) -> 0 | U31: =IFERROR(INDEX(Assumptions!$I$22:$I$25,MATCH(C31,Assumptions!$H$22:$H$25,0)),0) -> 0 | V31: =S31+T31+U31+IF(N31="Y",Assumptions!$B$16,0) -> 0 | W31: =IF(V31>=Assumptions!$B$14,"High",IF(V31>=Assumptions!$B$15,"Medium","Low")) -> Low | X31: =IF(H31=W31,"OK",IF(((H31="High")*3+(H31="Medium")*2+(H31="Low"))<((W31="High")*3+(W31="Medium")*2+(W31="Low")),"Under-rated","Over-rated")) -> OK | Y31: =INDEX(Assumptions!$L$22:$L$24,MATCH(H31,Assumptions!$K$22:$K$24,0)) -> 3 | Z31: =EDATE(G31,12*Y31) -> 47352 | AA31: =IF(Z31<Assumptions!$B$4,"Overdue",IF(Z31<=Assumptions!$B$4+60,"Due within 60 days","Current")) -> Current | AB31: =MAX(0,Assumptions!$B$4-Z31) -> 0 | AC31: =IF(COUNTIF($B$2:$B$41,B31)>1,"Duplicate","OK") -> OK | AD31: =IF(G31<F31,"Review before onboarding",IF(F31>Assumptions!$B$4,"Future onboarding","OK")) -> OK | AE31: =(P31>0)+(Q31>0)+(X31<>"OK")+(AC31<>"OK")+(AD31<>"OK")+(AA31="Overdue") -> 0
A32: C031 | B32: Meridian Textile Exports Pvt Ltd | C32: Corporate | D32: India | E32: Import/Export Trading | F32: 44980 | G32: 45904 | H32: Low | I32: Y | J32: Y | K32: Y | L32: Y | M32: Clear | N32: N | O32: 0 | P32: =4-COUNTIF(I32:L32,"Y") -> 0 | Q32: =COUNTBLANK(A32:O32) -> 0 | R32: =IF(P32>0,"Incomplete - Docs",IF(M32<>"Clear","Incomplete - Screening","Complete")) -> Complete | S32: =IFERROR(INDEX(Assumptions!$B$22:$B$39,MATCH(D32,Assumptions!$A$22:$A$39,0)),0) -> 0 | T32: =IFERROR(INDEX(Assumptions!$F$22:$F$35,MATCH(E32,Assumptions!$E$22:$E$35,0)),0) -> 2 | U32: =IFERROR(INDEX(Assumptions!$I$22:$I$25,MATCH(C32,Assumptions!$H$22:$H$25,0)),0) -> 0 | V32: =S32+T32+U32+IF(N32="Y",Assumptions!$B$16,0) -> 2 | W32: =IF(V32>=Assumptions!$B$14,"High",IF(V32>=Assumptions!$B$15,"Medium","Low")) -> Low | X32: =IF(H32=W32,"OK",IF(((H32="High")*3+(H32="Medium")*2+(H32="Low"))<((W32="High")*3+(W32="Medium")*2+(W32="Low")),"Under-rated","Over-rated")) -> OK | Y32: =INDEX(Assumptions!$L$22:$L$24,MATCH(H32,Assumptions!$K$22:$K$24,0)) -> 3 | Z32: =EDATE(G32,12*Y32) -> 47000 | AA32: =IF(Z32<Assumptions!$B$4,"Overdue",IF(Z32<=Assumptions!$B$4+60,"Due within 60 days","Current")) -> Current | AB32: =MAX(0,Assumptions!$B$4-Z32) -> 0 | AC32: =IF(COUNTIF($B$2:$B$41,B32)>1,"Duplicate","OK") -> Duplicate | AD32: =IF(G32<F32,"Review before onboarding",IF(F32>Assumptions!$B$4,"Future onboarding","OK")) -> OK | AE32: =(P32>0)+(Q32>0)+(X32<>"OK")+(AC32<>"OK")+(AD32<>"OK")+(AA32="Overdue") -> 1
A33: C032 | B33: Anatolia Steel Works AS | C33: Corporate | D33: Turkey | E33: Manufacturing | F33: 44034 | G33: 45078 | H33: Low | I33: Y | J33: Y | K33: Y | L33: Y | M33: Clear | N33: N | O33: 0 | P33: =4-COUNTIF(I33:L33,"Y") -> 0 | Q33: =COUNTBLANK(A33:O33) -> 0 | R33: =IF(P33>0,"Incomplete - Docs",IF(M33<>"Clear","Incomplete - Screening","Complete")) -> Complete | S33: =IFERROR(INDEX(Assumptions!$B$22:$B$39,MATCH(D33,Assumptions!$A$22:$A$39,0)),0) -> 1 | T33: =IFERROR(INDEX(Assumptions!$F$22:$F$35,MATCH(E33,Assumptions!$E$22:$E$35,0)),0) -> 0 | U33: =IFERROR(INDEX(Assumptions!$I$22:$I$25,MATCH(C33,Assumptions!$H$22:$H$25,0)),0) -> 0 | V33: =S33+T33+U33+IF(N33="Y",Assumptions!$B$16,0) -> 1 | W33: =IF(V33>=Assumptions!$B$14,"High",IF(V33>=Assumptions!$B$15,"Medium","Low")) -> Low | X33: =IF(H33=W33,"OK",IF(((H33="High")*3+(H33="Medium")*2+(H33="Low"))<((W33="High")*3+(W33="Medium")*2+(W33="Low")),"Under-rated","Over-rated")) -> OK | Y33: =INDEX(Assumptions!$L$22:$L$24,MATCH(H33,Assumptions!$K$22:$K$24,0)) -> 3 | Z33: =EDATE(G33,12*Y33) -> 46174 | AA33: =IF(Z33<Assumptions!$B$4,"Overdue",IF(Z33<=Assumptions!$B$4+60,"Due within 60 days","Current")) -> Overdue | AB33: =MAX(0,Assumptions!$B$4-Z33) -> 147 | AC33: =IF(COUNTIF($B$2:$B$41,B33)>1,"Duplicate","OK") -> OK | AD33: =IF(G33<F33,"Review before onboarding",IF(F33>Assumptions!$B$4,"Future onboarding","OK")) -> OK | AE33: =(P33>0)+(Q33>0)+(X33<>"OK")+(AC33<>"OK")+(AD33<>"OK")+(AA33="Overdue") -> 1
A34: C033 | B34: Lakeview Medical Supplies Inc | C34: Corporate | D34: Canada | E34: Healthcare | F34: 45193 | G34: 46189 | H34: Low | I34: Y | J34: Y | K34: N | L34: Y | M34: Clear | N34: N | O34: 0 | P34: =4-COUNTIF(I34:L34,"Y") -> 1 | Q34: =COUNTBLANK(A34:O34) -> 0 | R34: =IF(P34>0,"Incomplete - Docs",IF(M34<>"Clear","Incomplete - Screening","Complete")) -> Incomplete - Docs | S34: =IFERROR(INDEX(Assumptions!$B$22:$B$39,MATCH(D34,Assumptions!$A$22:$A$39,0)),0) -> 0 | T34: =IFERROR(INDEX(Assumptions!$F$22:$F$35,MATCH(E34,Assumptions!$E$22:$E$35,0)),0) -> 0 | U34: =IFERROR(INDEX(Assumptions!$I$22:$I$25,MATCH(C34,Assumptions!$H$22:$H$25,0)),0) -> 0 | V34: =S34+T34+U34+IF(N34="Y",Assumptions!$B$16,0) -> 0 | W34: =IF(V34>=Assumptions!$B$14,"High",IF(V34>=Assumptions!$B$15,"Medium","Low")) -> Low | X34: =IF(H34=W34,"OK",IF(((H34="High")*3+(H34="Medium")*2+(H34="Low"))<((W34="High")*3+(W34="Medium")*2+(W34="Low")),"Under-rated","Over-rated")) -> OK | Y34: =INDEX(Assumptions!$L$22:$L$24,MATCH(H34,Assumptions!$K$22:$K$24,0)) -> 3 | Z34: =EDATE(G34,12*Y34) -> 47285 | AA34: =IF(Z34<Assumptions!$B$4,"Overdue",IF(Z34<=Assumptions!$B$4+60,"Due within 60 days","Current")) -> Current | AB34: =MAX(0,Assumptions!$B$4-Z34) -> 0 | AC34: =IF(COUNTIF($B$2:$B$41,B34)>1,"Duplicate","OK") -> OK | AD34: =IF(G34<F34,"Review before onboarding",IF(F34>Assumptions!$B$4,"Future onboarding","OK")) -> OK | AE34: =(P34>0)+(Q34>0)+(X34<>"OK")+(AC34<>"OK")+(AD34<>"OK")+(AA34="Overdue") -> 1
A35: C034 | B35: Skyline Hospitality Group Ltd | C35: Corporate | D35: India | E35: Restaurants & Hospitality | F35: 43990 | G35: 45369 | H35: Low | I35: Y | J35: Y | K35: Y | L35: Y | M35: Clear | N35: N | O35: 25000 | P35: =4-COUNTIF(I35:L35,"Y") -> 0 | Q35: =COUNTBLANK(A35:O35) -> 0 | R35: =IF(P35>0,"Incomplete - Docs",IF(M35<>"Clear","Incomplete - Screening","Complete")) -> Complete | S35: =IFERROR(INDEX(Assumptions!$B$22:$B$39,MATCH(D35,Assumptions!$A$22:$A$39,0)),0) -> 0 | T35: =IFERROR(INDEX(Assumptions!$F$22:$F$35,MATCH(E35,Assumptions!$E$22:$E$35,0)),0) -> 2 | U35: =IFERROR(INDEX(Assumptions!$I$22:$I$25,MATCH(C35,Assumptions!$H$22:$H$25,0)),0) -> 0 | V35: =S35+T35+U35+IF(N35="Y",Assumptions!$B$16,0) -> 2 | W35: =IF(V35>=Assumptions!$B$14,"High",IF(V35>=Assumptions!$B$15,"Medium","Low")) -> Low | X35: =IF(H35=W35,"OK",IF(((H35="High")*3+(H35="Medium")*2+(H35="Low"))<((W35="High")*3+(W35="Medium")*2+(W35="Low")),"Under-rated","Over-rated")) -> OK | Y35: =INDEX(Assumptions!$L$22:$L$24,MATCH(H35,Assumptions!$K$22:$K$24,0)) -> 3 | Z35: =EDATE(G35,12*Y35) -> 46464 | AA35: =IF(Z35<Assumptions!$B$4,"Overdue",IF(Z35<=Assumptions!$B$4+60,"Due within 60 days","Current")) -> Current | AB35: =MAX(0,Assumptions!$B$4-Z35) -> 0 | AC35: =IF(COUNTIF($B$2:$B$41,B35)>1,"Duplicate","OK") -> OK | AD35: =IF(G35<F35,"Review before onboarding",IF(F35>Assumptions!$B$4,"Future onboarding","OK")) -> OK | AE35: =(P35>0)+(Q35>0)+(X35<>"OK")+(AC35<>"OK")+(AD35<>"OK")+(AA35="Overdue") -> 0
A36: C035 | B36: Granite Peak Mining Services Ltd | C36: Corporate | D36: Canada | E36: Logistics & Shipping | F36: 43855 | G36: 45055 | H36: Low | I36: Y | J36: Y | K36: Y | L36: Y | M36: Clear | N36: N | O36: 0 | P36: =4-COUNTIF(I36:L36,"Y") -> 0 | Q36: =COUNTBLANK(A36:O36) -> 0 | R36: =IF(P36>0,"Incomplete - Docs",IF(M36<>"Clear","Incomplete - Screening","Complete")) -> Complete | S36: =IFERROR(INDEX(Assumptions!$B$22:$B$39,MATCH(D36,Assumptions!$A$22:$A$39,0)),0) -> 0 | T36: =IFERROR(INDEX(Assumptions!$F$22:$F$35,MATCH(E36,Assumptions!$E$22:$E$35,0)),0) -> 1 | U36: =IFERROR(INDEX(Assumptions!$I$22:$I$25,MATCH(C36,Assumptions!$H$22:$H$25,0)),0) -> 0 | V36: =S36+T36+U36+IF(N36="Y",Assumptions!$B$16,0) -> 1 | W36: =IF(V36>=Assumptions!$B$14,"High",IF(V36>=Assumptions!$B$15,"Medium","Low")) -> Low | X36: =IF(H36=W36,"OK",IF(((H36="High")*3+(H36="Medium")*2+(H36="Low"))<((W36="High")*3+(W36="Medium")*2+(W36="Low")),"Under-rated","Over-rated")) -> OK | Y36: =INDEX(Assumptions!$L$22:$L$24,MATCH(H36,Assumptions!$K$22:$K$24,0)) -> 3 | Z36: =EDATE(G36,12*Y36) -> 46151 | AA36: =IF(Z36<Assumptions!$B$4,"Overdue",IF(Z36<=Assumptions!$B$4+60,"Due within 60 days","Current")) -> Overdue | AB36: =MAX(0,Assumptions!$B$4-Z36) -> 170 | AC36: =IF(COUNTIF($B$2:$B$41,B36)>1,"Duplicate","OK") -> OK | AD36: =IF(G36<F36,"Review before onboarding",IF(F36>Assumptions!$B$4,"Future onboarding","OK")) -> OK | AE36: =(P36>0)+(Q36>0)+(X36<>"OK")+(AC36<>"OK")+(AD36<>"OK")+(AA36="Overdue") -> 1
A37: C036 | B37: Baltic Star Shipping Ltd | C37: Corporate | D37: Cyprus | E37: Logistics & Shipping | F37: 44975 | G37: 45393 | H37: Low | I37: Y | J37: Y | K37: Y | L37: Y | M37: Potential Match | N37: N | O37: 0 | P37: =4-COUNTIF(I37:L37,"Y") -> 0 | Q37: =COUNTBLANK(A37:O37) -> 0 | R37: =IF(P37>0,"Incomplete - Docs",IF(M37<>"Clear","Incomplete - Screening","Complete")) -> Incomplete - Screening | S37: =IFERROR(INDEX(Assumptions!$B$22:$B$39,MATCH(D37,Assumptions!$A$22:$A$39,0)),0) -> 1 | T37: =IFERROR(INDEX(Assumptions!$F$22:$F$35,MATCH(E37,Assumptions!$E$22:$E$35,0)),0) -> 1 | U37: =IFERROR(INDEX(Assumptions!$I$22:$I$25,MATCH(C37,Assumptions!$H$22:$H$25,0)),0) -> 0 | V37: =S37+T37+U37+IF(N37="Y",Assumptions!$B$16,0) -> 2 | W37: =IF(V37>=Assumptions!$B$14,"High",IF(V37>=Assumptions!$B$15,"Medium","Low")) -> Low | X37: =IF(H37=W37,"OK",IF(((H37="High")*3+(H37="Medium")*2+(H37="Low"))<((W37="High")*3+(W37="Medium")*2+(W37="Low")),"Under-rated","Over-rated")) -> OK | Y37: =INDEX(Assumptions!$L$22:$L$24,MATCH(H37,Assumptions!$K$22:$K$24,0)) -> 3 | Z37: =EDATE(G37,12*Y37) -> 46488 | AA37: =IF(Z37<Assumptions!$B$4,"Overdue",IF(Z37<=Assumptions!$B$4+60,"Due within 60 days","Current")) -> Current | AB37: =MAX(0,Assumptions!$B$4-Z37) -> 0 | AC37: =IF(COUNTIF($B$2:$B$41,B37)>1,"Duplicate","OK") -> OK | AD37: =IF(G37<F37,"Review before onboarding",IF(F37>Assumptions!$B$4,"Future onboarding","OK")) -> OK | AE37: =(P37>0)+(Q37>0)+(X37<>"OK")+(AC37<>"OK")+(AD37<>"OK")+(AA37="Overdue") -> 0
A38: C037 | B38: Emerald Isle Software Ltd | C38: Corporate | D38: United Kingdom | E38: Software/IT | F38: 44629 | G38: 45846 | H38: Low | I38: Y | J38: Y | K38: Y | L38: Y | M38: Clear | N38: N | O38: 0 | P38: =4-COUNTIF(I38:L38,"Y") -> 0 | Q38: =COUNTBLANK(A38:O38) -> 0 | R38: =IF(P38>0,"Incomplete - Docs",IF(M38<>"Clear","Incomplete - Screening","Complete")) -> Complete | S38: =IFERROR(INDEX(Assumptions!$B$22:$B$39,MATCH(D38,Assumptions!$A$22:$A$39,0)),0) -> 0 | T38: =IFERROR(INDEX(Assumptions!$F$22:$F$35,MATCH(E38,Assumptions!$E$22:$E$35,0)),0) -> 0 | U38: =IFERROR(INDEX(Assumptions!$I$22:$I$25,MATCH(C38,Assumptions!$H$22:$H$25,0)),0) -> 0 | V38: =S38+T38+U38+IF(N38="Y",Assumptions!$B$16,0) -> 0 | W38: =IF(V38>=Assumptions!$B$14,"High",IF(V38>=Assumptions!$B$15,"Medium","Low")) -> Low | X38: =IF(H38=W38,"OK",IF(((H38="High")*3+(H38="Medium")*2+(H38="Low"))<((W38="High")*3+(W38="Medium")*2+(W38="Low")),"Under-rated","Over-rated")) -> OK | Y38: =INDEX(Assumptions!$L$22:$L$24,MATCH(H38,Assumptions!$K$22:$K$24,0)) -> 3 | Z38: =EDATE(G38,12*Y38) -> 46942 | AA38: =IF(Z38<Assumptions!$B$4,"Overdue",IF(Z38<=Assumptions!$B$4+60,"Due within 60 days","Current")) -> Current | AB38: =MAX(0,Assumptions!$B$4-Z38) -> 0 | AC38: =IF(COUNTIF($B$2:$B$41,B38)>1,"Duplicate","OK") -> OK | AD38: =IF(G38<F38,"Review before onboarding",IF(F38>Assumptions!$B$4,"Future onboarding","OK")) -> OK | AE38: =(P38>0)+(Q38>0)+(X38<>"OK")+(AC38<>"OK")+(AD38<>"OK")+(AA38="Overdue") -> 0
A39: C038 | B39: Zenith Wellness Clinics Pvt Ltd | C39: Corporate | D39: India | E39: Healthcare | F39: 46296 | G39: 46296 | H39: Low | I39: N | J39: N | L39: N | M39: Not Done | N39: N | O39: 0 | P39: =4-COUNTIF(I39:L39,"Y") -> 4 | Q39: =COUNTBLANK(A39:O39) -> 1 | R39: =IF(P39>0,"Incomplete - Docs",IF(M39<>"Clear","Incomplete - Screening","Complete")) -> Incomplete - Docs | S39: =IFERROR(INDEX(Assumptions!$B$22:$B$39,MATCH(D39,Assumptions!$A$22:$A$39,0)),0) -> 0 | T39: =IFERROR(INDEX(Assumptions!$F$22:$F$35,MATCH(E39,Assumptions!$E$22:$E$35,0)),0) -> 0 | U39: =IFERROR(INDEX(Assumptions!$I$22:$I$25,MATCH(C39,Assumptions!$H$22:$H$25,0)),0) -> 0 | V39: =S39+T39+U39+IF(N39="Y",Assumptions!$B$16,0) -> 0 | W39: =IF(V39>=Assumptions!$B$14,"High",IF(V39>=Assumptions!$B$15,"Medium","Low")) -> Low | X39: =IF(H39=W39,"OK",IF(((H39="High")*3+(H39="Medium")*2+(H39="Low"))<((W39="High")*3+(W39="Medium")*2+(W39="Low")),"Under-rated","Over-rated")) -> OK | Y39: =INDEX(Assumptions!$L$22:$L$24,MATCH(H39,Assumptions!$K$22:$K$24,0)) -> 3 | Z39: =EDATE(G39,12*Y39) -> 47392 | AA39: =IF(Z39<Assumptions!$B$4,"Overdue",IF(Z39<=Assumptions!$B$4+60,"Due within 60 days","Current")) -> Current | AB39: =MAX(0,Assumptions!$B$4-Z39) -> 0 | AC39: =IF(COUNTIF($B$2:$B$41,B39)>1,"Duplicate","OK") -> OK | AD39: =IF(G39<F39,"Review before onboarding",IF(F39>Assumptions!$B$4,"Future onboarding","OK")) -> OK | AE39: =(P39>0)+(Q39>0)+(X39<>"OK")+(AC39<>"OK")+(AD39<>"OK")+(AA39="Overdue") -> 2
A40: C039 | B40: Ridgeway Used Cars Ltd | C40: Corporate | D40: United Kingdom | E40: Used Vehicle Dealers | F40: 43744 | G40: 45460 | H40: Low | I40: Y | J40: Y | K40: Y | L40: Y | M40: Clear | N40: N | O40: 35000 | P40: =4-COUNTIF(I40:L40,"Y") -> 0 | Q40: =COUNTBLANK(A40:O40) -> 0 | R40: =IF(P40>0,"Incomplete - Docs",IF(M40<>"Clear","Incomplete - Screening","Complete")) -> Complete | S40: =IFERROR(INDEX(Assumptions!$B$22:$B$39,MATCH(D40,Assumptions!$A$22:$A$39,0)),0) -> 0 | T40: =IFERROR(INDEX(Assumptions!$F$22:$F$35,MATCH(E40,Assumptions!$E$22:$E$35,0)),0) -> 2 | U40: =IFERROR(INDEX(Assumptions!$I$22:$I$25,MATCH(C40,Assumptions!$H$22:$H$25,0)),0) -> 0 | V40: =S40+T40+U40+IF(N40="Y",Assumptions!$B$16,0) -> 2 | W40: =IF(V40>=Assumptions!$B$14,"High",IF(V40>=Assumptions!$B$15,"Medium","Low")) -> Low | X40: =IF(H40=W40,"OK",IF(((H40="High")*3+(H40="Medium")*2+(H40="Low"))<((W40="High")*3+(W40="Medium")*2+(W40="Low")),"Under-rated","Over-rated")) -> OK | Y40: =INDEX(Assumptions!$L$22:$L$24,MATCH(H40,Assumptions!$K$22:$K$24,0)) -> 3 | Z40: =EDATE(G40,12*Y40) -> 46555 | AA40: =IF(Z40<Assumptions!$B$4,"Overdue",IF(Z40<=Assumptions!$B$4+60,"Due within 60 days","Current")) -> Current | AB40: =MAX(0,Assumptions!$B$4-Z40) -> 0 | AC40: =IF(COUNTIF($B$2:$B$41,B40)>1,"Duplicate","OK") -> OK | AD40: =IF(G40<F40,"Review before onboarding",IF(F40>Assumptions!$B$4,"Future onboarding","OK")) -> OK | AE40: =(P40>0)+(Q40>0)+(X40<>"OK")+(AC40<>"OK")+(AD40<>"OK")+(AA40="Overdue") -> 0
A41: C040 | B41: Orchid Textiles Pvt Ltd | C41: Corporate | D41: India | E41: Manufacturing | F41: 43985 | G41: 45394 | H41: Low | I41: Y | J41: Y | K41: Y | L41: Y | M41: Clear | N41: N | O41: 0 | P41: =4-COUNTIF(I41:L41,"Y") -> 0 | Q41: =COUNTBLANK(A41:O41) -> 0 | R41: =IF(P41>0,"Incomplete - Docs",IF(M41<>"Clear","Incomplete - Screening","Complete")) -> Complete | S41: =IFERROR(INDEX(Assumptions!$B$22:$B$39,MATCH(D41,Assumptions!$A$22:$A$39,0)),0) -> 0 | T41: =IFERROR(INDEX(Assumptions!$F$22:$F$35,MATCH(E41,Assumptions!$E$22:$E$35,0)),0) -> 0 | U41: =IFERROR(INDEX(Assumptions!$I$22:$I$25,MATCH(C41,Assumptions!$H$22:$H$25,0)),0) -> 0 | V41: =S41+T41+U41+IF(N41="Y",Assumptions!$B$16,0) -> 0 | W41: =IF(V41>=Assumptions!$B$14,"High",IF(V41>=Assumptions!$B$15,"Medium","Low")) -> Low | X41: =IF(H41=W41,"OK",IF(((H41="High")*3+(H41="Medium")*2+(H41="Low"))<((W41="High")*3+(W41="Medium")*2+(W41="Low")),"Under-rated","Over-rated")) -> OK | Y41: =INDEX(Assumptions!$L$22:$L$24,MATCH(H41,Assumptions!$K$22:$K$24,0)) -> 3 | Z41: =EDATE(G41,12*Y41) -> 46489 | AA41: =IF(Z41<Assumptions!$B$4,"Overdue",IF(Z41<=Assumptions!$B$4+60,"Due within 60 days","Current")) -> Current | AB41: =MAX(0,Assumptions!$B$4-Z41) -> 0 | AC41: =IF(COUNTIF($B$2:$B$41,B41)>1,"Duplicate","OK") -> OK | AD41: =IF(G41<F41,"Review before onboarding",IF(F41>Assumptions!$B$4,"Future onboarding","OK")) -> OK | AE41: =(P41>0)+(Q41>0)+(X41<>"OK")+(AC41<>"OK")+(AD41<>"OK")+(AA41="Overdue") -> 0

Sheet Transactions
A1: Txn ID | B1: Txn Date | C1: Client ID | D1: Txn Type | E1: Amount (USD) | F1: Counterparty Country | G1: Narrative | H1: Client Name | I1: Cash? (Y/N) | J1: Direction | K1: Near-Threshold Cash? | L1: Counterparty Country Score | M1: Daily Cash Total (client / day / direction) | N1: CTR Trigger | O1: Client KYC File Status
A2: T0001 | B2: 46266 | C2: C003 | D2: Wire In | E2: 17700 | F2: Canada | G2: Customer receipt | H2: =IFERROR(INDEX(Client_Master!$B$2:$B$41,MATCH(C2,Client_Master!$A$2:$A$41,0)),"UNKNOWN CLIENT") -> Lotus Healthcare Systems Ltd | I2: =IF(LEFT(D2,4)="Cash","Y","N") -> N | J2: =IF(OR(D2="Cash Deposit",D2="Wire In"),"In","Out") -> In | K2: =IF(AND(I2="Y",E2>=Assumptions!$B$6,E2<=Assumptions!$B$5),"Y","N") -> N | L2: =IFERROR(INDEX(Assumptions!$B$22:$B$39,MATCH(F2,Assumptions!$A$22:$A$39,0)),0) -> 0 | M2: =IF(I2="Y",SUMIFS($E$2:$E$114,$C$2:$C$114,C2,$B$2:$B$114,B2,$I$2:$I$114,"Y",$J$2:$J$114,J2),0) -> 0 | N2: =IF(M2>Assumptions!$B$5,"CTR","") | O2: =IFERROR(INDEX(Client_Master!$R$2:$R$41,MATCH(C2,Client_Master!$A$2:$A$41,0)),"No KYC record") -> Complete
A3: T0002 | B3: 46266 | C3: C023 | D3: Wire Out | E3: 78700 | F3: Germany | G3: Trade settlement | H3: =IFERROR(INDEX(Client_Master!$B$2:$B$41,MATCH(C3,Client_Master!$A$2:$A$41,0)),"UNKNOWN CLIENT") -> Cedar Hill Property Holdings Ltd | I3: =IF(LEFT(D3,4)="Cash","Y","N") -> N | J3: =IF(OR(D3="Cash Deposit",D3="Wire In"),"In","Out") -> Out | K3: =IF(AND(I3="Y",E3>=Assumptions!$B$6,E3<=Assumptions!$B$5),"Y","N") -> N | L3: =IFERROR(INDEX(Assumptions!$B$22:$B$39,MATCH(F3,Assumptions!$A$22:$A$39,0)),0) -> 0 | M3: =IF(I3="Y",SUMIFS($E$2:$E$114,$C$2:$C$114,C3,$B$2:$B$114,B3,$I$2:$I$114,"Y",$J$2:$J$114,J3),0) -> 0 | N3: =IF(M3>Assumptions!$B$5,"CTR","") | O3: =IFERROR(INDEX(Client_Master!$R$2:$R$41,MATCH(C3,Client_Master!$A$2:$A$41,0)),"No KYC record") -> Complete
A4: T0003 | B4: 46267 | C4: C011 | D4: Wire In | E4: 48400 | F4: Switzerland | G4: Customer receipt | H4: =IFERROR(INDEX(Client_Master!$B$2:$B$41,MATCH(C4,Client_Master!$A$2:$A$41,0)),"UNKNOWN CLIENT") -> Coral Reef Gaming Ltd | I4: =IF(LEFT(D4,4)="Cash","Y","N") -> N | J4: =IF(OR(D4="Cash Deposit",D4="Wire In"),"In","Out") -> In | K4: =IF(AND(I4="Y",E4>=Assumptions!$B$6,E4<=Assumptions!$B$5),"Y","N") -> N | L4: =IFERROR(INDEX(Assumptions!$B$22:$B$39,MATCH(F4,Assumptions!$A$22:$A$39,0)),0) -> 0 | M4: =IF(I4="Y",SUMIFS($E$2:$E$114,$C$2:$C$114,C4,$B$2:$B$114,B4,$I$2:$I$114,"Y",$J$2:$J$114,J4),0) -> 0 | N4: =IF(M4>Assumptions!$B$5,"CTR","") | O4: =IFERROR(INDEX(Client_Master!$R$2:$R$41,MATCH(C4,Client_Master!$A$2:$A$41,0)),"No KYC record") -> Complete
A5: T0004 | B5: 46267 | C5: C030 | D5: Wire Out | E5: 54100 | F5: Switzerland | G5: Trade settlement | H5: =IFERROR(INDEX(Client_Master!$B$2:$B$41,MATCH(C5,Client_Master!$A$2:$A$41,0)),"UNKNOWN CLIENT") -> Delta Cloud Systems Pvt Ltd | I5: =IF(LEFT(D5,4)="Cash","Y","N") -> N | J5: =IF(OR(D5="Cash Deposit",D5="Wire In"),"In","Out") -> Out | K5: =IF(AND(I5="Y",E5>=Assumptions!$B$6,E5<=Assumptions!$B$5),"Y","N") -> N | L5: =IFERROR(INDEX(Assumptions!$B$22:$B$39,MATCH(F5,Assumptions!$A$22:$A$39,0)),0) -> 0 | M5: =IF(I5="Y",SUMIFS($E$2:$E$114,$C$2:$C$114,C5,$B$2:$B$114,B5,$I$2:$I$114,"Y",$J$2:$J$114,J5),0) -> 0 | N5: =IF(M5>Assumptions!$B$5,"CTR","") | O5: =IFERROR(INDEX(Client_Master!$R$2:$R$41,MATCH(C5,Client_Master!$A$2:$A$41,0)),"No KYC record") -> Complete
A6: T0005 | B6: 46267 | C6: C032 | D6: Wire In | E6: 28500 | F6: Canada | G6: Customer receipt | H6: =IFERROR(INDEX(Client_Master!$B$2:$B$41,MATCH(C6,Client_Master!$A$2:$A$41,0)),"UNKNOWN CLIENT") -> Anatolia Steel Works AS | I6: =IF(LEFT(D6,4)="Cash","Y","N") -> N | J6: =IF(OR(D6="Cash Deposit",D6="Wire In"),"In","Out") -> In | K6: =IF(AND(I6="Y",E6>=Assumptions!$B$6,E6<=Assumptions!$B$5),"Y","N") -> N | L6: =IFERROR(INDEX(Assumptions!$B$22:$B$39,MATCH(F6,Assumptions!$A$22:$A$39,0)),0) -> 0 | M6: =IF(I6="Y",SUMIFS($E$2:$E$114,$C$2:$C$114,C6,$B$2:$B$114,B6,$I$2:$I$114,"Y",$J$2:$J$114,J6),0) -> 0 | N6: =IF(M6>Assumptions!$B$5,"CTR","") | O6: =IFERROR(INDEX(Client_Master!$R$2:$R$41,MATCH(C6,Client_Master!$A$2:$A$41,0)),"No KYC record") -> Complete
A7: T0006 | B7: 46268 | C7: C014 | D7: Wire In | E7: 43400 | F7: Singapore | G7: Customer receipt | H7: =IFERROR(INDEX(Client_Master!$B$2:$B$41,MATCH(C7,Client_Master!$A$2:$A$41,0)),"UNKNOWN CLIENT") -> Maple Leaf Health Clinics Inc | I7: =IF(LEFT(D7,4)="Cash","Y","N") -> N | J7: =IF(OR(D7="Cash Deposit",D7="Wire In"),"In","Out") -> In | K7: =IF(AND(I7="Y",E7>=Assumptions!$B$6,E7<=Assumptions!$B$5),"Y","N") -> N | L7: =IFERROR(INDEX(Assumptions!$B$22:$B$39,MATCH(F7,Assumptions!$A$22:$A$39,0)),0) -> 0 | M7: =IF(I7="Y",SUMIFS($E$2:$E$114,$C$2:$C$114,C7,$B$2:$B$114,B7,$I$2:$I$114,"Y",$J$2:$J$114,J7),0) -> 0 | N7: =IF(M7>Assumptions!$B$5,"CTR","") | O7: =IFERROR(INDEX(Client_Master!$R$2:$R$41,MATCH(C7,Client_Master!$A$2:$A$41,0)),"No KYC record") -> Complete
A8: T0007 | B8: 46268 | C8: C026 | D8: Wire Out | E8: 31900 | F8: Singapore | G8: Trade settlement | H8: =IFERROR(INDEX(Client_Master!$B$2:$B$41,MATCH(C8,Client_Master!$A$2:$A$41,0)),"UNKNOWN CLIENT") -> Palm Bay Casino Resorts | I8: =IF(LEFT(D8,4)="Cash","Y","N") -> N | J8: =IF(OR(D8="Cash Deposit",D8="Wire In"),"In","Out") -> Out | K8: =IF(AND(I8="Y",E8>=Assumptions!$B$6,E8<=Assumptions!$B$5),"Y","N") -> N | L8: =IFERROR(INDEX(Assumptions!$B$22:$B$39,MATCH(F8,Assumptions!$A$22:$A$39,0)),0) -> 0 | M8: =IF(I8="Y",SUMIFS($E$2:$E$114,$C$2:$C$114,C8,$B$2:$B$114,B8,$I$2:$I$114,"Y",$J$2:$J$114,J8),0) -> 0 | N8: =IF(M8>Assumptions!$B$5,"CTR","") | O8: =IFERROR(INDEX(Client_Master!$R$2:$R$41,MATCH(C8,Client_Master!$A$2:$A$41,0)),"No KYC record") -> Complete
A9: T0008 | B9: 46268 | C9: C033 | D9: Wire Out | E9: 34000 | F9: Hong Kong | G9: Trade settlement | H9: =IFERROR(INDEX(Client_Master!$B$2:$B$41,MATCH(C9,Client_Master!$A$2:$A$41,0)),"UNKNOWN CLIENT") -> Lakeview Medical Supplies Inc | I9: =IF(LEFT(D9,4)="Cash","Y","N") -> N | J9: =IF(OR(D9="Cash Deposit",D9="Wire In"),"In","Out") -> Out | K9: =IF(AND(I9="Y",E9>=Assumptions!$B$6,E9<=Assumptions!$B$5),"Y","N") -> N | L9: =IFERROR(INDEX(Assumptions!$B$22:$B$39,MATCH(F9,Assumptions!$A$22:$A$39,0)),0) -> 1 | M9: =IF(I9="Y",SUMIFS($E$2:$E$114,$C$2:$C$114,C9,$B$2:$B$114,B9,$I$2:$I$114,"Y",$J$2:$J$114,J9),0) -> 0 | N9: =IF(M9>Assumptions!$B$5,"CTR","") | O9: =IFERROR(INDEX(Client_Master!$R$2:$R$41,MATCH(C9,Client_Master!$A$2:$A$41,0)),"No KYC record") -> Incomplete - Docs
A10: T0009 | B10: 46269 | C10: C001 | D10: Wire In | E10: 66000 | F10: Japan | G10: Customer receipt | H10: =IFERROR(INDEX(Client_Master!$B$2:$B$41,MATCH(C10,Client_Master!$A$2:$A$41,0)),"UNKNOWN CLIENT") -> Aurora Software Solutions Pvt Ltd | I10: =IF(LEFT(D10,4)="Cash","Y","N") -> N | J10: =IF(OR(D10="Cash Deposit",D10="Wire In"),"In","Out") -> In | K10: =IF(AND(I10="Y",E10>=Assumptions!$B$6,E10<=Assumptions!$B$5),"Y","N") -> N | L10: =IFERROR(INDEX(Assumptions!$B$22:$B$39,MATCH(F10,Assumptions!$A$22:$A$39,0)),0) -> 0 | M10: =IF(I10="Y",SUMIFS($E$2:$E$114,$C$2:$C$114,C10,$B$2:$B$114,B10,$I$2:$I$114,"Y",$J$2:$J$114,J10),0) -> 0 | N10: =IF(M10>Assumptions!$B$5,"CTR","") | O10: =IFERROR(INDEX(Client_Master!$R$2:$R$41,MATCH(C10,Client_Master!$A$2:$A$41,0)),"No KYC record") -> Complete
A11: T0010 | B11: 46269 | C11: C026 | D11: Wire Out | E11: 79700 | F11: Germany | G11: Trade settlement | H11: =IFERROR(INDEX(Client_Master!$B$2:$B$41,MATCH(C11,Client_Master!$A$2:$A$41,0)),"UNKNOWN CLIENT") -> Palm Bay Casino Resorts | I11: =IF(LEFT(D11,4)="Cash","Y","N") -> N | J11: =IF(OR(D11="Cash Deposit",D11="Wire In"),"In","Out") -> Out | K11: =IF(AND(I11="Y",E11>=Assumptions!$B$6,E11<=Assumptions!$B$5),"Y","N") -> N | L11: =IFERROR(INDEX(Assumptions!$B$22:$B$39,MATCH(F11,Assumptions!$A$22:$A$39,0)),0) -> 0 | M11: =IF(I11="Y",SUMIFS($E$2:$E$114,$C$2:$C$114,C11,$B$2:$B$114,B11,$I$2:$I$114,"Y",$J$2:$J$114,J11),0) -> 0 | N11: =IF(M11>Assumptions!$B$5,"CTR","") | O11: =IFERROR(INDEX(Client_Master!$R$2:$R$41,MATCH(C11,Client_Master!$A$2:$A$41,0)),"No KYC record") -> Complete
A12: T0011 | B12: 46272 | C12: C006 | D12: Wire Out | E12: 81800 | F12: Switzerland | G12: Trade settlement | H12: =IFERROR(INDEX(Client_Master!$B$2:$B$41,MATCH(C12,Client_Master!$A$2:$A$41,0)),"UNKNOWN CLIENT") -> Meridian Textile Exports Pvt Ltd | I12: =IF(LEFT(D12,4)="Cash","Y","N") -> N | J12: =IF(OR(D12="Cash Deposit",D12="Wire In"),"In","Out") -> Out | K12: =IF(AND(I12="Y",E12>=Assumptions!$B$6,E12<=Assumptions!$B$5),"Y","N") -> N | L12: =IFERROR(INDEX(Assumptions!$B$22:$B$39,MATCH(F12,Assumptions!$A$22:$A$39,0)),0) -> 0 | M12: =IF(I12="Y",SUMIFS($E$2:$E$114,$C$2:$C$114,C12,$B$2:$B$114,B12,$I$2:$I$114,"Y",$J$2:$J$114,J12),0) -> 0 | N12: =IF(M12>Assumptions!$B$5,"CTR","") | O12: =IFERROR(INDEX(Client_Master!$R$2:$R$41,MATCH(C12,Client_Master!$A$2:$A$41,0)),"No KYC record") -> Complete
A13: T0012 | B13: 46272 | C13: C011 | D13: Wire In | E13: 75900 | F13: Switzerland | G13: Customer receipt | H13: =IFERROR(INDEX(Client_Master!$B$2:$B$41,MATCH(C13,Client_Master!$A$2:$A$41,0)),"UNKNOWN CLIENT") -> Coral Reef Gaming Ltd | I13: =IF(LEFT(D13,4)="Cash","Y","N") -> N | J13: =IF(OR(D13="Cash Deposit",D13="Wire In"),"In","Out") -> In | K13: =IF(AND(I13="Y",E13>=Assumptions!$B$6,E13<=Assumptions!$B$5),"Y","N") -> N | L13: =IFERROR(INDEX(Assumptions!$B$22:$B$39,MATCH(F13,Assumptions!$A$22:$A$39,0)),0) -> 0 | M13: =IF(I13="Y",SUMIFS($E$2:$E$114,$C$2:$C$114,C13,$B$2:$B$114,B13,$I$2:$I$114,"Y",$J$2:$J$114,J13),0) -> 0 | N13: =IF(M13>Assumptions!$B$5,"CTR","") | O13: =IFERROR(INDEX(Client_Master!$R$2:$R$41,MATCH(C13,Client_Master!$A$2:$A$41,0)),"No KYC record") -> Complete
... A114: T0113 | B114: 46318 | C114: C026 | D114: Wire Out | E114: 41200 | F114: United Kingdom | G114: Trade settlement | H114: =IFERROR(INDEX(Client_Master!$B$2:$B$41,MATCH(C114,Client_Master!$A$2:$A$41,0)),"UNKNOWN CLIENT") -> Palm Bay Casino Resorts | I114: =IF(LEFT(D114,4)="Cash","Y","N") -> N | J114: =IF(OR(D114="Cash Deposit",D114="Wire In"),"In","Out") -> Out | K114: =IF(AND(I114="Y",E114>=Assumptions!$B$6,E114<=Assumptions!$B$5),"Y","N") -> N | L114: =IFERROR(INDEX(Assumptions!$B$22:$B$39,MATCH(F114,Assumptions!$A$22:$A$39,0)),0) -> 0 | M114: =IF(I114="Y",SUMIFS($E$2:$E$114,$C$2:$C$114,C114,$B$2:$B$114,B114,$I$2:$I$114,"Y",$J$2:$J$114,J114),0) -> 0 | N114: =IF(M114>Assumptions!$B$5,"CTR","") | O114: =IFERROR(INDEX(Client_Master!$R$2:$R$41,MATCH(C114,Client_Master!$A$2:$A$41,0)),"No KYC record") -> Complete

Sheet CTR_Log
A1: Client ID | B1: Cash Activity Date | C1: Client Name | D1: Cash In (Deposits) | E1: Cash Out (Withdrawals) | F1: CTR Required? | G1: # Cash Txns Aggregated | H1: Filing Deadline | I1: Filing Status | J1: Filed Date | K1: Days to File | L1: Timeliness | M1: Reviewer Notes
A2: C019 | B2: 46273 | C2: =IFERROR(INDEX(Client_Master!$B$2:$B$41,MATCH(A2,Client_Master!$A$2:$A$41,0)),"UNKNOWN CLIENT") -> Metro Fuel & Convenience Stores Inc | D2: =SUMIFS(Transactions!$E$2:$E$114,Transactions!$C$2:$C$114,A2,Transactions!$B$2:$B$114,B2,Transactions!$D$2:$D$114,"Cash Deposit") -> 3100 | E2: =SUMIFS(Transactions!$E$2:$E$114,Transactions!$C$2:$C$114,A2,Transactions!$B$2:$B$114,B2,Transactions!$D$2:$D$114,"Cash Withdrawal") -> 0 | F2: =IF(OR(D2>Assumptions!$B$5,E2>Assumptions!$B$5),"YES","No") -> No | G2: =COUNTIFS(Transactions!$C$2:$C$114,A2,Transactions!$B$2:$B$114,B2,Transactions!$I$2:$I$114,"Y") -> 1 | H2: =IF(F2="YES",B2+Assumptions!$B$10,"") | K2: =IF(AND(F2="YES",ISNUMBER(J2)),J2-B2,"") | L2: =IF(F2<>"YES","",IF(NOT(ISNUMBER(J2)),IF(Assumptions!$B$4>H2,"LATE - Not Filed","Pending - within deadline"),IF(J2<=H2,"On time","Late")))
A3: C012 | B3: 46274 | C3: =IFERROR(INDEX(Client_Master!$B$2:$B$41,MATCH(A3,Client_Master!$A$2:$A$41,0)),"UNKNOWN CLIENT") -> Brightline Retail Holdings Inc | D3: =SUMIFS(Transactions!$E$2:$E$114,Transactions!$C$2:$C$114,A3,Transactions!$B$2:$B$114,B3,Transactions!$D$2:$D$114,"Cash Deposit") -> 2800 | E3: =SUMIFS(Transactions!$E$2:$E$114,Transactions!$C$2:$C$114,A3,Transactions!$B$2:$B$114,B3,Transactions!$D$2:$D$114,"Cash Withdrawal") -> 0 | F3: =IF(OR(D3>Assumptions!$B$5,E3>Assumptions!$B$5),"YES","No") -> No | G3: =COUNTIFS(Transactions!$C$2:$C$114,A3,Transactions!$B$2:$B$114,B3,Transactions!$I$2:$I$114,"Y") -> 1 | H3: =IF(F3="YES",B3+Assumptions!$B$10,"") | K3: =IF(AND(F3="YES",ISNUMBER(J3)),J3-B3,"") | L3: =IF(F3<>"YES","",IF(NOT(ISNUMBER(J3)),IF(Assumptions!$B$4>H3,"LATE - Not Filed","Pending - within deadline"),IF(J3<=H3,"On time","Late")))
A4: C008 | B4: 46275 | C4: =IFERROR(INDEX(Client_Master!$B$2:$B$41,MATCH(A4,Client_Master!$A$2:$A$41,0)),"UNKNOWN CLIENT") -> Golden Crest Jewellers LLC | D4: =SUMIFS(Transactions!$E$2:$E$114,Transactions!$C$2:$C$114,A4,Transactions!$B$2:$B$114,B4,Transactions!$D$2:$D$114,"Cash Deposit") -> 30000 | E4: =SUMIFS(Transactions!$E$2:$E$114,Transactions!$C$2:$C$114,A4,Transactions!$B$2:$B$114,B4,Transactions!$D$2:$D$114,"Cash Withdrawal") -> 0 | F4: =IF(OR(D4>Assumptions!$B$5,E4>Assumptions!$B$5),"YES","No") -> YES | G4: =COUNTIFS(Transactions!$C$2:$C$114,A4,Transactions!$B$2:$B$114,B4,Transactions!$I$2:$I$114,"Y") -> 1 | H4: =IF(F4="YES",B4+Assumptions!$B$10,"") -> 46290 | I4: Filed | J4: 46283 | K4: =IF(AND(F4="YES",ISNUMBER(J4)),J4-B4,"") -> 8 | L4: =IF(F4<>"YES","",IF(NOT(ISNUMBER(J4)),IF(Assumptions!$B$4>H4,"LATE - Not Filed","Pending - within deadline"),IF(J4<=H4,"On time","Late"))) -> On time
A5: C005 | B5: 46279 | C5: =IFERROR(INDEX(Client_Master!$B$2:$B$41,MATCH(A5,Client_Master!$A$2:$A$41,0)),"UNKNOWN CLIENT") -> Spice Route Restaurants Group Inc | D5: =SUMIFS(Transactions!$E$2:$E$114,Transactions!$C$2:$C$114,A5,Transactions!$B$2:$B$114,B5,Transactions!$D$2:$D$114,"Cash Deposit") -> 3400 | E5: =SUMIFS(Transactions!$E$2:$E$114,Transactions!$C$2:$C$114,A5,Transactions!$B$2:$B$114,B5,Transactions!$D$2:$D$114,"Cash Withdrawal") -> 0 | F5: =IF(OR(D5>Assumptions!$B$5,E5>Assumptions!$B$5),"YES","No") -> No | G5: =COUNTIFS(Transactions!$C$2:$C$114,A5,Transactions!$B$2:$B$114,B5,Transactions!$I$2:$I$114,"Y") -> 1 | H5: =IF(F5="YES",B5+Assumptions!$B$10,"") | K5: =IF(AND(F5="YES",ISNUMBER(J5)),J5-B5,"") | L5: =IF(F5<>"YES","",IF(NOT(ISNUMBER(J5)),IF(Assumptions!$B$4>H5,"LATE - Not Filed","Pending - within deadline"),IF(J5<=H5,"On time","Late")))
A6: C024 | B6: 46281 | C6: =IFERROR(INDEX(Client_Master!$B$2:$B$41,MATCH(A6,Client_Master!$A$2:$A$41,0)),"UNKNOWN CLIENT") -> Sunrise Auto Traders LLC | D6: =SUMIFS(Transactions!$E$2:$E$114,Transactions!$C$2:$C$114,A6,Transactions!$B$2:$B$114,B6,Transactions!$D$2:$D$114,"Cash Deposit") -> 4200 | E6: =SUMIFS(Transactions!$E$2:$E$114,Transactions!$C$2:$C$114,A6,Transactions!$B$2:$B$114,B6,Transactions!$D$2:$D$114,"Cash Withdrawal") -> 0 | F6: =IF(OR(D6>Assumptions!$B$5,E6>Assumptions!$B$5),"YES","No") -> No | G6: =COUNTIFS(Transactions!$C$2:$C$114,A6,Transactions!$B$2:$B$114,B6,Transactions!$I$2:$I$114,"Y") -> 1 | H6: =IF(F6="YES",B6+Assumptions!$B$10,"") | K6: =IF(AND(F6="YES",ISNUMBER(J6)),J6-B6,"") | L6: =IF(F6<>"YES","",IF(NOT(ISNUMBER(J6)),IF(Assumptions!$B$4>H6,"LATE - Not Filed","Pending - within deadline"),IF(J6<=H6,"On time","Late")))
A7: C039 | B7: 46286 | C7: =IFERROR(INDEX(Client_Master!$B$2:$B$41,MATCH(A7,Client_Master!$A$2:$A$41,0)),"UNKNOWN CLIENT") -> Ridgeway Used Cars Ltd | D7: =SUMIFS(Transactions!$E$2:$E$114,Transactions!$C$2:$C$114,A7,Transactions!$B$2:$B$114,B7,Transactions!$D$2:$D$114,"Cash Deposit") -> 3600 | E7: =SUMIFS(Transactions!$E$2:$E$114,Transactions!$C$2:$C$114,A7,Transactions!$B$2:$B$114,B7,Transactions!$D$2:$D$114,"Cash Withdrawal") -> 0 | F7: =IF(OR(D7>Assumptions!$B$5,E7>Assumptions!$B$5),"YES","No") -> No | G7: =COUNTIFS(Transactions!$C$2:$C$114,A7,Transactions!$B$2:$B$114,B7,Transactions!$I$2:$I$114,"Y") -> 1 | H7: =IF(F7="YES",B7+Assumptions!$B$10,"") | K7: =IF(AND(F7="YES",ISNUMBER(J7)),J7-B7,"") | L7: =IF(F7<>"YES","",IF(NOT(ISNUMBER(J7)),IF(Assumptions!$B$4>H7,"LATE - Not Filed","Pending - within deadline"),IF(J7<=H7,"On time","Late")))
A8: C019 | B8: 46287 | C8: =IFERROR(INDEX(Client_Master!$B$2:$B$41,MATCH(A8,Client_Master!$A$2:$A$41,0)),"UNKNOWN CLIENT") -> Metro Fuel & Convenience Stores Inc | D8: =SUMIFS(Transactions!$E$2:$E$114,Transactions!$C$2:$C$114,A8,Transactions!$B$2:$B$114,B8,Transactions!$D$2:$D$114,"Cash Deposit") -> 4000 | E8: =SUMIFS(Transactions!$E$2:$E$114,Transactions!$C$2:$C$114,A8,Transactions!$B$2:$B$114,B8,Transactions!$D$2:$D$114,"Cash Withdrawal") -> 0 | F8: =IF(OR(D8>Assumptions!$B$5,E8>Assumptions!$B$5),"YES","No") -> No | G8: =COUNTIFS(Transactions!$C$2:$C$114,A8,Transactions!$B$2:$B$114,B8,Transactions!$I$2:$I$114,"Y") -> 1 | H8: =IF(F8="YES",B8+Assumptions!$B$10,"") | K8: =IF(AND(F8="YES",ISNUMBER(J8)),J8-B8,"") | L8: =IF(F8<>"YES","",IF(NOT(ISNUMBER(J8)),IF(Assumptions!$B$4>H8,"LATE - Not Filed","Pending - within deadline"),IF(J8<=H8,"On time","Late")))
A9: C008 | B9: 46289 | C9: =IFERROR(INDEX(Client_Master!$B$2:$B$41,MATCH(A9,Client_Master!$A$2:$A$41,0)),"UNKNOWN CLIENT") -> Golden Crest Jewellers LLC | D9: =SUMIFS(Transactions!$E$2:$E$114,Transactions!$C$2:$C$114,A9,Transactions!$B$2:$B$114,B9,Transactions!$D$2:$D$114,"Cash Deposit") -> 28000 | E9: =SUMIFS(Transactions!$E$2:$E$114,Transactions!$C$2:$C$114,A9,Transactions!$B$2:$B$114,B9,Transactions!$D$2:$D$114,"Cash Withdrawal") -> 0 | F9: =IF(OR(D9>Assumptions!$B$5,E9>Assumptions!$B$5),"YES","No") -> YES | G9: =COUNTIFS(Transactions!$C$2:$C$114,A9,Transactions!$B$2:$B$114,B9,Transactions!$I$2:$I$114,"Y") -> 1 | H9: =IF(F9="YES",B9+Assumptions!$B$10,"") -> 46304 | I9: Filed | J9: 46302 | K9: =IF(AND(F9="YES",ISNUMBER(J9)),J9-B9,"") -> 13 | L9: =IF(F9<>"YES","",IF(NOT(ISNUMBER(J9)),IF(Assumptions!$B$4>H9,"LATE - Not Filed","Pending - within deadline"),IF(J9<=H9,"On time","Late"))) -> On time
A10: C005 | B10: 46293 | C10: =IFERROR(INDEX(Client_Master!$B$2:$B$41,MATCH(A10,Client_Master!$A$2:$A$41,0)),"UNKNOWN CLIENT") -> Spice Route Restaurants Group Inc | D10: =SUMIFS(Transactions!$E$2:$E$114,Transactions!$C$2:$C$114,A10,Transactions!$B$2:$B$114,B10,Transactions!$D$2:$D$114,"Cash Deposit") -> 4100 | E10: =SUMIFS(Transactions!$E$2:$E$114,Transactions!$C$2:$C$114,A10,Transactions!$B$2:$B$114,B10,Transactions!$D$2:$D$114,"Cash Withdrawal") -> 0 | F10: =IF(OR(D10>Assumptions!$B$5,E10>Assumptions!$B$5),"YES","No") -> No | G10: =COUNTIFS(Transactions!$C$2:$C$114,A10,Transactions!$B$2:$B$114,B10,Transactions!$I$2:$I$114,"Y") -> 1 | H10: =IF(F10="YES",B10+Assumptions!$B$10,"") | K10: =IF(AND(F10="YES",ISNUMBER(J10)),J10-B10,"") | L10: =IF(F10<>"YES","",IF(NOT(ISNUMBER(J10)),IF(Assumptions!$B$4>H10,"LATE - Not Filed","Pending - within deadline"),IF(J10<=H10,"On time","Late")))
A11: C012 | B11: 46295 | C11: =IFERROR(INDEX(Client_Master!$B$2:$B$41,MATCH(A11,Client_Master!$A$2:$A$41,0)),"UNKNOWN CLIENT") -> Brightline Retail Holdings Inc | D11: =SUMIFS(Transactions!$E$2:$E$114,Transactions!$C$2:$C$114,A11,Transactions!$B$2:$B$114,B11,Transactions!$D$2:$D$114,"Cash Deposit") -> 5200 | E11: =SUMIFS(Transactions!$E$2:$E$114,Transactions!$C$2:$C$114,A11,Transactions!$B$2:$B$114,B11,Transactions!$D$2:$D$114,"Cash Withdrawal") -> 0 | F11: =IF(OR(D11>Assumptions!$B$5,E11>Assumptions!$B$5),"YES","No") -> No | G11: =COUNTIFS(Transactions!$C$2:$C$114,A11,Transactions!$B$2:$B$114,B11,Transactions!$I$2:$I$114,"Y") -> 1 | H11: =IF(F11="YES",B11+Assumptions!$B$10,"") | K11: =IF(AND(F11="YES",ISNUMBER(J11)),J11-B11,"") | L11: =IF(F11<>"YES","",IF(NOT(ISNUMBER(J11)),IF(Assumptions!$B$4>H11,"LATE - Not Filed","Pending - within deadline"),IF(J11<=H11,"On time","Late")))
A12: C005 | B12: 46300 | C12: =IFERROR(INDEX(Client_Master!$B$2:$B$41,MATCH(A12,Client_Master!$A$2:$A$41,0)),"UNKNOWN CLIENT") -> Spice Route Restaurants Group Inc | D12: =SUMIFS(Transactions!$E$2:$E$114,Transactions!$C$2:$C$114,A12,Transactions!$B$2:$B$114,B12,Transactions!$D$2:$D$114,"Cash Deposit") -> 11300 | E12: =SUMIFS(Transactions!$E$2:$E$114,Transactions!$C$2:$C$114,A12,Transactions!$B$2:$B$114,B12,Transactions!$D$2:$D$114,"Cash Withdrawal") -> 0 | F12: =IF(OR(D12>Assumptions!$B$5,E12>Assumptions!$B$5),"YES","No") -> YES | G12: =COUNTIFS(Transactions!$C$2:$C$114,A12,Transactions!$B$2:$B$114,B12,Transactions!$I$2:$I$114,"Y") -> 2 | H12: =IF(F12="YES",B12+Assumptions!$B$10,"") -> 46315 | I12: Filed | J12: 46309 | K12: =IF(AND(F12="YES",ISNUMBER(J12)),J12-B12,"") -> 9 | L12: =IF(F12<>"YES","",IF(NOT(ISNUMBER(J12)),IF(Assumptions!$B$4>H12,"LATE - Not Filed","Pending - within deadline"),IF(J12<=H12,"On time","Late"))) -> On time | M12: Two deposits same day from two outlets - aggregated for one CTR.
A13: C024 | B13: 46302 | C13: =IFERROR(INDEX(Client_Master!$B$2:$B$41,MATCH(A13,Client_Master!$A$2:$A$41,0)),"UNKNOWN CLIENT") -> Sunrise Auto Traders LLC | D13: =SUMIFS(Transactions!$E$2:$E$114,Transactions!$C$2:$C$114,A13,Transactions!$B$2:$B$114,B13,Transactions!$D$2:$D$114,"Cash Deposit") -> 6100 | E13: =SUMIFS(Transactions!$E$2:$E$114,Transactions!$C$2:$C$114,A13,Transactions!$B$2:$B$114,B13,Transactions!$D$2:$D$114,"Cash Withdrawal") -> 0 | F13: =IF(OR(D13>Assumptions!$B$5,E13>Assumptions!$B$5),"YES","No") -> No | G13: =COUNTIFS(Transactions!$C$2:$C$114,A13,Transactions!$B$2:$B$114,B13,Transactions!$I$2:$I$114,"Y") -> 1 | H13: =IF(F13="YES",B13+Assumptions!$B$10,"") | K13: =IF(AND(F13="YES",ISNUMBER(J13)),J13-B13,"") | L13: =IF(F13<>"YES","",IF(NOT(ISNUMBER(J13)),IF(Assumptions!$B$4>H13,"LATE - Not Filed","Pending - within deadline"),IF(J13<=H13,"On time","Late")))
A14: C008 | B14: 46303 | C14: =IFERROR(INDEX(Client_Master!$B$2:$B$41,MATCH(A14,Client_Master!$A$2:$A$41,0)),"UNKNOWN CLIENT") -> Golden Crest Jewellers LLC | D14: =SUMIFS(Transactions!$E$2:$E$114,Transactions!$C$2:$C$114,A14,Transactions!$B$2:$B$114,B14,Transactions!$D$2:$D$114,"Cash Deposit") -> 27000 | E14: =SUMIFS(Transactions!$E$2:$E$114,Transactions!$C$2:$C$114,A14,Transactions!$B$2:$B$114,B14,Transactions!$D$2:$D$114,"Cash Withdrawal") -> 0 | F14: =IF(OR(D14>Assumptions!$B$5,E14>Assumptions!$B$5),"YES","No") -> YES | G14: =COUNTIFS(Transactions!$C$2:$C$114,A14,Transactions!$B$2:$B$114,B14,Transactions!$I$2:$I$114,"Y") -> 1 | H14: =IF(F14="YES",B14+Assumptions!$B$10,"") -> 46318 | I14: Not Filed | K14: =IF(AND(F14="YES",ISNUMBER(J14)),J14-B14,"") | L14: =IF(F14<>"YES","",IF(NOT(ISNUMBER(J14)),IF(Assumptions!$B$4>H14,"LATE - Not Filed","Pending - within deadline"),IF(J14<=H14,"On time","Late"))) -> LATE - Not Filed | M14: Filing deadline passed - see ESC-006.
A15: C041 | B15: 46304 | C15: =IFERROR(INDEX(Client_Master!$B$2:$B$41,MATCH(A15,Client_Master!$A$2:$A$41,0)),"UNKNOWN CLIENT") -> UNKNOWN CLIENT | D15: =SUMIFS(Transactions!$E$2:$E$114,Transactions!$C$2:$C$114,A15,Transactions!$B$2:$B$114,B15,Transactions!$D$2:$D$114,"Cash Deposit") -> 7800 | E15: =SUMIFS(Transactions!$E$2:$E$114,Transactions!$C$2:$C$114,A15,Transactions!$B$2:$B$114,B15,Transactions!$D$2:$D$114,"Cash Withdrawal") -> 0 | F15: =IF(OR(D15>Assumptions!$B$5,E15>Assumptions!$B$5),"YES","No") -> No | G15: =COUNTIFS(Transactions!$C$2:$C$114,A15,Transactions!$B$2:$B$114,B15,Transactions!$I$2:$I$114,"Y") -> 1 | H15: =IF(F15="YES",B15+Assumptions!$B$10,"") | K15: =IF(AND(F15="YES",ISNUMBER(J15)),J15-B15,"") | L15: =IF(F15<>"YES","",IF(NOT(ISNUMBER(J15)),IF(Assumptions!$B$4>H15,"LATE - Not Filed","Pending - within deadline"),IF(J15<=H15,"On time","Late"))) | M15: No KYC record for this client - see ESC-007.
A16: C019 | B16: 46307 | C16: =IFERROR(INDEX(Client_Master!$B$2:$B$41,MATCH(A16,Client_Master!$A$2:$A$41,0)),"UNKNOWN CLIENT") -> Metro Fuel & Convenience Stores Inc | D16: =SUMIFS(Transactions!$E$2:$E$114,Transactions!$C$2:$C$114,A16,Transactions!$B$2:$B$114,B16,Transactions!$D$2:$D$114,"Cash Deposit") -> 9500 | E16: =SUMIFS(Transactions!$E$2:$E$114,Transactions!$C$2:$C$114,A16,Transactions!$B$2:$B$114,B16,Transactions!$D$2:$D$114,"Cash Withdrawal") -> 0 | F16: =IF(OR(D16>Assumptions!$B$5,E16>Assumptions!$B$5),"YES","No") -> No | G16: =COUNTIFS(Transactions!$C$2:$C$114,A16,Transactions!$B$2:$B$114,B16,Transactions!$I$2:$I$114,"Y") -> 1 | H16: =IF(F16="YES",B16+Assumptions!$B$10,"") | K16: =IF(AND(F16="YES",ISNUMBER(J16)),J16-B16,"") | L16: =IF(F16<>"YES","",IF(NOT(ISNUMBER(J16)),IF(Assumptions!$B$4>H16,"LATE - Not Filed","Pending - within deadline"),IF(J16<=H16,"On time","Late")))
A17: C019 | B17: 46308 | C17: =IFERROR(INDEX(Client_Master!$B$2:$B$41,MATCH(A17,Client_Master!$A$2:$A$41,0)),"UNKNOWN CLIENT") -> Metro Fuel & Convenience Stores Inc | D17: =SUMIFS(Transactions!$E$2:$E$114,Transactions!$C$2:$C$114,A17,Transactions!$B$2:$B$114,B17,Transactions!$D$2:$D$114,"Cash Deposit") -> 9800 | E17: =SUMIFS(Transactions!$E$2:$E$114,Transactions!$C$2:$C$114,A17,Transactions!$B$2:$B$114,B17,Transactions!$D$2:$D$114,"Cash Withdrawal") -> 0 | F17: =IF(OR(D17>Assumptions!$B$5,E17>Assumptions!$B$5),"YES","No") -> No | G17: =COUNTIFS(Transactions!$C$2:$C$114,A17,Transactions!$B$2:$B$114,B17,Transactions!$I$2:$I$114,"Y") -> 1 | H17: =IF(F17="YES",B17+Assumptions!$B$10,"") | K17: =IF(AND(F17="YES",ISNUMBER(J17)),J17-B17,"") | L17: =IF(F17<>"YES","",IF(NOT(ISNUMBER(J17)),IF(Assumptions!$B$4>H17,"LATE - Not Filed","Pending - within deadline"),IF(J17<=H17,"On time","Late")))
A18: C039 | B18: 46308 | C18: =IFERROR(INDEX(Client_Master!$B$2:$B$41,MATCH(A18,Client_Master!$A$2:$A$41,0)),"UNKNOWN CLIENT") -> Ridgeway Used Cars Ltd | D18: =SUMIFS(Transactions!$E$2:$E$114,Transactions!$C$2:$C$114,A18,Transactions!$B$2:$B$114,B18,Transactions!$D$2:$D$114,"Cash Deposit") -> 5400 | E18: =SUMIFS(Transactions!$E$2:$E$114,Transactions!$C$2:$C$114,A18,Transactions!$B$2:$B$114,B18,Transactions!$D$2:$D$114,"Cash Withdrawal") -> 0 | F18: =IF(OR(D18>Assumptions!$B$5,E18>Assumptions!$B$5),"YES","No") -> No | G18: =COUNTIFS(Transactions!$C$2:$C$114,A18,Transactions!$B$2:$B$114,B18,Transactions!$I$2:$I$114,"Y") -> 1 | H18: =IF(F18="YES",B18+Assumptions!$B$10,"") | K18: =IF(AND(F18="YES",ISNUMBER(J18)),J18-B18,"") | L18: =IF(F18<>"YES","",IF(NOT(ISNUMBER(J18)),IF(Assumptions!$B$4>H18,"LATE - Not Filed","Pending - within deadline"),IF(J18<=H18,"On time","Late")))
A19: C019 | B19: 46310 | C19: =IFERROR(INDEX(Client_Master!$B$2:$B$41,MATCH(A19,Client_Master!$A$2:$A$41,0)),"UNKNOWN CLIENT") -> Metro Fuel & Convenience Stores Inc | D19: =SUMIFS(Transactions!$E$2:$E$114,Transactions!$C$2:$C$114,A19,Transactions!$B$2:$B$114,B19,Transactions!$D$2:$D$114,"Cash Deposit") -> 9200 | E19: =SUMIFS(Transactions!$E$2:$E$114,Transactions!$C$2:$C$114,A19,Transactions!$B$2:$B$114,B19,Transactions!$D$2:$D$114,"Cash Withdrawal") -> 0 | F19: =IF(OR(D19>Assumptions!$B$5,E19>Assumptions!$B$5),"YES","No") -> No | G19: =COUNTIFS(Transactions!$C$2:$C$114,A19,Transactions!$B$2:$B$114,B19,Transactions!$I$2:$I$114,"Y") -> 1 | H19: =IF(F19="YES",B19+Assumptions!$B$10,"") | K19: =IF(AND(F19="YES",ISNUMBER(J19)),J19-B19,"") | L19: =IF(F19<>"YES","",IF(NOT(ISNUMBER(J19)),IF(Assumptions!$B$4>H19,"LATE - Not Filed","Pending - within deadline"),IF(J19<=H19,"On time","Late")))
A20: C019 | B20: 46311 | C20: =IFERROR(INDEX(Client_Master!$B$2:$B$41,MATCH(A20,Client_Master!$A$2:$A$41,0)),"UNKNOWN CLIENT") -> Metro Fuel & Convenience Stores Inc | D20: =SUMIFS(Transactions!$E$2:$E$114,Transactions!$C$2:$C$114,A20,Transactions!$B$2:$B$114,B20,Transactions!$D$2:$D$114,"Cash Deposit") -> 9700 | E20: =SUMIFS(Transactions!$E$2:$E$114,Transactions!$C$2:$C$114,A20,Transactions!$B$2:$B$114,B20,Transactions!$D$2:$D$114,"Cash Withdrawal") -> 0 | F20: =IF(OR(D20>Assumptions!$B$5,E20>Assumptions!$B$5),"YES","No") -> No | G20: =COUNTIFS(Transactions!$C$2:$C$114,A20,Transactions!$B$2:$B$114,B20,Transactions!$I$2:$I$114,"Y") -> 1 | H20: =IF(F20="YES",B20+Assumptions!$B$10,"") | K20: =IF(AND(F20="YES",ISNUMBER(J20)),J20-B20,"") | L20: =IF(F20<>"YES","",IF(NOT(ISNUMBER(J20)),IF(Assumptions!$B$4>H20,"LATE - Not Filed","Pending - within deadline"),IF(J20<=H20,"On time","Late")))
A21: C012 | B21: 46315 | C21: =IFERROR(INDEX(Client_Master!$B$2:$B$41,MATCH(A21,Client_Master!$A$2:$A$41,0)),"UNKNOWN CLIENT") -> Brightline Retail Holdings Inc | D21: =SUMIFS(Transactions!$E$2:$E$114,Transactions!$C$2:$C$114,A21,Transactions!$B$2:$B$114,B21,Transactions!$D$2:$D$114,"Cash Deposit") -> 14500 | E21: =SUMIFS(Transactions!$E$2:$E$114,Transactions!$C$2:$C$114,A21,Transactions!$B$2:$B$114,B21,Transactions!$D$2:$D$114,"Cash Withdrawal") -> 0 | F21: =IF(OR(D21>Assumptions!$B$5,E21>Assumptions!$B$5),"YES","No") -> YES | G21: =COUNTIFS(Transactions!$C$2:$C$114,A21,Transactions!$B$2:$B$114,B21,Transactions!$I$2:$I$114,"Y") -> 1 | H21: =IF(F21="YES",B21+Assumptions!$B$10,"") -> 46330 | I21: Pending | K21: =IF(AND(F21="YES",ISNUMBER(J21)),J21-B21,"") | L21: =IF(F21<>"YES","",IF(NOT(ISNUMBER(J21)),IF(Assumptions!$B$4>H21,"LATE - Not Filed","Pending - within deadline"),IF(J21<=H21,"On time","Late"))) -> Pending - within deadline

Sheet Alert_Monitoring
A1: Client ID | B1: Client Name | C1: Assigned Rating | D1: Total Cash (USD) | E1: Expected Cash - window (USD) | F1: Near-Threshold Cash Txns | G1: CTR Days | H1: High-Risk Jurisdiction Txns | I1: Wire In Total | J1: Wire Out Total | K1: R1 Structuring | L1: R2 Cash > Profile | M1: R3 High-Risk Jurisdiction | N1: R4 PEP Activity | O1: R5 Pass-through | P1: R6 Sanctions Hit | Q1: Rules Triggered | R1: Disposition | S1: Rules Fired | U1: Monitoring rules (scenario logic)
A2: =Client_Master!A2 -> C001 | B2: =Client_Master!B2 -> Aurora Software Solutions Pvt Ltd | C2: =Client_Master!H2 -> Low | D2: =SUMIFS(Transactions!$E$2:$E$114,Transactions!$C$2:$C$114,A2,Transactions!$I$2:$I$114,"Y") -> 0 | E2: =Client_Master!O2*Assumptions!$B$9 -> 0 | F2: =COUNTIFS(Transactions!$C$2:$C$114,A2,Transactions!$K$2:$K$114,"Y") -> 0 | G2: =COUNTIFS(CTR_Log!$A$2:$A$21,A2,CTR_Log!$F$2:$F$21,"YES") -> 0 | H2: =COUNTIFS(Transactions!$C$2:$C$114,A2,Transactions!$L$2:$L$114,">=3") -> 0 | I2: =SUMIFS(Transactions!$E$2:$E$114,Transactions!$C$2:$C$114,A2,Transactions!$D$2:$D$114,"Wire In") -> 119900 | J2: =SUMIFS(Transactions!$E$2:$E$114,Transactions!$C$2:$C$114,A2,Transactions!$D$2:$D$114,"Wire Out") -> 76800 | K2: =IF(F2>=Assumptions!$B$7,1,0) -> 0 | L2: =IF(AND(D2>0,D2>E2*Assumptions!$B$8),1,0) -> 0 | M2: =IF(H2>0,1,0) -> 0 | N2: =IF(AND(Client_Master!N2="Y",I2+J2>=Assumptions!$B$11),1,0) -> 0 | O2: =IF(AND(I2>=Assumptions!$B$13,J2>=Assumptions!$B$13),IF(ABS(J2/I2-1)<=Assumptions!$B$12,1,0),0) -> 0 | P2: =IF(Client_Master!M2="Potential Match",1,0) -> 0 | Q2: =SUM(K2:P2) -> 0 | R2: =IF(OR(K2=1,M2=1,N2=1,P2=1,Q2>=2),"ESCALATE",IF(Q2=1,"Analyst Review","No Action")) -> No Action | S2: =TRIM(IF(K2=1,"R1 Structuring; ","")&IF(L2=1,"R2 Cash>Profile; ","")&IF(M2=1,"R3 High-Risk Jurisdiction; ","")&IF(N2=1,"R4 PEP Activity; ","")&IF(O2=1,"R5 Pass-through; ","")&IF(P2=1,"R6 Sanctions Hit; ","")) | U2: R1 Structuring | V2: Near-threshold cash transactions (from lower bound up to CTR threshold) >= minimum count.
A3: =Client_Master!A3 -> C002 | B3: =Client_Master!B3 -> Nordic Precision Manufacturing GmbH | C3: =Client_Master!H3 -> Low | D3: =SUMIFS(Transactions!$E$2:$E$114,Transactions!$C$2:$C$114,A3,Transactions!$I$2:$I$114,"Y") -> 0 | E3: =Client_Master!O3*Assumptions!$B$9 -> 0 | F3: =COUNTIFS(Transactions!$C$2:$C$114,A3,Transactions!$K$2:$K$114,"Y") -> 0 | G3: =COUNTIFS(CTR_Log!$A$2:$A$21,A3,CTR_Log!$F$2:$F$21,"YES") -> 0 | H3: =COUNTIFS(Transactions!$C$2:$C$114,A3,Transactions!$L$2:$L$114,">=3") -> 0 | I3: =SUMIFS(Transactions!$E$2:$E$114,Transactions!$C$2:$C$114,A3,Transactions!$D$2:$D$114,"Wire In") -> 0 | J3: =SUMIFS(Transactions!$E$2:$E$114,Transactions!$C$2:$C$114,A3,Transactions!$D$2:$D$114,"Wire Out") -> 207800 | K3: =IF(F3>=Assumptions!$B$7,1,0) -> 0 | L3: =IF(AND(D3>0,D3>E3*Assumptions!$B$8),1,0) -> 0 | M3: =IF(H3>0,1,0) -> 0 | N3: =IF(AND(Client_Master!N3="Y",I3+J3>=Assumptions!$B$11),1,0) -> 0 | O3: =IF(AND(I3>=Assumptions!$B$13,J3>=Assumptions!$B$13),IF(ABS(J3/I3-1)<=Assumptions!$B$12,1,0),0) -> 0 | P3: =IF(Client_Master!M3="Potential Match",1,0) -> 0 | Q3: =SUM(K3:P3) -> 0 | R3: =IF(OR(K3=1,M3=1,N3=1,P3=1,Q3>=2),"ESCALATE",IF(Q3=1,"Analyst Review","No Action")) -> No Action | S3: =TRIM(IF(K3=1,"R1 Structuring; ","")&IF(L3=1,"R2 Cash>Profile; ","")&IF(M3=1,"R3 High-Risk Jurisdiction; ","")&IF(N3=1,"R4 PEP Activity; ","")&IF(O3=1,"R5 Pass-through; ","")&IF(P3=1,"R6 Sanctions Hit; ","")) | U3: R2 Cash > Profile | V3: Total cash exceeds expected monthly cash x window x multiple (or any cash if profile is zero).
A4: =Client_Master!A4 -> C003 | B4: =Client_Master!B4 -> Lotus Healthcare Systems Ltd | C4: =Client_Master!H4 -> Low | D4: =SUMIFS(Transactions!$E$2:$E$114,Transactions!$C$2:$C$114,A4,Transactions!$I$2:$I$114,"Y") -> 0 | E4: =Client_Master!O4*Assumptions!$B$9 -> 0 | F4: =COUNTIFS(Transactions!$C$2:$C$114,A4,Transactions!$K$2:$K$114,"Y") -> 0 | G4: =COUNTIFS(CTR_Log!$A$2:$A$21,A4,CTR_Log!$F$2:$F$21,"YES") -> 0 | H4: =COUNTIFS(Transactions!$C$2:$C$114,A4,Transactions!$L$2:$L$114,">=3") -> 0 | I4: =SUMIFS(Transactions!$E$2:$E$114,Transactions!$C$2:$C$114,A4,Transactions!$D$2:$D$114,"Wire In") -> 47700 | J4: =SUMIFS(Transactions!$E$2:$E$114,Transactions!$C$2:$C$114,A4,Transactions!$D$2:$D$114,"Wire Out") -> 109000 | K4: =IF(F4>=Assumptions!$B$7,1,0) -> 0 | L4: =IF(AND(D4>0,D4>E4*Assumptions!$B$8),1,0) -> 0 | M4: =IF(H4>0,1,0) -> 0 | N4: =IF(AND(Client_Master!N4="Y",I4+J4>=Assumptions!$B$11),1,0) -> 0 | O4: =IF(AND(I4>=Assumptions!$B$13,J4>=Assumptions!$B$13),IF(ABS(J4/I4-1)<=Assumptions!$B$12,1,0),0) -> 0 | P4: =IF(Client_Master!M4="Potential Match",1,0) -> 0 | Q4: =SUM(K4:P4) -> 0 | R4: =IF(OR(K4=1,M4=1,N4=1,P4=1,Q4>=2),"ESCALATE",IF(Q4=1,"Analyst Review","No Action")) -> No Action | S4: =TRIM(IF(K4=1,"R1 Structuring; ","")&IF(L4=1,"R2 Cash>Profile; ","")&IF(M4=1,"R3 High-Risk Jurisdiction; ","")&IF(N4=1,"R4 PEP Activity; ","")&IF(O4=1,"R5 Pass-through; ","")&IF(P4=1,"R6 Sanctions Hit; ","")) | U4: R3 High-Risk Jurisdiction | V4: Any transaction with a counterparty in a score-3 country.
A5: =Client_Master!A5 -> C004 | B5: =Client_Master!B5 -> Thames Consulting Partners LLP | C5: =Client_Master!H5 -> Low | D5: =SUMIFS(Transactions!$E$2:$E$114,Transactions!$C$2:$C$114,A5,Transactions!$I$2:$I$114,"Y") -> 0 | E5: =Client_Master!O5*Assumptions!$B$9 -> 0 | F5: =COUNTIFS(Transactions!$C$2:$C$114,A5,Transactions!$K$2:$K$114,"Y") -> 0 | G5: =COUNTIFS(CTR_Log!$A$2:$A$21,A5,CTR_Log!$F$2:$F$21,"YES") -> 0 | H5: =COUNTIFS(Transactions!$C$2:$C$114,A5,Transactions!$L$2:$L$114,">=3") -> 0 | I5: =SUMIFS(Transactions!$E$2:$E$114,Transactions!$C$2:$C$114,A5,Transactions!$D$2:$D$114,"Wire In") -> 118000 | J5: =SUMIFS(Transactions!$E$2:$E$114,Transactions!$C$2:$C$114,A5,Transactions!$D$2:$D$114,"Wire Out") -> 48500 | K5: =IF(F5>=Assumptions!$B$7,1,0) -> 0 | L5: =IF(AND(D5>0,D5>E5*Assumptions!$B$8),1,0) -> 0 | M5: =IF(H5>0,1,0) -> 0 | N5: =IF(AND(Client_Master!N5="Y",I5+J5>=Assumptions!$B$11),1,0) -> 0 | O5: =IF(AND(I5>=Assumptions!$B$13,J5>=Assumptions!$B$13),IF(ABS(J5/I5-1)<=Assumptions!$B$12,1,0),0) -> 0 | P5: =IF(Client_Master!M5="Potential Match",1,0) -> 0 | Q5: =SUM(K5:P5) -> 0 | R5: =IF(OR(K5=1,M5=1,N5=1,P5=1,Q5>=2),"ESCALATE",IF(Q5=1,"Analyst Review","No Action")) -> No Action | S5: =TRIM(IF(K5=1,"R1 Structuring; ","")&IF(L5=1,"R2 Cash>Profile; ","")&IF(M5=1,"R3 High-Risk Jurisdiction; ","")&IF(N5=1,"R4 PEP Activity; ","")&IF(O5=1,"R5 Pass-through; ","")&IF(P5=1,"R6 Sanctions Hit; ","")) | U5: R4 PEP Activity | V5: PEP client with total wire value at/above the review threshold.
A6: =Client_Master!A6 -> C005 | B6: =Client_Master!B6 -> Spice Route Restaurants Group Inc | C6: =Client_Master!H6 -> Low | D6: =SUMIFS(Transactions!$E$2:$E$114,Transactions!$C$2:$C$114,A6,Transactions!$I$2:$I$114,"Y") -> 18800 | E6: =Client_Master!O6*Assumptions!$B$9 -> 80000 | F6: =COUNTIFS(Transactions!$C$2:$C$114,A6,Transactions!$K$2:$K$114,"Y") -> 0 | G6: =COUNTIFS(CTR_Log!$A$2:$A$21,A6,CTR_Log!$F$2:$F$21,"YES") -> 1 | H6: =COUNTIFS(Transactions!$C$2:$C$114,A6,Transactions!$L$2:$L$114,">=3") -> 0 | I6: =SUMIFS(Transactions!$E$2:$E$114,Transactions!$C$2:$C$114,A6,Transactions!$D$2:$D$114,"Wire In") -> 0 | J6: =SUMIFS(Transactions!$E$2:$E$114,Transactions!$C$2:$C$114,A6,Transactions!$D$2:$D$114,"Wire Out") -> 0 | K6: =IF(F6>=Assumptions!$B$7,1,0) -> 0 | L6: =IF(AND(D6>0,D6>E6*Assumptions!$B$8),1,0) -> 0 | M6: =IF(H6>0,1,0) -> 0 | N6: =IF(AND(Client_Master!N6="Y",I6+J6>=Assumptions!$B$11),1,0) -> 0 | O6: =IF(AND(I6>=Assumptions!$B$13,J6>=Assumptions!$B$13),IF(ABS(J6/I6-1)<=Assumptions!$B$12,1,0),0) -> 0 | P6: =IF(Client_Master!M6="Potential Match",1,0) -> 0 | Q6: =SUM(K6:P6) -> 0 | R6: =IF(OR(K6=1,M6=1,N6=1,P6=1,Q6>=2),"ESCALATE",IF(Q6=1,"Analyst Review","No Action")) -> No Action | S6: =TRIM(IF(K6=1,"R1 Structuring; ","")&IF(L6=1,"R2 Cash>Profile; ","")&IF(M6=1,"R3 High-Risk Jurisdiction; ","")&IF(N6=1,"R4 PEP Activity; ","")&IF(O6=1,"R5 Pass-through; ","")&IF(P6=1,"R6 Sanctions Hit; ","")) | U6: R5 Pass-through | V6: Wire In and Wire Out both >= minimum and within the tolerance of each other (rapid in/out).
A7: =Client_Master!A7 -> C006 | B7: =Client_Master!B7 -> Meridian Textile Exports Pvt Ltd | C7: =Client_Master!H7 -> Low | D7: =SUMIFS(Transactions!$E$2:$E$114,Transactions!$C$2:$C$114,A7,Transactions!$I$2:$I$114,"Y") -> 0 | E7: =Client_Master!O7*Assumptions!$B$9 -> 0 | F7: =COUNTIFS(Transactions!$C$2:$C$114,A7,Transactions!$K$2:$K$114,"Y") -> 0 | G7: =COUNTIFS(CTR_Log!$A$2:$A$21,A7,CTR_Log!$F$2:$F$21,"YES") -> 0 | H7: =COUNTIFS(Transactions!$C$2:$C$114,A7,Transactions!$L$2:$L$114,">=3") -> 0 | I7: =SUMIFS(Transactions!$E$2:$E$114,Transactions!$C$2:$C$114,A7,Transactions!$D$2:$D$114,"Wire In") -> 155700 | J7: =SUMIFS(Transactions!$E$2:$E$114,Transactions!$C$2:$C$114,A7,Transactions!$D$2:$D$114,"Wire Out") -> 81800 | K7: =IF(F7>=Assumptions!$B$7,1,0) -> 0 | L7: =IF(AND(D7>0,D7>E7*Assumptions!$B$8),1,0) -> 0 | M7: =IF(H7>0,1,0) -> 0 | N7: =IF(AND(Client_Master!N7="Y",I7+J7>=Assumptions!$B$11),1,0) -> 0 | O7: =IF(AND(I7>=Assumptions!$B$13,J7>=Assumptions!$B$13),IF(ABS(J7/I7-1)<=Assumptions!$B$12,1,0),0) -> 0 | P7: =IF(Client_Master!M7="Potential Match",1,0) -> 0 | Q7: =SUM(K7:P7) -> 0 | R7: =IF(OR(K7=1,M7=1,N7=1,P7=1,Q7>=2),"ESCALATE",IF(Q7=1,"Analyst Review","No Action")) -> No Action | S7: =TRIM(IF(K7=1,"R1 Structuring; ","")&IF(L7=1,"R2 Cash>Profile; ","")&IF(M7=1,"R3 High-Risk Jurisdiction; ","")&IF(N7=1,"R4 PEP Activity; ","")&IF(O7=1,"R5 Pass-through; ","")&IF(P7=1,"R6 Sanctions Hit; ","")) | U7: R6 Sanctions Hit | V7: Screening result is "Potential Match" (unresolved).
A8: =Client_Master!A8 -> C007 | B8: =Client_Master!B8 -> Alpine Logistics AG | C8: =Client_Master!H8 -> Low | D8: =SUMIFS(Transactions!$E$2:$E$114,Transactions!$C$2:$C$114,A8,Transactions!$I$2:$I$114,"Y") -> 0 | E8: =Client_Master!O8*Assumptions!$B$9 -> 0 | F8: =COUNTIFS(Transactions!$C$2:$C$114,A8,Transactions!$K$2:$K$114,"Y") -> 0 | G8: =COUNTIFS(CTR_Log!$A$2:$A$21,A8,CTR_Log!$F$2:$F$21,"YES") -> 0 | H8: =COUNTIFS(Transactions!$C$2:$C$114,A8,Transactions!$L$2:$L$114,">=3") -> 0 | I8: =SUMIFS(Transactions!$E$2:$E$114,Transactions!$C$2:$C$114,A8,Transactions!$D$2:$D$114,"Wire In") -> 69700 | J8: =SUMIFS(Transactions!$E$2:$E$114,Transactions!$C$2:$C$114,A8,Transactions!$D$2:$D$114,"Wire Out") -> 0 | K8: =IF(F8>=Assumptions!$B$7,1,0) -> 0 | L8: =IF(AND(D8>0,D8>E8*Assumptions!$B$8),1,0) -> 0 | M8: =IF(H8>0,1,0) -> 0 | N8: =IF(AND(Client_Master!N8="Y",I8+J8>=Assumptions!$B$11),1,0) -> 0 | O8: =IF(AND(I8>=Assumptions!$B$13,J8>=Assumptions!$B$13),IF(ABS(J8/I8-1)<=Assumptions!$B$12,1,0),0) -> 0 | P8: =IF(Client_Master!M8="Potential Match",1,0) -> 0 | Q8: =SUM(K8:P8) -> 0 | R8: =IF(OR(K8=1,M8=1,N8=1,P8=1,Q8>=2),"ESCALATE",IF(Q8=1,"Analyst Review","No Action")) -> No Action | S8: =TRIM(IF(K8=1,"R1 Structuring; ","")&IF(L8=1,"R2 Cash>Profile; ","")&IF(M8=1,"R3 High-Risk Jurisdiction; ","")&IF(N8=1,"R4 PEP Activity; ","")&IF(O8=1,"R5 Pass-through; ","")&IF(P8=1,"R6 Sanctions Hit; ","")) | U8: Disposition | V8: ESCALATE if R1, R3, R4 or R6 fires, or 2+ rules fire. Analyst Review if exactly one other rule fires. Else No Action.
A9: =Client_Master!A9 -> C008 | B9: =Client_Master!B9 -> Golden Crest Jewellers LLC | C9: =Client_Master!H9 -> Low | D9: =SUMIFS(Transactions!$E$2:$E$114,Transactions!$C$2:$C$114,A9,Transactions!$I$2:$I$114,"Y") -> 85000 | E9: =Client_Master!O9*Assumptions!$B$9 -> 40000 | F9: =COUNTIFS(Transactions!$C$2:$C$114,A9,Transactions!$K$2:$K$114,"Y") -> 0 | G9: =COUNTIFS(CTR_Log!$A$2:$A$21,A9,CTR_Log!$F$2:$F$21,"YES") -> 3 | H9: =COUNTIFS(Transactions!$C$2:$C$114,A9,Transactions!$L$2:$L$114,">=3") -> 0 | I9: =SUMIFS(Transactions!$E$2:$E$114,Transactions!$C$2:$C$114,A9,Transactions!$D$2:$D$114,"Wire In") -> 0 | J9: =SUMIFS(Transactions!$E$2:$E$114,Transactions!$C$2:$C$114,A9,Transactions!$D$2:$D$114,"Wire Out") -> 0 | K9: =IF(F9>=Assumptions!$B$7,1,0) -> 0 | L9: =IF(AND(D9>0,D9>E9*Assumptions!$B$8),1,0) -> 1 | M9: =IF(H9>0,1,0) -> 0 | N9: =IF(AND(Client_Master!N9="Y",I9+J9>=Assumptions!$B$11),1,0) -> 0 | O9: =IF(AND(I9>=Assumptions!$B$13,J9>=Assumptions!$B$13),IF(ABS(J9/I9-1)<=Assumptions!$B$12,1,0),0) -> 0 | P9: =IF(Client_Master!M9="Potential Match",1,0) -> 0 | Q9: =SUM(K9:P9) -> 1 | R9: =IF(OR(K9=1,M9=1,N9=1,P9=1,Q9>=2),"ESCALATE",IF(Q9=1,"Analyst Review","No Action")) -> Analyst Review | S9: =TRIM(IF(K9=1,"R1 Structuring; ","")&IF(L9=1,"R2 Cash>Profile; ","")&IF(M9=1,"R3 High-Risk Jurisdiction; ","")&IF(N9=1,"R4 PEP Activity; ","")&IF(O9=1,"R5 Pass-through; ","")&IF(P9=1,"R6 Sanctions Hit; ","")) -> R2 Cash>Profile;
A10: =Client_Master!A10 -> C009 | B10: =Client_Master!B10 -> Pinnacle Realty Developers Ltd | C10: =Client_Master!H10 -> Medium | D10: =SUMIFS(Transactions!$E$2:$E$114,Transactions!$C$2:$C$114,A10,Transactions!$I$2:$I$114,"Y") -> 0 | E10: =Client_Master!O10*Assumptions!$B$9 -> 0 | F10: =COUNTIFS(Transactions!$C$2:$C$114,A10,Transactions!$K$2:$K$114,"Y") -> 0 | G10: =COUNTIFS(CTR_Log!$A$2:$A$21,A10,CTR_Log!$F$2:$F$21,"YES") -> 0 | H10: =COUNTIFS(Transactions!$C$2:$C$114,A10,Transactions!$L$2:$L$114,">=3") -> 0 | I10: =SUMIFS(Transactions!$E$2:$E$114,Transactions!$C$2:$C$114,A10,Transactions!$D$2:$D$114,"Wire In") -> 74300 | J10: =SUMIFS(Transactions!$E$2:$E$114,Transactions!$C$2:$C$114,A10,Transactions!$D$2:$D$114,"Wire Out") -> 0 | K10: =IF(F10>=Assumptions!$B$7,1,0) -> 0 | L10: =IF(AND(D10>0,D10>E10*Assumptions!$B$8),1,0) -> 0 | M10: =IF(H10>0,1,0) -> 0 | N10: =IF(AND(Client_Master!N10="Y",I10+J10>=Assumptions!$B$11),1,0) -> 0 | O10: =IF(AND(I10>=Assumptions!$B$13,J10>=Assumptions!$B$13),IF(ABS(J10/I10-1)<=Assumptions!$B$12,1,0),0) -> 0 | P10: =IF(Client_Master!M10="Potential Match",1,0) -> 0 | Q10: =SUM(K10:P10) -> 0 | R10: =IF(OR(K10=1,M10=1,N10=1,P10=1,Q10>=2),"ESCALATE",IF(Q10=1,"Analyst Review","No Action")) -> No Action | S10: =TRIM(IF(K10=1,"R1 Structuring; ","")&IF(L10=1,"R2 Cash>Profile; ","")&IF(M10=1,"R3 High-Risk Jurisdiction; ","")&IF(N10=1,"R4 PEP Activity; ","")&IF(O10=1,"R5 Pass-through; ","")&IF(P10=1,"R6 Sanctions Hit; ",""))
A11: =Client_Master!A11 -> C010 | B11: =Client_Master!B11 -> Harbour Point Trading Co | C11: =Client_Master!H11 -> Medium | D11: =SUMIFS(Transactions!$E$2:$E$114,Transactions!$C$2:$C$114,A11,Transactions!$I$2:$I$114,"Y") -> 0 | E11: =Client_Master!O11*Assumptions!$B$9 -> 0 | F11: =COUNTIFS(Transactions!$C$2:$C$114,A11,Transactions!$K$2:$K$114,"Y") -> 0 | G11: =COUNTIFS(CTR_Log!$A$2:$A$21,A11,CTR_Log!$F$2:$F$21,"YES") -> 0 | H11: =COUNTIFS(Transactions!$C$2:$C$114,A11,Transactions!$L$2:$L$114,">=3") -> 0 | I11: =SUMIFS(Transactions!$E$2:$E$114,Transactions!$C$2:$C$114,A11,Transactions!$D$2:$D$114,"Wire In") -> 82200 | J11: =SUMIFS(Transactions!$E$2:$E$114,Transactions!$C$2:$C$114,A11,Transactions!$D$2:$D$114,"Wire Out") -> 60400 | K11: =IF(F11>=Assumptions!$B$7,1,0) -> 0 | L11: =IF(AND(D11>0,D11>E11*Assumptions!$B$8),1,0) -> 0 | M11: =IF(H11>0,1,0) -> 0 | N11: =IF(AND(Client_Master!N11="Y",I11+J11>=Assumptions!$B$11),1,0) -> 0 | O11: =IF(AND(I11>=Assumptions!$B$13,J11>=Assumptions!$B$13),IF(ABS(J11/I11-1)<=Assumptions!$B$12,1,0),0) -> 0 | P11: =IF(Client_Master!M11="Potential Match",1,0) -> 0 | Q11: =SUM(K11:P11) -> 0 | R11: =IF(OR(K11=1,M11=1,N11=1,P11=1,Q11>=2),"ESCALATE",IF(Q11=1,"Analyst Review","No Action")) -> No Action | S11: =TRIM(IF(K11=1,"R1 Structuring; ","")&IF(L11=1,"R2 Cash>Profile; ","")&IF(M11=1,"R3 High-Risk Jurisdiction; ","")&IF(N11=1,"R4 PEP Activity; ","")&IF(O11=1,"R5 Pass-through; ","")&IF(P11=1,"R6 Sanctions Hit; ",""))
A12: =Client_Master!A12 -> C011 | B12: =Client_Master!B12 -> Coral Reef Gaming Ltd | C12: =Client_Master!H12 -> Medium | D12: =SUMIFS(Transactions!$E$2:$E$114,Transactions!$C$2:$C$114,A12,Transactions!$I$2:$I$114,"Y") -> 0 | E12: =Client_Master!O12*Assumptions!$B$9 -> 0 | F12: =COUNTIFS(Transactions!$C$2:$C$114,A12,Transactions!$K$2:$K$114,"Y") -> 0 | G12: =COUNTIFS(CTR_Log!$A$2:$A$21,A12,CTR_Log!$F$2:$F$21,"YES") -> 0 | H12: =COUNTIFS(Transactions!$C$2:$C$114,A12,Transactions!$L$2:$L$114,">=3") -> 0 | I12: =SUMIFS(Transactions!$E$2:$E$114,Transactions!$C$2:$C$114,A12,Transactions!$D$2:$D$114,"Wire In") -> 124300 | J12: =SUMIFS(Transactions!$E$2:$E$114,Transactions!$C$2:$C$114,A12,Transactions!$D$2:$D$114,"Wire Out") -> 32700 | K12: =IF(F12>=Assumptions!$B$7,1,0) -> 0 | L12: =IF(AND(D12>0,D12>E12*Assumptions!$B$8),1,0) -> 0 | M12: =IF(H12>0,1,0) -> 0 | N12: =IF(AND(Client_Master!N12="Y",I12+J12>=Assumptions!$B$11),1,0) -> 0 | O12: =IF(AND(I12>=Assumptions!$B$13,J12>=Assumptions!$B$13),IF(ABS(J12/I12-1)<=Assumptions!$B$12,1,0),0) -> 0 | P12: =IF(Client_Master!M12="Potential Match",1,0) -> 0 | Q12: =SUM(K12:P12) -> 0 | R12: =IF(OR(K12=1,M12=1,N12=1,P12=1,Q12>=2),"ESCALATE",IF(Q12=1,"Analyst Review","No Action")) -> No Action | S12: =TRIM(IF(K12=1,"R1 Structuring; ","")&IF(L12=1,"R2 Cash>Profile; ","")&IF(M12=1,"R3 High-Risk Jurisdiction; ","")&IF(N12=1,"R4 PEP Activity; ","")&IF(O12=1,"R5 Pass-through; ","")&IF(P12=1,"R6 Sanctions Hit; ",""))
A13: =Client_Master!A13 -> C012 | B13: =Client_Master!B13 -> Brightline Retail Holdings Inc | C13: =Client_Master!H13 -> Low | D13: =SUMIFS(Transactions!$E$2:$E$114,Transactions!$C$2:$C$114,A13,Transactions!$I$2:$I$114,"Y") -> 22500 | E13: =Client_Master!O13*Assumptions!$B$9 -> 90000 | F13: =COUNTIFS(Transactions!$C$2:$C$114,A13,Transactions!$K$2:$K$114,"Y") -> 0 | G13: =COUNTIFS(CTR_Log!$A$2:$A$21,A13,CTR_Log!$F$2:$F$21,"YES") -> 1 | H13: =COUNTIFS(Transactions!$C$2:$C$114,A13,Transactions!$L$2:$L$114,">=3") -> 0 | I13: =SUMIFS(Transactions!$E$2:$E$114,Transactions!$C$2:$C$114,A13,Transactions!$D$2:$D$114,"Wire In") -> 0 | J13: =SUMIFS(Transactions!$E$2:$E$114,Transactions!$C$2:$C$114,A13,Transactions!$D$2:$D$114,"Wire Out") -> 0 | K13: =IF(F13>=Assumptions!$B$7,1,0) -> 0 | L13: =IF(AND(D13>0,D13>E13*Assumptions!$B$8),1,0) -> 0 | M13: =IF(H13>0,1,0) -> 0 | N13: =IF(AND(Client_Master!N13="Y",I13+J13>=Assumptions!$B$11),1,0) -> 0 | O13: =IF(AND(I13>=Assumptions!$B$13,J13>=Assumptions!$B$13),IF(ABS(J13/I13-1)<=Assumptions!$B$12,1,0),0) -> 0 | P13: =IF(Client_Master!M13="Potential Match",1,0) -> 0 | Q13: =SUM(K13:P13) -> 0 | R13: =IF(OR(K13=1,M13=1,N13=1,P13=1,Q13>=2),"ESCALATE",IF(Q13=1,"Analyst Review","No Action")) -> No Action | S13: =TRIM(IF(K13=1,"R1 Structuring; ","")&IF(L13=1,"R2 Cash>Profile; ","")&IF(M13=1,"R3 High-Risk Jurisdiction; ","")&IF(N13=1,"R4 PEP Activity; ","")&IF(O13=1,"R5 Pass-through; ","")&IF(P13=1,"R6 Sanctions Hit; ",""))
A14: =Client_Master!A14 -> C013 | B14: =Client_Master!B14 -> Sakura Electronics KK | C14: =Client_Master!H14 -> Low | D14: =SUMIFS(Transactions!$E$2:$E$114,Transactions!$C$2:$C$114,A14,Transactions!$I$2:$I$114,"Y") -> 0 | E14: =Client_Master!O14*Assumptions!$B$9 -> 0 | F14: =COUNTIFS(Transactions!$C$2:$C$114,A14,Transactions!$K$2:$K$114,"Y") -> 0 | G14: =COUNTIFS(CTR_Log!$A$2:$A$21,A14,CTR_Log!$F$2:$F$21,"YES") -> 0 | H14: =COUNTIFS(Transactions!$C$2:$C$114,A14,Transactions!$L$2:$L$114,">=3") -> 0 | I14: =SUMIFS(Transactions!$E$2:$E$114,Transactions!$C$2:$C$114,A14,Transactions!$D$2:$D$114,"Wire In") -> 80800 | J14: =SUMIFS(Transactions!$E$2:$E$114,Transactions!$C$2:$C$114,A14,Transactions!$D$2:$D$114,"Wire Out") -> 58000 | K14: =IF(F14>=Assumptions!$B$7,1,0) -> 0 | L14: =IF(AND(D14>0,D14>E14*Assumptions!$B$8),1,0) -> 0 | M14: =IF(H14>0,1,0) -> 0 | N14: =IF(AND(Client_Master!N14="Y",I14+J14>=Assumptions!$B$11),1,0) -> 0 | O14: =IF(AND(I14>=Assumptions!$B$13,J14>=Assumptions!$B$13),IF(ABS(J14/I14-1)<=Assumptions!$B$12,1,0),0) -> 0 | P14: =IF(Client_Master!M14="Potential Match",1,0) -> 0 | Q14: =SUM(K14:P14) -> 0 | R14: =IF(OR(K14=1,M14=1,N14=1,P14=1,Q14>=2),"ESCALATE",IF(Q14=1,"Analyst Review","No Action")) -> No Action | S14: =TRIM(IF(K14=1,"R1 Structuring; ","")&IF(L14=1,"R2 Cash>Profile; ","")&IF(M14=1,"R3 High-Risk Jurisdiction; ","")&IF(N14=1,"R4 PEP Activity; ","")&IF(O14=1,"R5 Pass-through; ","")&IF(P14=1,"R6 Sanctions Hit; ",""))
A15: =Client_Master!A15 -> C014 | B15: =Client_Master!B15 -> Maple Leaf Health Clinics Inc | C15: =Client_Master!H15 -> Low | D15: =SUMIFS(Transactions!$E$2:$E$114,Transactions!$C$2:$C$114,A15,Transactions!$I$2:$I$114,"Y") -> 0 | E15: =Client_Master!O15*Assumptions!$B$9 -> 0 | F15: =COUNTIFS(Transactions!$C$2:$C$114,A15,Transactions!$K$2:$K$114,"Y") -> 0 | G15: =COUNTIFS(CTR_Log!$A$2:$A$21,A15,CTR_Log!$F$2:$F$21,"YES") -> 0 | H15: =COUNTIFS(Transactions!$C$2:$C$114,A15,Transactions!$L$2:$L$114,">=3") -> 0 | I15: =SUMIFS(Transactions!$E$2:$E$114,Transactions!$C$2:$C$114,A15,Transactions!$D$2:$D$114,"Wire In") -> 99600 | J15: =SUMIFS(Transactions!$E$2:$E$114,Transactions!$C$2:$C$114,A15,Transactions!$D$2:$D$114,"Wire Out") -> 0 | K15: =IF(F15>=Assumptions!$B$7,1,0) -> 0 | L15: =IF(AND(D15>0,D15>E15*Assumptions!$B$8),1,0) -> 0 | M15: =IF(H15>0,1,0) -> 0 | N15: =IF(AND(Client_Master!N15="Y",I15+J15>=Assumptions!$B$11),1,0) -> 0 | O15: =IF(AND(I15>=Assumptions!$B$13,J15>=Assumptions!$B$13),IF(ABS(J15/I15-1)<=Assumptions!$B$12,1,0),0) -> 0 | P15: =IF(Client_Master!M15="Potential Match",1,0) -> 0 | Q15: =SUM(K15:P15) -> 0 | R15: =IF(OR(K15=1,M15=1,N15=1,P15=1,Q15>=2),"ESCALATE",IF(Q15=1,"Analyst Review","No Action")) -> No Action | S15: =TRIM(IF(K15=1,"R1 Structuring; ","")&IF(L15=1,"R2 Cash>Profile; ","")&IF(M15=1,"R3 High-Risk Jurisdiction; ","")&IF(N15=1,"R4 PEP Activity; ","")&IF(O15=1,"R5 Pass-through; ","")&IF(P15=1,"R6 Sanctions Hit; ",""))
A16: =Client_Master!A16 -> C015 | B16: =Client_Master!B16 -> Hollis Capital Partners LLP | C16: =Client_Master!H16 -> Medium | D16: =SUMIFS(Transactions!$E$2:$E$114,Transactions!$C$2:$C$114,A16,Transactions!$I$2:$I$114,"Y") -> 0 | E16: =Client_Master!O16*Assumptions!$B$9 -> 0 | F16: =COUNTIFS(Transactions!$C$2:$C$114,A16,Transactions!$K$2:$K$114,"Y") -> 0 | G16: =COUNTIFS(CTR_Log!$A$2:$A$21,A16,CTR_Log!$F$2:$F$21,"YES") -> 0 | H16: =COUNTIFS(Transactions!$C$2:$C$114,A16,Transactions!$L$2:$L$114,">=3") -> 0 | I16: =SUMIFS(Transactions!$E$2:$E$114,Transactions!$C$2:$C$114,A16,Transactions!$D$2:$D$114,"Wire In") -> 150000 | J16: =SUMIFS(Transactions!$E$2:$E$114,Transactions!$C$2:$C$114,A16,Transactions!$D$2:$D$114,"Wire Out") -> 90000 | K16: =IF(F16>=Assumptions!$B$7,1,0) -> 0 | L16: =IF(AND(D16>0,D16>E16*Assumptions!$B$8),1,0) -> 0 | M16: =IF(H16>0,1,0) -> 0 | N16: =IF(AND(Client_Master!N16="Y",I16+J16>=Assumptions!$B$11),1,0) -> 1 | O16: =IF(AND(I16>=Assumptions!$B$13,J16>=Assumptions!$B$13),IF(ABS(J16/I16-1)<=Assumptions!$B$12,1,0),0) -> 0 | P16: =IF(Client_Master!M16="Potential Match",1,0) -> 0 | Q16: =SUM(K16:P16) -> 1 | R16: =IF(OR(K16=1,M16=1,N16=1,P16=1,Q16>=2),"ESCALATE",IF(Q16=1,"Analyst Review","No Action")) -> ESCALATE | S16: =TRIM(IF(K16=1,"R1 Structuring; ","")&IF(L16=1,"R2 Cash>Profile; ","")&IF(M16=1,"R3 High-Risk Jurisdiction; ","")&IF(N16=1,"R4 PEP Activity; ","")&IF(O16=1,"R5 Pass-through; ","")&IF(P16=1,"R6 Sanctions Hit; ","")) -> R4 PEP Activity;
A17: =Client_Master!A17 -> C016 | B17: =Client_Master!B17 -> Bluewave Software Labs Inc | C17: =Client_Master!H17 -> Low | D17: =SUMIFS(Transactions!$E$2:$E$114,Transactions!$C$2:$C$114,A17,Transactions!$I$2:$I$114,"Y") -> 0 | E17: =Client_Master!O17*Assumptions!$B$9 -> 0 | F17: =COUNTIFS(Transactions!$C$2:$C$114,A17,Transactions!$K$2:$K$114,"Y") -> 0 | G17: =COUNTIFS(CTR_Log!$A$2:$A$21,A17,CTR_Log!$F$2:$F$21,"YES") -> 0 | H17: =COUNTIFS(Transactions!$C$2:$C$114,A17,Transactions!$L$2:$L$114,">=3") -> 0 | I17: =SUMIFS(Transactions!$E$2:$E$114,Transactions!$C$2:$C$114,A17,Transactions!$D$2:$D$114,"Wire In") -> 0 | J17: =SUMIFS(Transactions!$E$2:$E$114,Transactions!$C$2:$C$114,A17,Transactions!$D$2:$D$114,"Wire Out") -> 118500 | K17: =IF(F17>=Assumptions!$B$7,1,0) -> 0 | L17: =IF(AND(D17>0,D17>E17*Assumptions!$B$8),1,0) -> 0 | M17: =IF(H17>0,1,0) -> 0 | N17: =IF(AND(Client_Master!N17="Y",I17+J17>=Assumptions!$B$11),1,0) -> 0 | O17: =IF(AND(I17>=Assumptions!$B$13,J17>=Assumptions!$B$13),IF(ABS(J17/I17-1)<=Assumptions!$B$12,1,0),0) -> 0 | P17: =IF(Client_Master!M17="Potential Match",1,0) -> 0 | Q17: =SUM(K17:P17) -> 0 | R17: =IF(OR(K17=1,M17=1,N17=1,P17=1,Q17>=2),"ESCALATE",IF(Q17=1,"Analyst Review","No Action")) -> No Action | S17: =TRIM(IF(K17=1,"R1 Structuring; ","")&IF(L17=1,"R2 Cash>Profile; ","")&IF(M17=1,"R3 High-Risk Jurisdiction; ","")&IF(N17=1,"R4 PEP Activity; ","")&IF(O17=1,"R5 Pass-through; ","")&IF(P17=1,"R6 Sanctions Hit; ",""))
A18: =Client_Master!A18 -> C017 | B18: =Client_Master!B18 -> Evergreen Charitable Foundation | C18: =Client_Master!H18 -> Medium | D18: =SUMIFS(Transactions!$E$2:$E$114,Transactions!$C$2:$C$114,A18,Transactions!$I$2:$I$114,"Y") -> 0 | E18: =Client_Master!O18*Assumptions!$B$9 -> 0 | F18: =COUNTIFS(Transactions!$C$2:$C$114,A18,Transactions!$K$2:$K$114,"Y") -> 0 | G18: =COUNTIFS(CTR_Log!$A$2:$A$21,A18,CTR_Log!$F$2:$F$21,"YES") -> 0 | H18: =COUNTIFS(Transactions!$C$2:$C$114,A18,Transactions!$L$2:$L$114,">=3") -> 0 | I18: =SUMIFS(Transactions!$E$2:$E$114,Transactions!$C$2:$C$114,A18,Transactions!$D$2:$D$114,"Wire In") -> 159600 | J18: =SUMIFS(Transactions!$E$2:$E$114,Transactions!$C$2:$C$114,A18,Transactions!$D$2:$D$114,"Wire Out") -> 0 | K18: =IF(F18>=Assumptions!$B$7,1,0) -> 0 | L18: =IF(AND(D18>0,D18>E18*Assumptions!$B$8),1,0) -> 0 | M18: =IF(H18>0,1,0) -> 0 | N18: =IF(AND(Client_Master!N18="Y",I18+J18>=Assumptions!$B$11),1,0) -> 0 | O18: =IF(AND(I18>=Assumptions!$B$13,J18>=Assumptions!$B$13),IF(ABS(J18/I18-1)<=Assumptions!$B$12,1,0),0) -> 0 | P18: =IF(Client_Master!M18="Potential Match",1,0) -> 0 | Q18: =SUM(K18:P18) -> 0 | R18: =IF(OR(K18=1,M18=1,N18=1,P18=1,Q18>=2),"ESCALATE",IF(Q18=1,"Analyst Review","No Action")) -> No Action | S18: =TRIM(IF(K18=1,"R1 Structuring; ","")&IF(L18=1,"R2 Cash>Profile; ","")&IF(M18=1,"R3 High-Risk Jurisdiction; ","")&IF(N18=1,"R4 PEP Activity; ","")&IF(O18=1,"R5 Pass-through; ","")&IF(P18=1,"R6 Sanctions Hit; ",""))
A19: =Client_Master!A19 -> C018 | B19: =Client_Master!B19 -> Orion Freight Forwarders Pvt Ltd | C19: =Client_Master!H19 -> Low | D19: =SUMIFS(Transactions!$E$2:$E$114,Transactions!$C$2:$C$114,A19,Transactions!$I$2:$I$114,"Y") -> 0 | E19: =Client_Master!O19*Assumptions!$B$9 -> 0 | F19: =COUNTIFS(Transactions!$C$2:$C$114,A19,Transactions!$K$2:$K$114,"Y") -> 0 | G19: =COUNTIFS(CTR_Log!$A$2:$A$21,A19,CTR_Log!$F$2:$F$21,"YES") -> 0 | H19: =COUNTIFS(Transactions!$C$2:$C$114,A19,Transactions!$L$2:$L$114,">=3") -> 0 | I19: =SUMIFS(Transactions!$E$2:$E$114,Transactions!$C$2:$C$114,A19,Transactions!$D$2:$D$114,"Wire In") -> 86700 | J19: =SUMIFS(Transactions!$E$2:$E$114,Transactions!$C$2:$C$114,A19,Transactions!$D$2:$D$114,"Wire Out") -> 59900 | K19: =IF(F19>=Assumptions!$B$7,1,0) -> 0 | L19: =IF(AND(D19>0,D19>E19*Assumptions!$B$8),1,0) -> 0 | M19: =IF(H19>0,1,0) -> 0 | N19: =IF(AND(Client_Master!N19="Y",I19+J19>=Assumptions!$B$11),1,0) -> 0 | O19: =IF(AND(I19>=Assumptions!$B$13,J19>=Assumptions!$B$13),IF(ABS(J19/I19-1)<=Assumptions!$B$12,1,0),0) -> 0 | P19: =IF(Client_Master!M19="Potential Match",1,0) -> 0 | Q19: =SUM(K19:P19) -> 0 | R19: =IF(OR(K19=1,M19=1,N19=1,P19=1,Q19>=2),"ESCALATE",IF(Q19=1,"Analyst Review","No Action")) -> No Action | S19: =TRIM(IF(K19=1,"R1 Structuring; ","")&IF(L19=1,"R2 Cash>Profile; ","")&IF(M19=1,"R3 High-Risk Jurisdiction; ","")&IF(N19=1,"R4 PEP Activity; ","")&IF(O19=1,"R5 Pass-through; ","")&IF(P19=1,"R6 Sanctions Hit; ",""))
A20: =Client_Master!A20 -> C019 | B20: =Client_Master!B20 -> Metro Fuel & Convenience Stores Inc | C20: =Client_Master!H20 -> Low | D20: =SUMIFS(Transactions!$E$2:$E$114,Transactions!$C$2:$C$114,A20,Transactions!$I$2:$I$114,"Y") -> 45300 | E20: =Client_Master!O20*Assumptions!$B$9 -> 60000 | F20: =COUNTIFS(Transactions!$C$2:$C$114,A20,Transactions!$K$2:$K$114,"Y") -> 4 | G20: =COUNTIFS(CTR_Log!$A$2:$A$21,A20,CTR_Log!$F$2:$F$21,"YES") -> 0 | H20: =COUNTIFS(Transactions!$C$2:$C$114,A20,Transactions!$L$2:$L$114,">=3") -> 0 | I20: =SUMIFS(Transactions!$E$2:$E$114,Transactions!$C$2:$C$114,A20,Transactions!$D$2:$D$114,"Wire In") -> 0 | J20: =SUMIFS(Transactions!$E$2:$E$114,Transactions!$C$2:$C$114,A20,Transactions!$D$2:$D$114,"Wire Out") -> 0 | K20: =IF(F20>=Assumptions!$B$7,1,0) -> 1 | L20: =IF(AND(D20>0,D20>E20*Assumptions!$B$8),1,0) -> 0 | M20: =IF(H20>0,1,0) -> 0 | N20: =IF(AND(Client_Master!N20="Y",I20+J20>=Assumptions!$B$11),1,0) -> 0 | O20: =IF(AND(I20>=Assumptions!$B$13,J20>=Assumptions!$B$13),IF(ABS(J20/I20-1)<=Assumptions!$B$12,1,0),0) -> 0 | P20: =IF(Client_Master!M20="Potential Match",1,0) -> 0 | Q20: =SUM(K20:P20) -> 1 | R20: =IF(OR(K20=1,M20=1,N20=1,P20=1,Q20>=2),"ESCALATE",IF(Q20=1,"Analyst Review","No Action")) -> ESCALATE | S20: =TRIM(IF(K20=1,"R1 Structuring; ","")&IF(L20=1,"R2 Cash>Profile; ","")&IF(M20=1,"R3 High-Risk Jurisdiction; ","")&IF(N20=1,"R4 PEP Activity; ","")&IF(O20=1,"R5 Pass-through; ","")&IF(P20=1,"R6 Sanctions Hit; ","")) -> R1 Structuring;
... A41: =Client_Master!A41 -> C040 | B41: =Client_Master!B41 -> Orchid Textiles Pvt Ltd | C41: =Client_Master!H41 -> Low | D41: =SUMIFS(Transactions!$E$2:$E$114,Transactions!$C$2:$C$114,A41,Transactions!$I$2:$I$114,"Y") -> 0 | E41: =Client_Master!O41*Assumptions!$B$9 -> 0 | F41: =COUNTIFS(Transactions!$C$2:$C$114,A41,Transactions!$K$2:$K$114,"Y") -> 0 | G41: =COUNTIFS(CTR_Log!$A$2:$A$21,A41,CTR_Log!$F$2:$F$21,"YES") -> 0 | H41: =COUNTIFS(Transactions!$C$2:$C$114,A41,Transactions!$L$2:$L$114,">=3") -> 0 | I41: =SUMIFS(Transactions!$E$2:$E$114,Transactions!$C$2:$C$114,A41,Transactions!$D$2:$D$114,"Wire In") -> 89900 | J41: =SUMIFS(Transactions!$E$2:$E$114,Transactions!$C$2:$C$114,A41,Transactions!$D$2:$D$114,"Wire Out") -> 51500 | K41: =IF(F41>=Assumptions!$B$7,1,0) -> 0 | L41: =IF(AND(D41>0,D41>E41*Assumptions!$B$8),1,0) -> 0 | M41: =IF(H41>0,1,0) -> 0 | N41: =IF(AND(Client_Master!N41="Y",I41+J41>=Assumptions!$B$11),1,0) -> 0 | O41: =IF(AND(I41>=Assumptions!$B$13,J41>=Assumptions!$B$13),IF(ABS(J41/I41-1)<=Assumptions!$B$12,1,0),0) -> 0 | P41: =IF(Client_Master!M41="Potential Match",1,0) -> 0 | Q41: =SUM(K41:P41) -> 0 | R41: =IF(OR(K41=1,M41=1,N41=1,P41=1,Q41>=2),"ESCALATE",IF(Q41=1,"Analyst Review","No Action")) -> No Action | S41: =TRIM(IF(K41=1,"R1 Structuring; ","")&IF(L41=1,"R2 Cash>Profile; ","")&IF(M41=1,"R3 High-Risk Jurisdiction; ","")&IF(N41=1,"R4 PEP Activity; ","")&IF(O41=1,"R5 Pass-through; ","")&IF(P41=1,"R6 Sanctions Hit; ",""))

Sheet Escalation_Matrix
A1: Level | B1: Typical Triggers | C1: Required Action | D1: Escalate To | E1: SLA (business days) | F1: Documentation Required
A2: L1 - Analyst Review | B2: Single monitoring rule (R2, R5); data-quality exceptions; missing documents; rating mismatches. | C2: Review file, request missing documents via RM, correct record, document rationale. | D2: Team Lead / QC | E2: 3 | F2: Case note, document request log, updated KYC record.
A3: L2 - Compliance | B3: PEP activity; sanctions potential match; activity before KYC completion; account with no KYC record; late CTR. | C3: Refer with draft risk summary. Restrict activity where policy requires. Obtain senior-management sign-off where needed. | D3: Compliance (Middle Office) | E3: 5 | F3: Risk summary, supporting evidence, screening disposition, approval record.
A4: L3 - AML Investigations | B4: Structuring pattern; high-risk jurisdiction flows with no rationale; unexplained pass-through. | C4: Refer for investigation and Suspicious Activity/Transaction Report decision. Do NOT tip off the client. | D4: GFCC AML Investigations | E4: 10 | F4: Full transaction timeline, red-flag summary, KYC profile, prior alerts.
A6: Confidentiality reminder
A7: Escalations, STR/SAR decisions and investigation outcomes are confidential. Never disclose them to the client (tipping-off). Client-facing replies stay generic.

Sheet Escalation_Log
A1: Case ID | B1: Date Raised | C1: Client ID | D1: Client Name | E1: Trigger / Red Flag | F1: Analyst Risk Summary | G1: Escalation Level | H1: Escalated To | I1: SLA (business days) | J1: Date Closed | K1: Status | L1: Business Days Open | M1: SLA Status | N1: System Alert Disposition | O1: Outcome / Decision
A2: ESC-001 | B2: 46314 | C2: C019 | D2: =IFERROR(INDEX(Client_Master!$B$2:$B$41,MATCH(C2,Client_Master!$A$2:$A$41,0)),"UNKNOWN CLIENT") -> Metro Fuel & Convenience Stores Inc | E2: R1 - Structuring pattern | F2: Four cash deposits of $9,200-$9,800 (total $38,200) were made between 12 and 16 Oct, each just below the $10,000 CTR threshold. No single deposit triggered a CTR, but the clustering is consistent with possible structuring. Client is a low-risk retail business with a stated cash profile of $30,000 per month; no business reason for the pattern is documented. Referred for STR consideration. Client not contacted (tipping-off). | G2: L3 - AML Investigations | H2: GFCC AML Investigations | I2: =INDEX(Escalation_Matrix!$E$2:$E$4,MATCH(G2,Escalation_Matrix!$A$2:$A$4,0)) -> 10 | K2: =IF(ISNUMBER(J2),"Closed","Open") -> Open | L2: =NETWORKDAYS(B2,IF(ISNUMBER(J2),J2,Assumptions!$B$4))-1 -> 5 | M2: =IF(L2>I2,"SLA Breached","Within SLA") -> Within SLA | N2: =IFERROR(INDEX(Alert_Monitoring!$R$2:$R$41,MATCH(C2,Alert_Monitoring!$A$2:$A$41,0)),"N/A - not in CRM") -> ESCALATE | O2: Pending - STR/SAR decision by AML Investigations.
A3: ESC-002 | B3: 46303 | C3: C027 | D3: =IFERROR(INDEX(Client_Master!$B$2:$B$41,MATCH(C3,Client_Master!$A$2:$A$41,0)),"UNKNOWN CLIENT") -> Irrawaddy Trade Links Ltd | E3: R3 - Wires to high-risk jurisdiction | F3: Two outbound wires totalling $105,000 (29 Sep $45,000; 6 Oct $60,000) were sent to a counterparty in Myanmar, a score-3 country in this model. Client is an import/export trader assigned a Low rating although the model calculates Medium. No trade documents on file link the payments to goods. Enhanced due diligence and rating correction required. | G3: L3 - AML Investigations | H3: GFCC AML Investigations | I3: =INDEX(Escalation_Matrix!$E$2:$E$4,MATCH(G3,Escalation_Matrix!$A$2:$A$4,0)) -> 10 | K3: =IF(ISNUMBER(J3),"Closed","Open") -> Open | L3: =NETWORKDAYS(B3,IF(ISNUMBER(J3),J3,Assumptions!$B$4))-1 -> 12 | M3: =IF(L3>I3,"SLA Breached","Within SLA") -> SLA Breached | N3: =IFERROR(INDEX(Alert_Monitoring!$R$2:$R$41,MATCH(C3,Alert_Monitoring!$A$2:$A$41,0)),"N/A - not in CRM") -> ESCALATE | O3: Pending - trade documents requested via RM; rating correction raised.
A4: ESC-003 | B4: 46304 | C4: C015 | D4: =IFERROR(INDEX(Client_Master!$B$2:$B$41,MATCH(C4,Client_Master!$A$2:$A$41,0)),"UNKNOWN CLIENT") -> Hollis Capital Partners LLP | E4: R4 - PEP with high-value wires | F4: Client is a politically exposed person. Total wire activity of $240,000 in the window (inbound $150,000 from the UK on 1 Oct; outbound $90,000 to the Cayman Islands on 8 Oct) exceeds the $100,000 PEP review threshold. Policy requires documented source of wealth and senior-management approval. | G4: L2 - Compliance | H4: Compliance (Middle Office) | I4: =INDEX(Escalation_Matrix!$E$2:$E$4,MATCH(G4,Escalation_Matrix!$A$2:$A$4,0)) -> 5 | J4: 46310 | K4: =IF(ISNUMBER(J4),"Closed","Open") -> Closed | L4: =NETWORKDAYS(B4,IF(ISNUMBER(J4),J4,Assumptions!$B$4))-1 -> 4 | M4: =IF(L4>I4,"SLA Breached","Within SLA") -> Within SLA | N4: =IFERROR(INDEX(Alert_Monitoring!$R$2:$R$41,MATCH(C4,Alert_Monitoring!$A$2:$A$41,0)),"N/A - not in CRM") -> ESCALATE | O4: Closed - source-of-wealth evidence reviewed and consistent with profile; senior-management approval recorded; annual EDD review confirmed.
A5: ESC-004 | B5: 46301 | C5: C022 | D5: =IFERROR(INDEX(Client_Master!$B$2:$B$41,MATCH(C5,Client_Master!$A$2:$A$41,0)),"UNKNOWN CLIENT") -> Vantage Commodities Trading FZE | E5: R5 - Pass-through pattern | F5: Inbound wire of $250,000 (2 Oct) was followed within three days by an outbound wire of $246,500 (5 Oct) to Panama - about 98.6% of funds moved out. Rapid movement with no holding period can indicate pass-through activity, so supporting trade documents were requested. | G5: L2 - Compliance | H5: Compliance (Middle Office) | I5: =INDEX(Escalation_Matrix!$E$2:$E$4,MATCH(G5,Escalation_Matrix!$A$2:$A$4,0)) -> 5 | J5: 46308 | K5: =IF(ISNUMBER(J5),"Closed","Open") -> Closed | L5: =NETWORKDAYS(B5,IF(ISNUMBER(J5),J5,Assumptions!$B$4))-1 -> 5 | M5: =IF(L5>I5,"SLA Breached","Within SLA") -> Within SLA | N5: =IFERROR(INDEX(Alert_Monitoring!$R$2:$R$41,MATCH(C5,Alert_Monitoring!$A$2:$A$41,0)),"N/A - not in CRM") -> Analyst Review | O5: Closed - invoices and shipping documents obtained; activity consistent with commodity trading cycle. Added to 90-day enhanced monitoring.
A6: ESC-005 | B6: 46315 | C6: C036 | D6: =IFERROR(INDEX(Client_Master!$B$2:$B$41,MATCH(C6,Client_Master!$A$2:$A$41,0)),"UNKNOWN CLIENT") -> Baltic Star Shipping Ltd | E6: R6 - Sanctions screening potential match | F6: Name screening returned a potential match to a watchlist entry. Registered address and incorporation number differ from the listed entity, which points to a false positive, but the disposition is not yet documented. The client has an active account. | G6: L2 - Compliance | H6: Compliance (Middle Office) | I6: =INDEX(Escalation_Matrix!$E$2:$E$4,MATCH(G6,Escalation_Matrix!$A$2:$A$4,0)) -> 5 | K6: =IF(ISNUMBER(J6),"Closed","Open") -> Open | L6: =NETWORKDAYS(B6,IF(ISNUMBER(J6),J6,Assumptions!$B$4))-1 -> 4 | M6: =IF(L6>I6,"SLA Breached","Within SLA") -> Within SLA | N6: =IFERROR(INDEX(Alert_Monitoring!$R$2:$R$41,MATCH(C6,Alert_Monitoring!$A$2:$A$41,0)),"N/A - not in CRM") -> ESCALATE | O6: Pending - registry extract requested to discount the match.
A7: ESC-006 | B7: 46321 | C7: C008 | D7: =IFERROR(INDEX(Client_Master!$B$2:$B$41,MATCH(C7,Client_Master!$A$2:$A$41,0)),"UNKNOWN CLIENT") -> Golden Crest Jewellers LLC | E7: Late CTR + cash above profile + rating mismatch | F7: The $27,000 cash deposit on 8 Oct required a CTR by 23 Oct and has not been filed. Total cash of $85,000 in the window exceeds the stated profile of $20,000 per month. Assigned rating (Low) is below the model rating (Medium) for a jewellery business in the UAE. | G7: L2 - Compliance | H7: Compliance (Middle Office) | I7: =INDEX(Escalation_Matrix!$E$2:$E$4,MATCH(G7,Escalation_Matrix!$A$2:$A$4,0)) -> 5 | K7: =IF(ISNUMBER(J7),"Closed","Open") -> Open | L7: =NETWORKDAYS(B7,IF(ISNUMBER(J7),J7,Assumptions!$B$4))-1 -> 0 | M7: =IF(L7>I7,"SLA Breached","Within SLA") -> Within SLA | N7: =IFERROR(INDEX(Alert_Monitoring!$R$2:$R$41,MATCH(C7,Alert_Monitoring!$A$2:$A$41,0)),"N/A - not in CRM") -> Analyst Review | O7: Pending - file CTR and document late-filing reason; rating review raised.
A8: ESC-007 | B8: 46317 | C8: C041 | D8: =IFERROR(INDEX(Client_Master!$B$2:$B$41,MATCH(C8,Client_Master!$A$2:$A$41,0)),"UNKNOWN CLIENT") -> UNKNOWN CLIENT | E8: Active account with no KYC record | F8: Core banking shows an active account for C041 with a $7,800 cash deposit (9 Oct) and a $52,000 inbound wire (14 Oct), but there is no client record in the KYC system. Activity is taking place with no CIP/CDD on file. | G8: L2 - Compliance | H8: Compliance (Middle Office) | I8: =INDEX(Escalation_Matrix!$E$2:$E$4,MATCH(G8,Escalation_Matrix!$A$2:$A$4,0)) -> 5 | K8: =IF(ISNUMBER(J8),"Closed","Open") -> Open | L8: =NETWORKDAYS(B8,IF(ISNUMBER(J8),J8,Assumptions!$B$4))-1 -> 2 | M8: =IF(L8>I8,"SLA Breached","Within SLA") -> Within SLA | N8: =IFERROR(INDEX(Alert_Monitoring!$R$2:$R$41,MATCH(C8,Alert_Monitoring!$A$2:$A$41,0)),"N/A - not in CRM") -> N/A - not in CRM | O8: Pending - account restriction requested; KYC onboarding file to be traced.
A9: ESC-008 | B9: 46314 | C9: C038 | D9: =IFERROR(INDEX(Client_Master!$B$2:$B$41,MATCH(C9,Client_Master!$A$2:$A$41,0)),"UNKNOWN CLIENT") -> Zenith Wellness Clinics Pvt Ltd | E9: Activity before KYC completion | F9: New client onboarded 1 Oct. Sanctions screening is not done and CIP and UBO documents are outstanding, yet a $40,000 inbound wire was received on 15 Oct. | G9: L2 - Compliance | H9: Compliance (Middle Office) | I9: =INDEX(Escalation_Matrix!$E$2:$E$4,MATCH(G9,Escalation_Matrix!$A$2:$A$4,0)) -> 5 | K9: =IF(ISNUMBER(J9),"Closed","Open") -> Open | L9: =NETWORKDAYS(B9,IF(ISNUMBER(J9),J9,Assumptions!$B$4))-1 -> 5 | M9: =IF(L9>I9,"SLA Breached","Within SLA") -> Within SLA | N9: =IFERROR(INDEX(Alert_Monitoring!$R$2:$R$41,MATCH(C9,Alert_Monitoring!$A$2:$A$41,0)),"N/A - not in CRM") -> No Action | O9: Pending - documents chased via RM; funds held pending completion.
A10: ESC-009 | B10: 46317 | C10: C017 | D10: =IFERROR(INDEX(Client_Master!$B$2:$B$41,MATCH(C10,Client_Master!$A$2:$A$41,0)),"UNKNOWN CLIENT") -> Evergreen Charitable Foundation | E10: Beneficial owner not identified | F10: KYC file shows the ultimate beneficial owner (UBO) is not identified while the account is active and transacting. | G10: L1 - Analyst Review | H10: Team Lead / QC | I10: =INDEX(Escalation_Matrix!$E$2:$E$4,MATCH(G10,Escalation_Matrix!$A$2:$A$4,0)) -> 3 | K10: =IF(ISNUMBER(J10),"Closed","Open") -> Open | L10: =NETWORKDAYS(B10,IF(ISNUMBER(J10),J10,Assumptions!$B$4))-1 -> 2 | M10: =IF(L10>I10,"SLA Breached","Within SLA") -> Within SLA | N10: =IFERROR(INDEX(Alert_Monitoring!$R$2:$R$41,MATCH(C10,Alert_Monitoring!$A$2:$A$41,0)),"N/A - not in CRM") -> No Action | O10: Pending - UBO declaration requested via RM.
A11: ESC-010 | B11: 46316 | C11: C031 | D11: =IFERROR(INDEX(Client_Master!$B$2:$B$41,MATCH(C11,Client_Master!$A$2:$A$41,0)),"UNKNOWN CLIENT") -> Meridian Textile Exports Pvt Ltd | E11: Duplicate client record | F11: Legal name on C031 is identical to C006 with different IDs. Risk of split history and missed monitoring. | G11: L1 - Analyst Review | H11: Team Lead / QC | I11: =INDEX(Escalation_Matrix!$E$2:$E$4,MATCH(G11,Escalation_Matrix!$A$2:$A$4,0)) -> 3 | K11: =IF(ISNUMBER(J11),"Closed","Open") -> Open | L11: =NETWORKDAYS(B11,IF(ISNUMBER(J11),J11,Assumptions!$B$4))-1 -> 3 | M11: =IF(L11>I11,"SLA Breached","Within SLA") -> Within SLA | N11: =IFERROR(INDEX(Alert_Monitoring!$R$2:$R$41,MATCH(C11,Alert_Monitoring!$A$2:$A$41,0)),"N/A - not in CRM") -> No Action | O11: Pending - merge request raised to client data team.

Sheet Src_CoreBanking
A1: Client ID | B1: Legal Name (Core Banking) | C1: Country | D1: Risk Rating | E1: Account Status
A2: C001 | B2: Aurora Software Solutions Pvt Ltd | C2: India | D2: Low | E2: Active
A3: C002 | B3: Nordic Precision Manufacturing GmbH | C3: Germany | D3: Low | E3: Active
A4: C003 | B4: Lotus Healthcare Systems Limited | C4: India | D4: Low | E4: Active
A5: C004 | B5: Thames Consulting Partners LLP | C5: United Kingdom | D5: Low | E5: Active
A6: C005 | B6: Spice Route Restaurants Group Inc | C6: United States | D6: Low | E6: Active
A7: C006 | B7: Meridian Textile Exports Pvt Ltd | C7: India | D7: Low | E7: Active
A8: C007 | B8: Alpine Logistics AG | C8: Switzerland | D8: Low | E8: Active
A9: C008 | B9: Golden Crest Jewellers LLC | C9: United Arab Emirates | D9: Low | E9: Active
A10: C009 | B10: Pinnacle Realty Developers Ltd | C10: Singapore | D10: Medium | E10: Active
A11: C010 | B11: Harbour Point Trading Co | C11: Singapore | D11: Medium | E11: Active
A12: C011 | B12: Coral Reef Gaming Ltd | C12: Cayman Islands | D12: Medium | E12: Active
... A41: C041 | B41: Oakridge Holdings Inc | C41: United States | D41: Low | E41: Active

Sheet Src_BankStatement
A1: Txn ID (Statement) | B1: Value Date | C1: Amount (USD)
A2: T0001 | B2: 46266 | C2: 17665
A3: T0002 | B3: 46266 | C3: 78700
A4: T0004 | B4: 46267 | C4: 54100
A5: T0005 | B5: 46267 | C5: 28500
A6: T0006 | B6: 46268 | C6: 44400
A7: T0007 | B7: 46268 | C7: 31900
A8: T0009 | B8: 46269 | C8: 66000
A9: T0010 | B9: 46269 | C9: 79700
A10: T0011 | B10: 46272 | C10: 80982
A11: T0012 | B11: 46272 | C11: 75900
A12: T0013 | B12: 46273 | C12: 59900
A13: T0013 | B13: 46273 | C13: 59900
... A114: T9901 | B114: 46316 | C114: 3200

Sheet Recon_Client
A1: Client ID | B1: CRM Name | C1: Core Banking Name | D1: Name Check | E1: CRM Country | F1: Core Country | G1: Country Check | H1: CRM Risk Rating | I1: Core Risk Rating | J1: Rating Check | K1: Core Account Status | L1: CRM File Status | M1: Overall Recon Status | N1: Control Flag
A2: C001 | B2: =IFERROR(INDEX(Client_Master!$B$2:$B$41,MATCH(A2,Client_Master!$A$2:$A$41,0)),"") -> Aurora Software Solutions Pvt Ltd | C2: =IFERROR(INDEX(Src_CoreBanking!$B$2:$B$41,MATCH(A2,Src_CoreBanking!$A$2:$A$41,0)),"") -> Aurora Software Solutions Pvt Ltd | D2: =IF(B2="","Missing in CRM",IF(C2="","Missing in Core",IF(TRIM(UPPER(B2))=TRIM(UPPER(C2)),"Match","Break"))) -> Match | E2: =IFERROR(INDEX(Client_Master!$D$2:$D$41,MATCH(A2,Client_Master!$A$2:$A$41,0)),"") -> India | F2: =IFERROR(INDEX(Src_CoreBanking!$C$2:$C$41,MATCH(A2,Src_CoreBanking!$A$2:$A$41,0)),"") -> India | G2: =IF(OR(E2="",F2=""),"n/a",IF(E2=F2,"Match","Break")) -> Match | H2: =IFERROR(INDEX(Client_Master!$H$2:$H$41,MATCH(A2,Client_Master!$A$2:$A$41,0)),"") -> Low | I2: =IFERROR(INDEX(Src_CoreBanking!$D$2:$D$41,MATCH(A2,Src_CoreBanking!$A$2:$A$41,0)),"") -> Low | J2: =IF(OR(H2="",I2=""),"n/a",IF(H2=I2,"Match","Break")) -> Match | K2: =IFERROR(INDEX(Src_CoreBanking!$E$2:$E$41,MATCH(A2,Src_CoreBanking!$A$2:$A$41,0)),"") -> Active | L2: =IFERROR(INDEX(Client_Master!$R$2:$R$41,MATCH(A2,Client_Master!$A$2:$A$41,0)),"") -> Complete | M2: =IF(OR(D2="Missing in CRM",D2="Missing in Core"),D2,IF(AND(D2="Match",G2="Match",J2="Match"),"Reconciled",TRIM("Break: "&IF(D2<>"Match","Name ","")&IF(G2<>"Match","Country ","")&IF(J2<>"Match","Rating","")))) -> Reconciled | N2: =IF(AND(K2="Active",L2<>"",L2<>"Complete"),"Active account - KYC incomplete",IF(AND(K2="Active",L2=""),"Active account - no KYC record",""))
A3: C002 | B3: =IFERROR(INDEX(Client_Master!$B$2:$B$41,MATCH(A3,Client_Master!$A$2:$A$41,0)),"") -> Nordic Precision Manufacturing GmbH | C3: =IFERROR(INDEX(Src_CoreBanking!$B$2:$B$41,MATCH(A3,Src_CoreBanking!$A$2:$A$41,0)),"") -> Nordic Precision Manufacturing GmbH | D3: =IF(B3="","Missing in CRM",IF(C3="","Missing in Core",IF(TRIM(UPPER(B3))=TRIM(UPPER(C3)),"Match","Break"))) -> Match | E3: =IFERROR(INDEX(Client_Master!$D$2:$D$41,MATCH(A3,Client_Master!$A$2:$A$41,0)),"") -> Germany | F3: =IFERROR(INDEX(Src_CoreBanking!$C$2:$C$41,MATCH(A3,Src_CoreBanking!$A$2:$A$41,0)),"") -> Germany | G3: =IF(OR(E3="",F3=""),"n/a",IF(E3=F3,"Match","Break")) -> Match | H3: =IFERROR(INDEX(Client_Master!$H$2:$H$41,MATCH(A3,Client_Master!$A$2:$A$41,0)),"") -> Low | I3: =IFERROR(INDEX(Src_CoreBanking!$D$2:$D$41,MATCH(A3,Src_CoreBanking!$A$2:$A$41,0)),"") -> Low | J3: =IF(OR(H3="",I3=""),"n/a",IF(H3=I3,"Match","Break")) -> Match | K3: =IFERROR(INDEX(Src_CoreBanking!$E$2:$E$41,MATCH(A3,Src_CoreBanking!$A$2:$A$41,0)),"") -> Active | L3: =IFERROR(INDEX(Client_Master!$R$2:$R$41,MATCH(A3,Client_Master!$A$2:$A$41,0)),"") -> Complete | M3: =IF(OR(D3="Missing in CRM",D3="Missing in Core"),D3,IF(AND(D3="Match",G3="Match",J3="Match"),"Reconciled",TRIM("Break: "&IF(D3<>"Match","Name ","")&IF(G3<>"Match","Country ","")&IF(J3<>"Match","Rating","")))) -> Reconciled | N3: =IF(AND(K3="Active",L3<>"",L3<>"Complete"),"Active account - KYC incomplete",IF(AND(K3="Active",L3=""),"Active account - no KYC record",""))
A4: C003 | B4: =IFERROR(INDEX(Client_Master!$B$2:$B$41,MATCH(A4,Client_Master!$A$2:$A$41,0)),"") -> Lotus Healthcare Systems Ltd | C4: =IFERROR(INDEX(Src_CoreBanking!$B$2:$B$41,MATCH(A4,Src_CoreBanking!$A$2:$A$41,0)),"") -> Lotus Healthcare Systems Limited | D4: =IF(B4="","Missing in CRM",IF(C4="","Missing in Core",IF(TRIM(UPPER(B4))=TRIM(UPPER(C4)),"Match","Break"))) -> Break | E4: =IFERROR(INDEX(Client_Master!$D$2:$D$41,MATCH(A4,Client_Master!$A$2:$A$41,0)),"") -> India | F4: =IFERROR(INDEX(Src_CoreBanking!$C$2:$C$41,MATCH(A4,Src_CoreBanking!$A$2:$A$41,0)),"") -> India | G4: =IF(OR(E4="",F4=""),"n/a",IF(E4=F4,"Match","Break")) -> Match | H4: =IFERROR(INDEX(Client_Master!$H$2:$H$41,MATCH(A4,Client_Master!$A$2:$A$41,0)),"") -> Low | I4: =IFERROR(INDEX(Src_CoreBanking!$D$2:$D$41,MATCH(A4,Src_CoreBanking!$A$2:$A$41,0)),"") -> Low | J4: =IF(OR(H4="",I4=""),"n/a",IF(H4=I4,"Match","Break")) -> Match | K4: =IFERROR(INDEX(Src_CoreBanking!$E$2:$E$41,MATCH(A4,Src_CoreBanking!$A$2:$A$41,0)),"") -> Active | L4: =IFERROR(INDEX(Client_Master!$R$2:$R$41,MATCH(A4,Client_Master!$A$2:$A$41,0)),"") -> Complete | M4: =IF(OR(D4="Missing in CRM",D4="Missing in Core"),D4,IF(AND(D4="Match",G4="Match",J4="Match"),"Reconciled",TRIM("Break: "&IF(D4<>"Match","Name ","")&IF(G4<>"Match","Country ","")&IF(J4<>"Match","Rating","")))) -> Break: Name | N4: =IF(AND(K4="Active",L4<>"",L4<>"Complete"),"Active account - KYC incomplete",IF(AND(K4="Active",L4=""),"Active account - no KYC record",""))
A5: C004 | B5: =IFERROR(INDEX(Client_Master!$B$2:$B$41,MATCH(A5,Client_Master!$A$2:$A$41,0)),"") -> Thames Consulting Partners LLP | C5: =IFERROR(INDEX(Src_CoreBanking!$B$2:$B$41,MATCH(A5,Src_CoreBanking!$A$2:$A$41,0)),"") -> Thames Consulting Partners LLP | D5: =IF(B5="","Missing in CRM",IF(C5="","Missing in Core",IF(TRIM(UPPER(B5))=TRIM(UPPER(C5)),"Match","Break"))) -> Match | E5: =IFERROR(INDEX(Client_Master!$D$2:$D$41,MATCH(A5,Client_Master!$A$2:$A$41,0)),"") -> United Kingdom | F5: =IFERROR(INDEX(Src_CoreBanking!$C$2:$C$41,MATCH(A5,Src_CoreBanking!$A$2:$A$41,0)),"") -> United Kingdom | G5: =IF(OR(E5="",F5=""),"n/a",IF(E5=F5,"Match","Break")) -> Match | H5: =IFERROR(INDEX(Client_Master!$H$2:$H$41,MATCH(A5,Client_Master!$A$2:$A$41,0)),"") -> Low | I5: =IFERROR(INDEX(Src_CoreBanking!$D$2:$D$41,MATCH(A5,Src_CoreBanking!$A$2:$A$41,0)),"") -> Low | J5: =IF(OR(H5="",I5=""),"n/a",IF(H5=I5,"Match","Break")) -> Match | K5: =IFERROR(INDEX(Src_CoreBanking!$E$2:$E$41,MATCH(A5,Src_CoreBanking!$A$2:$A$41,0)),"") -> Active | L5: =IFERROR(INDEX(Client_Master!$R$2:$R$41,MATCH(A5,Client_Master!$A$2:$A$41,0)),"") -> Complete | M5: =IF(OR(D5="Missing in CRM",D5="Missing in Core"),D5,IF(AND(D5="Match",G5="Match",J5="Match"),"Reconciled",TRIM("Break: "&IF(D5<>"Match","Name ","")&IF(G5<>"Match","Country ","")&IF(J5<>"Match","Rating","")))) -> Reconciled | N5: =IF(AND(K5="Active",L5<>"",L5<>"Complete"),"Active account - KYC incomplete",IF(AND(K5="Active",L5=""),"Active account - no KYC record",""))
A6: C005 | B6: =IFERROR(INDEX(Client_Master!$B$2:$B$41,MATCH(A6,Client_Master!$A$2:$A$41,0)),"") -> Spice Route Restaurants Group Inc | C6: =IFERROR(INDEX(Src_CoreBanking!$B$2:$B$41,MATCH(A6,Src_CoreBanking!$A$2:$A$41,0)),"") -> Spice Route Restaurants Group Inc | D6: =IF(B6="","Missing in CRM",IF(C6="","Missing in Core",IF(TRIM(UPPER(B6))=TRIM(UPPER(C6)),"Match","Break"))) -> Match | E6: =IFERROR(INDEX(Client_Master!$D$2:$D$41,MATCH(A6,Client_Master!$A$2:$A$41,0)),"") -> United States | F6: =IFERROR(INDEX(Src_CoreBanking!$C$2:$C$41,MATCH(A6,Src_CoreBanking!$A$2:$A$41,0)),"") -> United States | G6: =IF(OR(E6="",F6=""),"n/a",IF(E6=F6,"Match","Break")) -> Match | H6: =IFERROR(INDEX(Client_Master!$H$2:$H$41,MATCH(A6,Client_Master!$A$2:$A$41,0)),"") -> Low | I6: =IFERROR(INDEX(Src_CoreBanking!$D$2:$D$41,MATCH(A6,Src_CoreBanking!$A$2:$A$41,0)),"") -> Low | J6: =IF(OR(H6="",I6=""),"n/a",IF(H6=I6,"Match","Break")) -> Match | K6: =IFERROR(INDEX(Src_CoreBanking!$E$2:$E$41,MATCH(A6,Src_CoreBanking!$A$2:$A$41,0)),"") -> Active | L6: =IFERROR(INDEX(Client_Master!$R$2:$R$41,MATCH(A6,Client_Master!$A$2:$A$41,0)),"") -> Complete | M6: =IF(OR(D6="Missing in CRM",D6="Missing in Core"),D6,IF(AND(D6="Match",G6="Match",J6="Match"),"Reconciled",TRIM("Break: "&IF(D6<>"Match","Name ","")&IF(G6<>"Match","Country ","")&IF(J6<>"Match","Rating","")))) -> Reconciled | N6: =IF(AND(K6="Active",L6<>"",L6<>"Complete"),"Active account - KYC incomplete",IF(AND(K6="Active",L6=""),"Active account - no KYC record",""))
A7: C006 | B7: =IFERROR(INDEX(Client_Master!$B$2:$B$41,MATCH(A7,Client_Master!$A$2:$A$41,0)),"") -> Meridian Textile Exports Pvt Ltd | C7: =IFERROR(INDEX(Src_CoreBanking!$B$2:$B$41,MATCH(A7,Src_CoreBanking!$A$2:$A$41,0)),"") -> Meridian Textile Exports Pvt Ltd | D7: =IF(B7="","Missing in CRM",IF(C7="","Missing in Core",IF(TRIM(UPPER(B7))=TRIM(UPPER(C7)),"Match","Break"))) -> Match | E7: =IFERROR(INDEX(Client_Master!$D$2:$D$41,MATCH(A7,Client_Master!$A$2:$A$41,0)),"") -> India | F7: =IFERROR(INDEX(Src_CoreBanking!$C$2:$C$41,MATCH(A7,Src_CoreBanking!$A$2:$A$41,0)),"") -> India | G7: =IF(OR(E7="",F7=""),"n/a",IF(E7=F7,"Match","Break")) -> Match | H7: =IFERROR(INDEX(Client_Master!$H$2:$H$41,MATCH(A7,Client_Master!$A$2:$A$41,0)),"") -> Low | I7: =IFERROR(INDEX(Src_CoreBanking!$D$2:$D$41,MATCH(A7,Src_CoreBanking!$A$2:$A$41,0)),"") -> Low | J7: =IF(OR(H7="",I7=""),"n/a",IF(H7=I7,"Match","Break")) -> Match | K7: =IFERROR(INDEX(Src_CoreBanking!$E$2:$E$41,MATCH(A7,Src_CoreBanking!$A$2:$A$41,0)),"") -> Active | L7: =IFERROR(INDEX(Client_Master!$R$2:$R$41,MATCH(A7,Client_Master!$A$2:$A$41,0)),"") -> Complete | M7: =IF(OR(D7="Missing in CRM",D7="Missing in Core"),D7,IF(AND(D7="Match",G7="Match",J7="Match"),"Reconciled",TRIM("Break: "&IF(D7<>"Match","Name ","")&IF(G7<>"Match","Country ","")&IF(J7<>"Match","Rating","")))) -> Reconciled | N7: =IF(AND(K7="Active",L7<>"",L7<>"Complete"),"Active account - KYC incomplete",IF(AND(K7="Active",L7=""),"Active account - no KYC record",""))
A8: C007 | B8: =IFERROR(INDEX(Client_Master!$B$2:$B$41,MATCH(A8,Client_Master!$A$2:$A$41,0)),"") -> Alpine Logistics AG | C8: =IFERROR(INDEX(Src_CoreBanking!$B$2:$B$41,MATCH(A8,Src_CoreBanking!$A$2:$A$41,0)),"") -> Alpine Logistics AG | D8: =IF(B8="","Missing in CRM",IF(C8="","Missing in Core",IF(TRIM(UPPER(B8))=TRIM(UPPER(C8)),"Match","Break"))) -> Match | E8: =IFERROR(INDEX(Client_Master!$D$2:$D$41,MATCH(A8,Client_Master!$A$2:$A$41,0)),"") -> Switzerland | F8: =IFERROR(INDEX(Src_CoreBanking!$C$2:$C$41,MATCH(A8,Src_CoreBanking!$A$2:$A$41,0)),"") -> Switzerland | G8: =IF(OR(E8="",F8=""),"n/a",IF(E8=F8,"Match","Break")) -> Match | H8: =IFERROR(INDEX(Client_Master!$H$2:$H$41,MATCH(A8,Client_Master!$A$2:$A$41,0)),"") -> Low | I8: =IFERROR(INDEX(Src_CoreBanking!$D$2:$D$41,MATCH(A8,Src_CoreBanking!$A$2:$A$41,0)),"") -> Low | J8: =IF(OR(H8="",I8=""),"n/a",IF(H8=I8,"Match","Break")) -> Match | K8: =IFERROR(INDEX(Src_CoreBanking!$E$2:$E$41,MATCH(A8,Src_CoreBanking!$A$2:$A$41,0)),"") -> Active | L8: =IFERROR(INDEX(Client_Master!$R$2:$R$41,MATCH(A8,Client_Master!$A$2:$A$41,0)),"") -> Complete | M8: =IF(OR(D8="Missing in CRM",D8="Missing in Core"),D8,IF(AND(D8="Match",G8="Match",J8="Match"),"Reconciled",TRIM("Break: "&IF(D8<>"Match","Name ","")&IF(G8<>"Match","Country ","")&IF(J8<>"Match","Rating","")))) -> Reconciled | N8: =IF(AND(K8="Active",L8<>"",L8<>"Complete"),"Active account - KYC incomplete",IF(AND(K8="Active",L8=""),"Active account - no KYC record",""))
A9: C008 | B9: =IFERROR(INDEX(Client_Master!$B$2:$B$41,MATCH(A9,Client_Master!$A$2:$A$41,0)),"") -> Golden Crest Jewellers LLC | C9: =IFERROR(INDEX(Src_CoreBanking!$B$2:$B$41,MATCH(A9,Src_CoreBanking!$A$2:$A$41,0)),"") -> Golden Crest Jewellers LLC | D9: =IF(B9="","Missing in CRM",IF(C9="","Missing in Core",IF(TRIM(UPPER(B9))=TRIM(UPPER(C9)),"Match","Break"))) -> Match | E9: =IFERROR(INDEX(Client_Master!$D$2:$D$41,MATCH(A9,Client_Master!$A$2:$A$41,0)),"") -> United Arab Emirates | F9: =IFERROR(INDEX(Src_CoreBanking!$C$2:$C$41,MATCH(A9,Src_CoreBanking!$A$2:$A$41,0)),"") -> United Arab Emirates | G9: =IF(OR(E9="",F9=""),"n/a",IF(E9=F9,"Match","Break")) -> Match | H9: =IFERROR(INDEX(Client_Master!$H$2:$H$41,MATCH(A9,Client_Master!$A$2:$A$41,0)),"") -> Low | I9: =IFERROR(INDEX(Src_CoreBanking!$D$2:$D$41,MATCH(A9,Src_CoreBanking!$A$2:$A$41,0)),"") -> Low | J9: =IF(OR(H9="",I9=""),"n/a",IF(H9=I9,"Match","Break")) -> Match | K9: =IFERROR(INDEX(Src_CoreBanking!$E$2:$E$41,MATCH(A9,Src_CoreBanking!$A$2:$A$41,0)),"") -> Active | L9: =IFERROR(INDEX(Client_Master!$R$2:$R$41,MATCH(A9,Client_Master!$A$2:$A$41,0)),"") -> Complete | M9: =IF(OR(D9="Missing in CRM",D9="Missing in Core"),D9,IF(AND(D9="Match",G9="Match",J9="Match"),"Reconciled",TRIM("Break: "&IF(D9<>"Match","Name ","")&IF(G9<>"Match","Country ","")&IF(J9<>"Match","Rating","")))) -> Reconciled | N9: =IF(AND(K9="Active",L9<>"",L9<>"Complete"),"Active account - KYC incomplete",IF(AND(K9="Active",L9=""),"Active account - no KYC record",""))
A10: C009 | B10: =IFERROR(INDEX(Client_Master!$B$2:$B$41,MATCH(A10,Client_Master!$A$2:$A$41,0)),"") -> Pinnacle Realty Developers Ltd | C10: =IFERROR(INDEX(Src_CoreBanking!$B$2:$B$41,MATCH(A10,Src_CoreBanking!$A$2:$A$41,0)),"") -> Pinnacle Realty Developers Ltd | D10: =IF(B10="","Missing in CRM",IF(C10="","Missing in Core",IF(TRIM(UPPER(B10))=TRIM(UPPER(C10)),"Match","Break"))) -> Match | E10: =IFERROR(INDEX(Client_Master!$D$2:$D$41,MATCH(A10,Client_Master!$A$2:$A$41,0)),"") -> Singapore | F10: =IFERROR(INDEX(Src_CoreBanking!$C$2:$C$41,MATCH(A10,Src_CoreBanking!$A$2:$A$41,0)),"") -> Singapore | G10: =IF(OR(E10="",F10=""),"n/a",IF(E10=F10,"Match","Break")) -> Match | H10: =IFERROR(INDEX(Client_Master!$H$2:$H$41,MATCH(A10,Client_Master!$A$2:$A$41,0)),"") -> Medium | I10: =IFERROR(INDEX(Src_CoreBanking!$D$2:$D$41,MATCH(A10,Src_CoreBanking!$A$2:$A$41,0)),"") -> Medium | J10: =IF(OR(H10="",I10=""),"n/a",IF(H10=I10,"Match","Break")) -> Match | K10: =IFERROR(INDEX(Src_CoreBanking!$E$2:$E$41,MATCH(A10,Src_CoreBanking!$A$2:$A$41,0)),"") -> Active | L10: =IFERROR(INDEX(Client_Master!$R$2:$R$41,MATCH(A10,Client_Master!$A$2:$A$41,0)),"") -> Complete | M10: =IF(OR(D10="Missing in CRM",D10="Missing in Core"),D10,IF(AND(D10="Match",G10="Match",J10="Match"),"Reconciled",TRIM("Break: "&IF(D10<>"Match","Name ","")&IF(G10<>"Match","Country ","")&IF(J10<>"Match","Rating","")))) -> Reconciled | N10: =IF(AND(K10="Active",L10<>"",L10<>"Complete"),"Active account - KYC incomplete",IF(AND(K10="Active",L10=""),"Active account - no KYC record",""))
A11: C010 | B11: =IFERROR(INDEX(Client_Master!$B$2:$B$41,MATCH(A11,Client_Master!$A$2:$A$41,0)),"") -> Harbour Point Trading Co | C11: =IFERROR(INDEX(Src_CoreBanking!$B$2:$B$41,MATCH(A11,Src_CoreBanking!$A$2:$A$41,0)),"") -> Harbour Point Trading Co | D11: =IF(B11="","Missing in CRM",IF(C11="","Missing in Core",IF(TRIM(UPPER(B11))=TRIM(UPPER(C11)),"Match","Break"))) -> Match | E11: =IFERROR(INDEX(Client_Master!$D$2:$D$41,MATCH(A11,Client_Master!$A$2:$A$41,0)),"") -> Hong Kong | F11: =IFERROR(INDEX(Src_CoreBanking!$C$2:$C$41,MATCH(A11,Src_CoreBanking!$A$2:$A$41,0)),"") -> Singapore | G11: =IF(OR(E11="",F11=""),"n/a",IF(E11=F11,"Match","Break")) -> Break | H11: =IFERROR(INDEX(Client_Master!$H$2:$H$41,MATCH(A11,Client_Master!$A$2:$A$41,0)),"") -> Medium | I11: =IFERROR(INDEX(Src_CoreBanking!$D$2:$D$41,MATCH(A11,Src_CoreBanking!$A$2:$A$41,0)),"") -> Medium | J11: =IF(OR(H11="",I11=""),"n/a",IF(H11=I11,"Match","Break")) -> Match | K11: =IFERROR(INDEX(Src_CoreBanking!$E$2:$E$41,MATCH(A11,Src_CoreBanking!$A$2:$A$41,0)),"") -> Active | L11: =IFERROR(INDEX(Client_Master!$R$2:$R$41,MATCH(A11,Client_Master!$A$2:$A$41,0)),"") -> Complete | M11: =IF(OR(D11="Missing in CRM",D11="Missing in Core"),D11,IF(AND(D11="Match",G11="Match",J11="Match"),"Reconciled",TRIM("Break: "&IF(D11<>"Match","Name ","")&IF(G11<>"Match","Country ","")&IF(J11<>"Match","Rating","")))) -> Break: Country | N11: =IF(AND(K11="Active",L11<>"",L11<>"Complete"),"Active account - KYC incomplete",IF(AND(K11="Active",L11=""),"Active account - no KYC record",""))
A12: C011 | B12: =IFERROR(INDEX(Client_Master!$B$2:$B$41,MATCH(A12,Client_Master!$A$2:$A$41,0)),"") -> Coral Reef Gaming Ltd | C12: =IFERROR(INDEX(Src_CoreBanking!$B$2:$B$41,MATCH(A12,Src_CoreBanking!$A$2:$A$41,0)),"") -> Coral Reef Gaming Ltd | D12: =IF(B12="","Missing in CRM",IF(C12="","Missing in Core",IF(TRIM(UPPER(B12))=TRIM(UPPER(C12)),"Match","Break"))) -> Match | E12: =IFERROR(INDEX(Client_Master!$D$2:$D$41,MATCH(A12,Client_Master!$A$2:$A$41,0)),"") -> Cayman Islands | F12: =IFERROR(INDEX(Src_CoreBanking!$C$2:$C$41,MATCH(A12,Src_CoreBanking!$A$2:$A$41,0)),"") -> Cayman Islands | G12: =IF(OR(E12="",F12=""),"n/a",IF(E12=F12,"Match","Break")) -> Match | H12: =IFERROR(INDEX(Client_Master!$H$2:$H$41,MATCH(A12,Client_Master!$A$2:$A$41,0)),"") -> Medium | I12: =IFERROR(INDEX(Src_CoreBanking!$D$2:$D$41,MATCH(A12,Src_CoreBanking!$A$2:$A$41,0)),"") -> Medium | J12: =IF(OR(H12="",I12=""),"n/a",IF(H12=I12,"Match","Break")) -> Match | K12: =IFERROR(INDEX(Src_CoreBanking!$E$2:$E$41,MATCH(A12,Src_CoreBanking!$A$2:$A$41,0)),"") -> Active | L12: =IFERROR(INDEX(Client_Master!$R$2:$R$41,MATCH(A12,Client_Master!$A$2:$A$41,0)),"") -> Complete | M12: =IF(OR(D12="Missing in CRM",D12="Missing in Core"),D12,IF(AND(D12="Match",G12="Match",J12="Match"),"Reconciled",TRIM("Break: "&IF(D12<>"Match","Name ","")&IF(G12<>"Match","Country ","")&IF(J12<>"Match","Rating","")))) -> Reconciled | N12: =IF(AND(K12="Active",L12<>"",L12<>"Complete"),"Active account - KYC incomplete",IF(AND(K12="Active",L12=""),"Active account - no KYC record",""))
A13: C012 | B13: =IFERROR(INDEX(Client_Master!$B$2:$B$41,MATCH(A13,Client_Master!$A$2:$A$41,0)),"") -> Brightline Retail Holdings Inc | C13: =IFERROR(INDEX(Src_CoreBanking!$B$2:$B$41,MATCH(A13,Src_CoreBanking!$A$2:$A$41,0)),"") -> Brightline Retail Holdings Inc | D13: =IF(B13="","Missing in CRM",IF(C13="","Missing in Core",IF(TRIM(UPPER(B13))=TRIM(UPPER(C13)),"Match","Break"))) -> Match | E13: =IFERROR(INDEX(Client_Master!$D$2:$D$41,MATCH(A13,Client_Master!$A$2:$A$41,0)),"") -> United States | F13: =IFERROR(INDEX(Src_CoreBanking!$C$2:$C$41,MATCH(A13,Src_CoreBanking!$A$2:$A$41,0)),"") -> United States | G13: =IF(OR(E13="",F13=""),"n/a",IF(E13=F13,"Match","Break")) -> Match | H13: =IFERROR(INDEX(Client_Master!$H$2:$H$41,MATCH(A13,Client_Master!$A$2:$A$41,0)),"") -> Low | I13: =IFERROR(INDEX(Src_CoreBanking!$D$2:$D$41,MATCH(A13,Src_CoreBanking!$A$2:$A$41,0)),"") -> Low | J13: =IF(OR(H13="",I13=""),"n/a",IF(H13=I13,"Match","Break")) -> Match | K13: =IFERROR(INDEX(Src_CoreBanking!$E$2:$E$41,MATCH(A13,Src_CoreBanking!$A$2:$A$41,0)),"") -> Active | L13: =IFERROR(INDEX(Client_Master!$R$2:$R$41,MATCH(A13,Client_Master!$A$2:$A$41,0)),"") -> Complete | M13: =IF(OR(D13="Missing in CRM",D13="Missing in Core"),D13,IF(AND(D13="Match",G13="Match",J13="Match"),"Reconciled",TRIM("Break: "&IF(D13<>"Match","Name ","")&IF(G13<>"Match","Country ","")&IF(J13<>"Match","Rating","")))) -> Reconciled | N13: =IF(AND(K13="Active",L13<>"",L13<>"Complete"),"Active account - KYC incomplete",IF(AND(K13="Active",L13=""),"Active account - no KYC record",""))
... A42: C041 | B42: =IFERROR(INDEX(Client_Master!$B$2:$B$41,MATCH(A42,Client_Master!$A$2:$A$41,0)),"") | C42: =IFERROR(INDEX(Src_CoreBanking!$B$2:$B$41,MATCH(A42,Src_CoreBanking!$A$2:$A$41,0)),"") -> Oakridge Holdings Inc | D42: =IF(B42="","Missing in CRM",IF(C42="","Missing in Core",IF(TRIM(UPPER(B42))=TRIM(UPPER(C42)),"Match","Break"))) -> Missing in CRM | E42: =IFERROR(INDEX(Client_Master!$D$2:$D$41,MATCH(A42,Client_Master!$A$2:$A$41,0)),"") | F42: =IFERROR(INDEX(Src_CoreBanking!$C$2:$C$41,MATCH(A42,Src_CoreBanking!$A$2:$A$41,0)),"") -> United States | G42: =IF(OR(E42="",F42=""),"n/a",IF(E42=F42,"Match","Break")) -> n/a | H42: =IFERROR(INDEX(Client_Master!$H$2:$H$41,MATCH(A42,Client_Master!$A$2:$A$41,0)),"") | I42: =IFERROR(INDEX(Src_CoreBanking!$D$2:$D$41,MATCH(A42,Src_CoreBanking!$A$2:$A$41,0)),"") -> Low | J42: =IF(OR(H42="",I42=""),"n/a",IF(H42=I42,"Match","Break")) -> n/a | K42: =IFERROR(INDEX(Src_CoreBanking!$E$2:$E$41,MATCH(A42,Src_CoreBanking!$A$2:$A$41,0)),"") -> Active | L42: =IFERROR(INDEX(Client_Master!$R$2:$R$41,MATCH(A42,Client_Master!$A$2:$A$41,0)),"") | M42: =IF(OR(D42="Missing in CRM",D42="Missing in Core"),D42,IF(AND(D42="Match",G42="Match",J42="Match"),"Reconciled",TRIM("Break: "&IF(D42<>"Match","Name ","")&IF(G42<>"Match","Country ","")&IF(J42<>"Match","Rating","")))) -> Missing in CRM | N42: =IF(AND(K42="Active",L42<>"",L42<>"Complete"),"Active account - KYC incomplete",IF(AND(K42="Active",L42=""),"Active account - no KYC record","")) -> Active account - no KYC record

Sheet Recon_Txn
A1: Txn ID | B1: Ledger Amount | C1: Statement Amount | D1: # Times in Statement | E1: Recon Status | F1: Difference (Ledger - Statement) | G1: Net Break Value | H1: Client (per ledger) | I1: Analyst Note | K1: Control-total proof
A2: T0001 | B2: =IFERROR(INDEX(Transactions!$E$2:$E$114,MATCH(A2,Transactions!$A$2:$A$114,0)),"") -> 17700 | C2: =IFERROR(INDEX(Src_BankStatement!$C$2:$C$114,MATCH(A2,Src_BankStatement!$A$2:$A$114,0)),"") -> 17665 | D2: =COUNTIF(Src_BankStatement!$A$2:$A$114,A2) -> 1 | E2: =IF(AND(B2="",C2=""),"",IF(B2="","Missing in Ledger",IF(C2="","Missing in Statement",IF(D2>1,"Duplicate in Statement",IF(ABS(B2-C2)>0.005,"Amount Break","Matched"))))) -> Amount Break | F2: =IF(AND(ISNUMBER(B2),ISNUMBER(C2)),ROUND(B2-C2,2),"") -> 35 | G2: =IF(E2="Amount Break",B2-C2,IF(E2="Missing in Statement",B2,IF(E2="Missing in Ledger",-C2,IF(E2="Duplicate in Statement",-C2*(D2-1),0)))) -> 35 | H2: =IFERROR(INDEX(Transactions!$H$2:$H$114,MATCH(A2,Transactions!$A$2:$A$114,0)),"") -> Lotus Healthcare Systems Ltd | I2: Statement is 35.00 lower - bank charge netted off at source; ledger gross is correct. | K2: Ledger total (USD) | L2: =SUM(Transactions!$E$2:$E$114) -> 5155500
A3: T0002 | B3: =IFERROR(INDEX(Transactions!$E$2:$E$114,MATCH(A3,Transactions!$A$2:$A$114,0)),"") -> 78700 | C3: =IFERROR(INDEX(Src_BankStatement!$C$2:$C$114,MATCH(A3,Src_BankStatement!$A$2:$A$114,0)),"") -> 78700 | D3: =COUNTIF(Src_BankStatement!$A$2:$A$114,A3) -> 1 | E3: =IF(AND(B3="",C3=""),"",IF(B3="","Missing in Ledger",IF(C3="","Missing in Statement",IF(D3>1,"Duplicate in Statement",IF(ABS(B3-C3)>0.005,"Amount Break","Matched"))))) -> Matched | F3: =IF(AND(ISNUMBER(B3),ISNUMBER(C3)),ROUND(B3-C3,2),"") -> 0 | G3: =IF(E3="Amount Break",B3-C3,IF(E3="Missing in Statement",B3,IF(E3="Missing in Ledger",-C3,IF(E3="Duplicate in Statement",-C3*(D3-1),0)))) -> 0 | H3: =IFERROR(INDEX(Transactions!$H$2:$H$114,MATCH(A3,Transactions!$A$2:$A$114,0)),"") -> Cedar Hill Property Holdings Ltd | K3: Statement total (USD) | L3: =SUM(Src_BankStatement!$C$2:$C$114) -> 5136347
A4: T0003 | B4: =IFERROR(INDEX(Transactions!$E$2:$E$114,MATCH(A4,Transactions!$A$2:$A$114,0)),"") -> 48400 | C4: =IFERROR(INDEX(Src_BankStatement!$C$2:$C$114,MATCH(A4,Src_BankStatement!$A$2:$A$114,0)),"") | D4: =COUNTIF(Src_BankStatement!$A$2:$A$114,A4) -> 0 | E4: =IF(AND(B4="",C4=""),"",IF(B4="","Missing in Ledger",IF(C4="","Missing in Statement",IF(D4>1,"Duplicate in Statement",IF(ABS(B4-C4)>0.005,"Amount Break","Matched"))))) -> Missing in Statement | F4: =IF(AND(ISNUMBER(B4),ISNUMBER(C4)),ROUND(B4-C4,2),"") | G4: =IF(E4="Amount Break",B4-C4,IF(E4="Missing in Statement",B4,IF(E4="Missing in Ledger",-C4,IF(E4="Duplicate in Statement",-C4*(D4-1),0)))) -> 48400 | H4: =IFERROR(INDEX(Transactions!$H$2:$H$114,MATCH(A4,Transactions!$A$2:$A$114,0)),"") -> Coral Reef Gaming Ltd | I4: Not on statement - value date likely next cycle; recheck. | K4: Net difference (Ledger - Statement) | L4: =ROUND(L2-L3,2) -> 19153
A5: T0004 | B5: =IFERROR(INDEX(Transactions!$E$2:$E$114,MATCH(A5,Transactions!$A$2:$A$114,0)),"") -> 54100 | C5: =IFERROR(INDEX(Src_BankStatement!$C$2:$C$114,MATCH(A5,Src_BankStatement!$A$2:$A$114,0)),"") -> 54100 | D5: =COUNTIF(Src_BankStatement!$A$2:$A$114,A5) -> 1 | E5: =IF(AND(B5="",C5=""),"",IF(B5="","Missing in Ledger",IF(C5="","Missing in Statement",IF(D5>1,"Duplicate in Statement",IF(ABS(B5-C5)>0.005,"Amount Break","Matched"))))) -> Matched | F5: =IF(AND(ISNUMBER(B5),ISNUMBER(C5)),ROUND(B5-C5,2),"") -> 0 | G5: =IF(E5="Amount Break",B5-C5,IF(E5="Missing in Statement",B5,IF(E5="Missing in Ledger",-C5,IF(E5="Duplicate in Statement",-C5*(D5-1),0)))) -> 0 | H5: =IFERROR(INDEX(Transactions!$H$2:$H$114,MATCH(A5,Transactions!$A$2:$A$114,0)),"") -> Delta Cloud Systems Pvt Ltd | K5: Sum of itemised breaks | L5: =ROUND(SUM(G2:G115),2) -> 19153
A6: T0005 | B6: =IFERROR(INDEX(Transactions!$E$2:$E$114,MATCH(A6,Transactions!$A$2:$A$114,0)),"") -> 28500 | C6: =IFERROR(INDEX(Src_BankStatement!$C$2:$C$114,MATCH(A6,Src_BankStatement!$A$2:$A$114,0)),"") -> 28500 | D6: =COUNTIF(Src_BankStatement!$A$2:$A$114,A6) -> 1 | E6: =IF(AND(B6="",C6=""),"",IF(B6="","Missing in Ledger",IF(C6="","Missing in Statement",IF(D6>1,"Duplicate in Statement",IF(ABS(B6-C6)>0.005,"Amount Break","Matched"))))) -> Matched | F6: =IF(AND(ISNUMBER(B6),ISNUMBER(C6)),ROUND(B6-C6,2),"") -> 0 | G6: =IF(E6="Amount Break",B6-C6,IF(E6="Missing in Statement",B6,IF(E6="Missing in Ledger",-C6,IF(E6="Duplicate in Statement",-C6*(D6-1),0)))) -> 0 | H6: =IFERROR(INDEX(Transactions!$H$2:$H$114,MATCH(A6,Transactions!$A$2:$A$114,0)),"") -> Anatolia Steel Works AS | K6: Unexplained difference | L6: =ROUND(L4-L5,2) -> 0
A7: T0006 | B7: =IFERROR(INDEX(Transactions!$E$2:$E$114,MATCH(A7,Transactions!$A$2:$A$114,0)),"") -> 43400 | C7: =IFERROR(INDEX(Src_BankStatement!$C$2:$C$114,MATCH(A7,Src_BankStatement!$A$2:$A$114,0)),"") -> 44400 | D7: =COUNTIF(Src_BankStatement!$A$2:$A$114,A7) -> 1 | E7: =IF(AND(B7="",C7=""),"",IF(B7="","Missing in Ledger",IF(C7="","Missing in Statement",IF(D7>1,"Duplicate in Statement",IF(ABS(B7-C7)>0.005,"Amount Break","Matched"))))) -> Amount Break | F7: =IF(AND(ISNUMBER(B7),ISNUMBER(C7)),ROUND(B7-C7,2),"") -> -1000 | G7: =IF(E7="Amount Break",B7-C7,IF(E7="Missing in Statement",B7,IF(E7="Missing in Ledger",-C7,IF(E7="Duplicate in Statement",-C7*(D7-1),0)))) -> -1000 | H7: =IFERROR(INDEX(Transactions!$H$2:$H$114,MATCH(A7,Transactions!$A$2:$A$114,0)),"") -> Maple Leaf Health Clinics Inc | I7: Statement is 1,000 higher - keying error at bank; correction requested. | K7: Reconciliation result | L7: =IF(L6=0,"FULLY EXPLAINED","UNEXPLAINED DIFFERENCE") -> FULLY EXPLAINED
A8: T0007 | B8: =IFERROR(INDEX(Transactions!$E$2:$E$114,MATCH(A8,Transactions!$A$2:$A$114,0)),"") -> 31900 | C8: =IFERROR(INDEX(Src_BankStatement!$C$2:$C$114,MATCH(A8,Src_BankStatement!$A$2:$A$114,0)),"") -> 31900 | D8: =COUNTIF(Src_BankStatement!$A$2:$A$114,A8) -> 1 | E8: =IF(AND(B8="",C8=""),"",IF(B8="","Missing in Ledger",IF(C8="","Missing in Statement",IF(D8>1,"Duplicate in Statement",IF(ABS(B8-C8)>0.005,"Amount Break","Matched"))))) -> Matched | F8: =IF(AND(ISNUMBER(B8),ISNUMBER(C8)),ROUND(B8-C8,2),"") -> 0 | G8: =IF(E8="Amount Break",B8-C8,IF(E8="Missing in Statement",B8,IF(E8="Missing in Ledger",-C8,IF(E8="Duplicate in Statement",-C8*(D8-1),0)))) -> 0 | H8: =IFERROR(INDEX(Transactions!$H$2:$H$114,MATCH(A8,Transactions!$A$2:$A$114,0)),"") -> Palm Bay Casino Resorts
A9: T0008 | B9: =IFERROR(INDEX(Transactions!$E$2:$E$114,MATCH(A9,Transactions!$A$2:$A$114,0)),"") -> 34000 | C9: =IFERROR(INDEX(Src_BankStatement!$C$2:$C$114,MATCH(A9,Src_BankStatement!$A$2:$A$114,0)),"") | D9: =COUNTIF(Src_BankStatement!$A$2:$A$114,A9) -> 0 | E9: =IF(AND(B9="",C9=""),"",IF(B9="","Missing in Ledger",IF(C9="","Missing in Statement",IF(D9>1,"Duplicate in Statement",IF(ABS(B9-C9)>0.005,"Amount Break","Matched"))))) -> Missing in Statement | F9: =IF(AND(ISNUMBER(B9),ISNUMBER(C9)),ROUND(B9-C9,2),"") | G9: =IF(E9="Amount Break",B9-C9,IF(E9="Missing in Statement",B9,IF(E9="Missing in Ledger",-C9,IF(E9="Duplicate in Statement",-C9*(D9-1),0)))) -> 34000 | H9: =IFERROR(INDEX(Transactions!$H$2:$H$114,MATCH(A9,Transactions!$A$2:$A$114,0)),"") -> Lakeview Medical Supplies Inc | I9: Not on statement - possible failed/returned wire; chase with payments team.
A10: T0009 | B10: =IFERROR(INDEX(Transactions!$E$2:$E$114,MATCH(A10,Transactions!$A$2:$A$114,0)),"") -> 66000 | C10: =IFERROR(INDEX(Src_BankStatement!$C$2:$C$114,MATCH(A10,Src_BankStatement!$A$2:$A$114,0)),"") -> 66000 | D10: =COUNTIF(Src_BankStatement!$A$2:$A$114,A10) -> 1 | E10: =IF(AND(B10="",C10=""),"",IF(B10="","Missing in Ledger",IF(C10="","Missing in Statement",IF(D10>1,"Duplicate in Statement",IF(ABS(B10-C10)>0.005,"Amount Break","Matched"))))) -> Matched | F10: =IF(AND(ISNUMBER(B10),ISNUMBER(C10)),ROUND(B10-C10,2),"") -> 0 | G10: =IF(E10="Amount Break",B10-C10,IF(E10="Missing in Statement",B10,IF(E10="Missing in Ledger",-C10,IF(E10="Duplicate in Statement",-C10*(D10-1),0)))) -> 0 | H10: =IFERROR(INDEX(Transactions!$H$2:$H$114,MATCH(A10,Transactions!$A$2:$A$114,0)),"") -> Aurora Software Solutions Pvt Ltd
A11: T0010 | B11: =IFERROR(INDEX(Transactions!$E$2:$E$114,MATCH(A11,Transactions!$A$2:$A$114,0)),"") -> 79700 | C11: =IFERROR(INDEX(Src_BankStatement!$C$2:$C$114,MATCH(A11,Src_BankStatement!$A$2:$A$114,0)),"") -> 79700 | D11: =COUNTIF(Src_BankStatement!$A$2:$A$114,A11) -> 1 | E11: =IF(AND(B11="",C11=""),"",IF(B11="","Missing in Ledger",IF(C11="","Missing in Statement",IF(D11>1,"Duplicate in Statement",IF(ABS(B11-C11)>0.005,"Amount Break","Matched"))))) -> Matched | F11: =IF(AND(ISNUMBER(B11),ISNUMBER(C11)),ROUND(B11-C11,2),"") -> 0 | G11: =IF(E11="Amount Break",B11-C11,IF(E11="Missing in Statement",B11,IF(E11="Missing in Ledger",-C11,IF(E11="Duplicate in Statement",-C11*(D11-1),0)))) -> 0 | H11: =IFERROR(INDEX(Transactions!$H$2:$H$114,MATCH(A11,Transactions!$A$2:$A$114,0)),"") -> Palm Bay Casino Resorts
A12: T0011 | B12: =IFERROR(INDEX(Transactions!$E$2:$E$114,MATCH(A12,Transactions!$A$2:$A$114,0)),"") -> 81800 | C12: =IFERROR(INDEX(Src_BankStatement!$C$2:$C$114,MATCH(A12,Src_BankStatement!$A$2:$A$114,0)),"") -> 80982 | D12: =COUNTIF(Src_BankStatement!$A$2:$A$114,A12) -> 1 | E12: =IF(AND(B12="",C12=""),"",IF(B12="","Missing in Ledger",IF(C12="","Missing in Statement",IF(D12>1,"Duplicate in Statement",IF(ABS(B12-C12)>0.005,"Amount Break","Matched"))))) -> Amount Break | F12: =IF(AND(ISNUMBER(B12),ISNUMBER(C12)),ROUND(B12-C12,2),"") -> 818 | G12: =IF(E12="Amount Break",B12-C12,IF(E12="Missing in Statement",B12,IF(E12="Missing in Ledger",-C12,IF(E12="Duplicate in Statement",-C12*(D12-1),0)))) -> 818 | H12: =IFERROR(INDEX(Transactions!$H$2:$H$114,MATCH(A12,Transactions!$A$2:$A$114,0)),"") -> Meridian Textile Exports Pvt Ltd | I12: Statement ~1% lower - FX rate difference; confirm rate with Treasury.
A13: T0012 | B13: =IFERROR(INDEX(Transactions!$E$2:$E$114,MATCH(A13,Transactions!$A$2:$A$114,0)),"") -> 75900 | C13: =IFERROR(INDEX(Src_BankStatement!$C$2:$C$114,MATCH(A13,Src_BankStatement!$A$2:$A$114,0)),"") -> 75900 | D13: =COUNTIF(Src_BankStatement!$A$2:$A$114,A13) -> 1 | E13: =IF(AND(B13="",C13=""),"",IF(B13="","Missing in Ledger",IF(C13="","Missing in Statement",IF(D13>1,"Duplicate in Statement",IF(ABS(B13-C13)>0.005,"Amount Break","Matched"))))) -> Matched | F13: =IF(AND(ISNUMBER(B13),ISNUMBER(C13)),ROUND(B13-C13,2),"") -> 0 | G13: =IF(E13="Amount Break",B13-C13,IF(E13="Missing in Statement",B13,IF(E13="Missing in Ledger",-C13,IF(E13="Duplicate in Statement",-C13*(D13-1),0)))) -> 0 | H13: =IFERROR(INDEX(Transactions!$H$2:$H$114,MATCH(A13,Transactions!$A$2:$A$114,0)),"") -> Coral Reef Gaming Ltd
A14: T0013 | B14: =IFERROR(INDEX(Transactions!$E$2:$E$114,MATCH(A14,Transactions!$A$2:$A$114,0)),"") -> 59900 | C14: =IFERROR(INDEX(Src_BankStatement!$C$2:$C$114,MATCH(A14,Src_BankStatement!$A$2:$A$114,0)),"") -> 59900 | D14: =COUNTIF(Src_BankStatement!$A$2:$A$114,A14) -> 2 | E14: =IF(AND(B14="",C14=""),"",IF(B14="","Missing in Ledger",IF(C14="","Missing in Statement",IF(D14>1,"Duplicate in Statement",IF(ABS(B14-C14)>0.005,"Amount Break","Matched"))))) -> Duplicate in Statement | F14: =IF(AND(ISNUMBER(B14),ISNUMBER(C14)),ROUND(B14-C14,2),"") -> 0 | G14: =IF(E14="Amount Break",B14-C14,IF(E14="Missing in Statement",B14,IF(E14="Missing in Ledger",-C14,IF(E14="Duplicate in Statement",-C14*(D14-1),0)))) -> -59900 | H14: =IFERROR(INDEX(Transactions!$H$2:$H$114,MATCH(A14,Transactions!$A$2:$A$114,0)),"") -> Orion Freight Forwarders Pvt Ltd | I14: Posted twice on statement - duplicate credit/debit; raise reversal.
A15: T0014 | B15: =IFERROR(INDEX(Transactions!$E$2:$E$114,MATCH(A15,Transactions!$A$2:$A$114,0)),"") -> 3100 | C15: =IFERROR(INDEX(Src_BankStatement!$C$2:$C$114,MATCH(A15,Src_BankStatement!$A$2:$A$114,0)),"") -> 3100 | D15: =COUNTIF(Src_BankStatement!$A$2:$A$114,A15) -> 1 | E15: =IF(AND(B15="",C15=""),"",IF(B15="","Missing in Ledger",IF(C15="","Missing in Statement",IF(D15>1,"Duplicate in Statement",IF(ABS(B15-C15)>0.005,"Amount Break","Matched"))))) -> Matched | F15: =IF(AND(ISNUMBER(B15),ISNUMBER(C15)),ROUND(B15-C15,2),"") -> 0 | G15: =IF(E15="Amount Break",B15-C15,IF(E15="Missing in Statement",B15,IF(E15="Missing in Ledger",-C15,IF(E15="Duplicate in Statement",-C15*(D15-1),0)))) -> 0 | H15: =IFERROR(INDEX(Transactions!$H$2:$H$114,MATCH(A15,Transactions!$A$2:$A$114,0)),"") -> Metro Fuel & Convenience Stores Inc
A16: T0015 | B16: =IFERROR(INDEX(Transactions!$E$2:$E$114,MATCH(A16,Transactions!$A$2:$A$114,0)),"") -> 68500 | C16: =IFERROR(INDEX(Src_BankStatement!$C$2:$C$114,MATCH(A16,Src_BankStatement!$A$2:$A$114,0)),"") -> 68500 | D16: =COUNTIF(Src_BankStatement!$A$2:$A$114,A16) -> 1 | E16: =IF(AND(B16="",C16=""),"",IF(B16="","Missing in Ledger",IF(C16="","Missing in Statement",IF(D16>1,"Duplicate in Statement",IF(ABS(B16-C16)>0.005,"Amount Break","Matched"))))) -> Matched | F16: =IF(AND(ISNUMBER(B16),ISNUMBER(C16)),ROUND(B16-C16,2),"") -> 0 | G16: =IF(E16="Amount Break",B16-C16,IF(E16="Missing in Statement",B16,IF(E16="Missing in Ledger",-C16,IF(E16="Duplicate in Statement",-C16*(D16-1),0)))) -> 0 | H16: =IFERROR(INDEX(Transactions!$H$2:$H$114,MATCH(A16,Transactions!$A$2:$A$114,0)),"") -> Meridian Textile Exports Pvt Ltd
A17: T0016 | B17: =IFERROR(INDEX(Transactions!$E$2:$E$114,MATCH(A17,Transactions!$A$2:$A$114,0)),"") -> 2800 | C17: =IFERROR(INDEX(Src_BankStatement!$C$2:$C$114,MATCH(A17,Src_BankStatement!$A$2:$A$114,0)),"") -> 2800 | D17: =COUNTIF(Src_BankStatement!$A$2:$A$114,A17) -> 1 | E17: =IF(AND(B17="",C17=""),"",IF(B17="","Missing in Ledger",IF(C17="","Missing in Statement",IF(D17>1,"Duplicate in Statement",IF(ABS(B17-C17)>0.005,"Amount Break","Matched"))))) -> Matched | F17: =IF(AND(ISNUMBER(B17),ISNUMBER(C17)),ROUND(B17-C17,2),"") -> 0 | G17: =IF(E17="Amount Break",B17-C17,IF(E17="Missing in Statement",B17,IF(E17="Missing in Ledger",-C17,IF(E17="Duplicate in Statement",-C17*(D17-1),0)))) -> 0 | H17: =IFERROR(INDEX(Transactions!$H$2:$H$114,MATCH(A17,Transactions!$A$2:$A$114,0)),"") -> Brightline Retail Holdings Inc
A18: T0017 | B18: =IFERROR(INDEX(Transactions!$E$2:$E$114,MATCH(A18,Transactions!$A$2:$A$114,0)),"") -> 19600 | C18: =IFERROR(INDEX(Src_BankStatement!$C$2:$C$114,MATCH(A18,Src_BankStatement!$A$2:$A$114,0)),"") -> 19600 | D18: =COUNTIF(Src_BankStatement!$A$2:$A$114,A18) -> 1 | E18: =IF(AND(B18="",C18=""),"",IF(B18="","Missing in Ledger",IF(C18="","Missing in Statement",IF(D18>1,"Duplicate in Statement",IF(ABS(B18-C18)>0.005,"Amount Break","Matched"))))) -> Matched | F18: =IF(AND(ISNUMBER(B18),ISNUMBER(C18)),ROUND(B18-C18,2),"") -> 0 | G18: =IF(E18="Amount Break",B18-C18,IF(E18="Missing in Statement",B18,IF(E18="Missing in Ledger",-C18,IF(E18="Duplicate in Statement",-C18*(D18-1),0)))) -> 0 | H18: =IFERROR(INDEX(Transactions!$H$2:$H$114,MATCH(A18,Transactions!$A$2:$A$114,0)),"") -> Kestrel Engineering Services Pte Ltd
A19: T0018 | B19: =IFERROR(INDEX(Transactions!$E$2:$E$114,MATCH(A19,Transactions!$A$2:$A$114,0)),"") -> 30000 | C19: =IFERROR(INDEX(Src_BankStatement!$C$2:$C$114,MATCH(A19,Src_BankStatement!$A$2:$A$114,0)),"") -> 30000 | D19: =COUNTIF(Src_BankStatement!$A$2:$A$114,A19) -> 1 | E19: =IF(AND(B19="",C19=""),"",IF(B19="","Missing in Ledger",IF(C19="","Missing in Statement",IF(D19>1,"Duplicate in Statement",IF(ABS(B19-C19)>0.005,"Amount Break","Matched"))))) -> Matched | F19: =IF(AND(ISNUMBER(B19),ISNUMBER(C19)),ROUND(B19-C19,2),"") -> 0 | G19: =IF(E19="Amount Break",B19-C19,IF(E19="Missing in Statement",B19,IF(E19="Missing in Ledger",-C19,IF(E19="Duplicate in Statement",-C19*(D19-1),0)))) -> 0 | H19: =IFERROR(INDEX(Transactions!$H$2:$H$114,MATCH(A19,Transactions!$A$2:$A$114,0)),"") -> Golden Crest Jewellers LLC
A20: T0019 | B20: =IFERROR(INDEX(Transactions!$E$2:$E$114,MATCH(A20,Transactions!$A$2:$A$114,0)),"") -> 68900 | C20: =IFERROR(INDEX(Src_BankStatement!$C$2:$C$114,MATCH(A20,Src_BankStatement!$A$2:$A$114,0)),"") -> 68900 | D20: =COUNTIF(Src_BankStatement!$A$2:$A$114,A20) -> 1 | E20: =IF(AND(B20="",C20=""),"",IF(B20="","Missing in Ledger",IF(C20="","Missing in Statement",IF(D20>1,"Duplicate in Statement",IF(ABS(B20-C20)>0.005,"Amount Break","Matched"))))) -> Matched | F20: =IF(AND(ISNUMBER(B20),ISNUMBER(C20)),ROUND(B20-C20,2),"") -> 0 | G20: =IF(E20="Amount Break",B20-C20,IF(E20="Missing in Statement",B20,IF(E20="Missing in Ledger",-C20,IF(E20="Duplicate in Statement",-C20*(D20-1),0)))) -> 0 | H20: =IFERROR(INDEX(Transactions!$H$2:$H$114,MATCH(A20,Transactions!$A$2:$A$114,0)),"") -> Pinnacle Realty Developers Ltd
A21: T0020 | B21: =IFERROR(INDEX(Transactions!$E$2:$E$114,MATCH(A21,Transactions!$A$2:$A$114,0)),"") -> 57600 | C21: =IFERROR(INDEX(Src_BankStatement!$C$2:$C$114,MATCH(A21,Src_BankStatement!$A$2:$A$114,0)),"") -> 57600 | D21: =COUNTIF(Src_BankStatement!$A$2:$A$114,A21) -> 1 | E21: =IF(AND(B21="",C21=""),"",IF(B21="","Missing in Ledger",IF(C21="","Missing in Statement",IF(D21>1,"Duplicate in Statement",IF(ABS(B21-C21)>0.005,"Amount Break","Matched"))))) -> Matched | F21: =IF(AND(ISNUMBER(B21),ISNUMBER(C21)),ROUND(B21-C21,2),"") -> 0 | G21: =IF(E21="Amount Break",B21-C21,IF(E21="Missing in Statement",B21,IF(E21="Missing in Ledger",-C21,IF(E21="Duplicate in Statement",-C21*(D21-1),0)))) -> 0 | H21: =IFERROR(INDEX(Transactions!$H$2:$H$114,MATCH(A21,Transactions!$A$2:$A$114,0)),"") -> Zurich Wealth Advisory AG
A22: T0021 | B22: =IFERROR(INDEX(Transactions!$E$2:$E$114,MATCH(A22,Transactions!$A$2:$A$114,0)),"") -> 45200 | C22: =IFERROR(INDEX(Src_BankStatement!$C$2:$C$114,MATCH(A22,Src_BankStatement!$A$2:$A$114,0)),"") -> 45200 | D22: =COUNTIF(Src_BankStatement!$A$2:$A$114,A22) -> 1 | E22: =IF(AND(B22="",C22=""),"",IF(B22="","Missing in Ledger",IF(C22="","Missing in Statement",IF(D22>1,"Duplicate in Statement",IF(ABS(B22-C22)>0.005,"Amount Break","Matched"))))) -> Matched | F22: =IF(AND(ISNUMBER(B22),ISNUMBER(C22)),ROUND(B22-C22,2),"") -> 0 | G22: =IF(E22="Amount Break",B22-C22,IF(E22="Missing in Statement",B22,IF(E22="Missing in Ledger",-C22,IF(E22="Duplicate in Statement",-C22*(D22-1),0)))) -> 0 | H22: =IFERROR(INDEX(Transactions!$H$2:$H$114,MATCH(A22,Transactions!$A$2:$A$114,0)),"") -> Harbour Point Trading Co
A23: T0022 | B23: =IFERROR(INDEX(Transactions!$E$2:$E$114,MATCH(A23,Transactions!$A$2:$A$114,0)),"") -> 48200 | C23: =IFERROR(INDEX(Src_BankStatement!$C$2:$C$114,MATCH(A23,Src_BankStatement!$A$2:$A$114,0)),"") -> 48200 | D23: =COUNTIF(Src_BankStatement!$A$2:$A$114,A23) -> 1 | E23: =IF(AND(B23="",C23=""),"",IF(B23="","Missing in Ledger",IF(C23="","Missing in Statement",IF(D23>1,"Duplicate in Statement",IF(ABS(B23-C23)>0.005,"Amount Break","Matched"))))) -> Matched | F23: =IF(AND(ISNUMBER(B23),ISNUMBER(C23)),ROUND(B23-C23,2),"") -> 0 | G23: =IF(E23="Amount Break",B23-C23,IF(E23="Missing in Statement",B23,IF(E23="Missing in Ledger",-C23,IF(E23="Duplicate in Statement",-C23*(D23-1),0)))) -> 0 | H23: =IFERROR(INDEX(Transactions!$H$2:$H$114,MATCH(A23,Transactions!$A$2:$A$114,0)),"") -> Harbour Point Trading Co
A24: T0023 | B24: =IFERROR(INDEX(Transactions!$E$2:$E$114,MATCH(A24,Transactions!$A$2:$A$114,0)),"") -> 55700 | C24: =IFERROR(INDEX(Src_BankStatement!$C$2:$C$114,MATCH(A24,Src_BankStatement!$A$2:$A$114,0)),"") -> 55700 | D24: =COUNTIF(Src_BankStatement!$A$2:$A$114,A24) -> 1 | E24: =IF(AND(B24="",C24=""),"",IF(B24="","Missing in Ledger",IF(C24="","Missing in Statement",IF(D24>1,"Duplicate in Statement",IF(ABS(B24-C24)>0.005,"Amount Break","Matched"))))) -> Matched | F24: =IF(AND(ISNUMBER(B24),ISNUMBER(C24)),ROUND(B24-C24,2),"") -> 0 | G24: =IF(E24="Amount Break",B24-C24,IF(E24="Missing in Statement",B24,IF(E24="Missing in Ledger",-C24,IF(E24="Duplicate in Statement",-C24*(D24-1),0)))) -> 0 | H24: =IFERROR(INDEX(Transactions!$H$2:$H$114,MATCH(A24,Transactions!$A$2:$A$114,0)),"") -> Delta Cloud Systems Pvt Ltd
A25: T0024 | B25: =IFERROR(INDEX(Transactions!$E$2:$E$114,MATCH(A25,Transactions!$A$2:$A$114,0)),"") -> 89900 | C25: =IFERROR(INDEX(Src_BankStatement!$C$2:$C$114,MATCH(A25,Src_BankStatement!$A$2:$A$114,0)),"") -> 89900 | D25: =COUNTIF(Src_BankStatement!$A$2:$A$114,A25) -> 1 | E25: =IF(AND(B25="",C25=""),"",IF(B25="","Missing in Ledger",IF(C25="","Missing in Statement",IF(D25>1,"Duplicate in Statement",IF(ABS(B25-C25)>0.005,"Amount Break","Matched"))))) -> Matched | F25: =IF(AND(ISNUMBER(B25),ISNUMBER(C25)),ROUND(B25-C25,2),"") -> 0 | G25: =IF(E25="Amount Break",B25-C25,IF(E25="Missing in Statement",B25,IF(E25="Missing in Ledger",-C25,IF(E25="Duplicate in Statement",-C25*(D25-1),0)))) -> 0 | H25: =IFERROR(INDEX(Transactions!$H$2:$H$114,MATCH(A25,Transactions!$A$2:$A$114,0)),"") -> Orchid Textiles Pvt Ltd
A26: T0025 | B26: =IFERROR(INDEX(Transactions!$E$2:$E$114,MATCH(A26,Transactions!$A$2:$A$114,0)),"") -> 80200 | C26: =IFERROR(INDEX(Src_BankStatement!$C$2:$C$114,MATCH(A26,Src_BankStatement!$A$2:$A$114,0)),"") -> 80200 | D26: =COUNTIF(Src_BankStatement!$A$2:$A$114,A26) -> 1 | E26: =IF(AND(B26="",C26=""),"",IF(B26="","Missing in Ledger",IF(C26="","Missing in Statement",IF(D26>1,"Duplicate in Statement",IF(ABS(B26-C26)>0.005,"Amount Break","Matched"))))) -> Matched | F26: =IF(AND(ISNUMBER(B26),ISNUMBER(C26)),ROUND(B26-C26,2),"") -> 0 | G26: =IF(E26="Amount Break",B26-C26,IF(E26="Missing in Statement",B26,IF(E26="Missing in Ledger",-C26,IF(E26="Duplicate in Statement",-C26*(D26-1),0)))) -> 0 | H26: =IFERROR(INDEX(Transactions!$H$2:$H$114,MATCH(A26,Transactions!$A$2:$A$114,0)),"") -> Nordic Precision Manufacturing GmbH
... A114: T0113 | B114: =IFERROR(INDEX(Transactions!$E$2:$E$114,MATCH(A114,Transactions!$A$2:$A$114,0)),"") -> 41200 | C114: =IFERROR(INDEX(Src_BankStatement!$C$2:$C$114,MATCH(A114,Src_BankStatement!$A$2:$A$114,0)),"") -> 41200 | D114: =COUNTIF(Src_BankStatement!$A$2:$A$114,A114) -> 1 | E114: =IF(AND(B114="",C114=""),"",IF(B114="","Missing in Ledger",IF(C114="","Missing in Statement",IF(D114>1,"Duplicate in Statement",IF(ABS(B114-C114)>0.005,"Amount Break","Matched"))))) -> Matched | F114: =IF(AND(ISNUMBER(B114),ISNUMBER(C114)),ROUND(B114-C114,2),"") -> 0 | G114: =IF(E114="Amount Break",B114-C114,IF(E114="Missing in Statement",B114,IF(E114="Missing in Ledger",-C114,IF(E114="Duplicate in Statement",-C114*(D114-1),0)))) -> 0 | H114: =IFERROR(INDEX(Transactions!$H$2:$H$114,MATCH(A114,Transactions!$A$2:$A$114,0)),"") -> Palm Bay Casino Resorts
A115: T9901 | B115: =IFERROR(INDEX(Transactions!$E$2:$E$114,MATCH(A115,Transactions!$A$2:$A$114,0)),"") | C115: =IFERROR(INDEX(Src_BankStatement!$C$2:$C$114,MATCH(A115,Src_BankStatement!$A$2:$A$114,0)),"") -> 3200 | D115: =COUNTIF(Src_BankStatement!$A$2:$A$114,A115) -> 1 | E115: =IF(AND(B115="",C115=""),"",IF(B115="","Missing in Ledger",IF(C115="","Missing in Statement",IF(D115>1,"Duplicate in Statement",IF(ABS(B115-C115)>0.005,"Amount Break","Matched"))))) -> Missing in Ledger | F115: =IF(AND(ISNUMBER(B115),ISNUMBER(C115)),ROUND(B115-C115,2),"") | G115: =IF(E115="Amount Break",B115-C115,IF(E115="Missing in Statement",B115,IF(E115="Missing in Ledger",-C115,IF(E115="Duplicate in Statement",-C115*(D115-1),0)))) -> -3200 | H115: =IFERROR(INDEX(Transactions!$H$2:$H$114,MATCH(A115,Transactions!$A$2:$A$114,0)),"") | I115: On statement but not in ledger - unrecorded cash deposit; identify client and book.

Sheet Customer_Issues
A1: Issue ID | B1: Client ID | C1: Client Name | D1: Source | E1: Issue Type | F1: Description | G1: Priority | H1: Date Opened | I1: Date Resolved | J1: Owner Team | K1: Status | L1: Business Days Open | M1: SLA (business days) | N1: SLA Status | O1: Resolution / Action Taken
A2: ISS-001 | B2: C003 | C2: =IFERROR(INDEX(Client_Master!$B$2:$B$41,MATCH(B2,Client_Master!$A$2:$A$41,0)),"UNKNOWN CLIENT") -> Lotus Healthcare Systems Ltd | D2: Recon - name break | E2: Legal name mismatch | F2: Legal name differs between CRM and core banking (Ltd vs Limited). Client asked to confirm registry name. | G2: Medium | H2: 46314 | I2: 46318 | J2: Client Data Ops | K2: =IF(ISNUMBER(I2),"Closed","Open") -> Closed | L2: =NETWORKDAYS(H2,IF(ISNUMBER(I2),I2,Assumptions!$B$4))-1 -> 4 | M2: =INDEX(Assumptions!$O$22:$O$24,MATCH(G2,Assumptions!$N$22:$N$24,0)) -> 5 | N2: =IF(L2>M2,"SLA Breached","Within SLA") -> Within SLA | O2: Certificate of incorporation obtained; registry spelling confirmed. Core banking correction submitted - will clear on next extract.
A3: ISS-002 | B3: C010 | C3: =IFERROR(INDEX(Client_Master!$B$2:$B$41,MATCH(B3,Client_Master!$A$2:$A$41,0)),"UNKNOWN CLIENT") -> Harbour Point Trading Co | D3: Recon - country break | E3: Country of incorporation mismatch | F3: CRM shows Hong Kong; core banking shows Singapore. Account opening documents to be checked. | G3: High | H3: 46314 | J3: Client Data Ops | K3: =IF(ISNUMBER(I3),"Closed","Open") -> Open | L3: =NETWORKDAYS(H3,IF(ISNUMBER(I3),I3,Assumptions!$B$4))-1 -> 5 | M3: =INDEX(Assumptions!$O$22:$O$24,MATCH(G3,Assumptions!$N$22:$N$24,0)) -> 2 | N3: =IF(L3>M3,"SLA Breached","Within SLA") -> SLA Breached | O3: Awaiting incorporation certificate via RM.
A4: ISS-003 | B4: C014 | C4: =IFERROR(INDEX(Client_Master!$B$2:$B$41,MATCH(B4,Client_Master!$A$2:$A$41,0)),"UNKNOWN CLIENT") -> Maple Leaf Health Clinics Inc | D4: Recon - rating break | E4: Risk rating mismatch | F4: CRM Low vs core banking Medium. | G4: Medium | H4: 46314 | I4: 46317 | J4: KYC Quality | K4: =IF(ISNUMBER(I4),"Closed","Open") -> Closed | L4: =NETWORKDAYS(H4,IF(ISNUMBER(I4),I4,Assumptions!$B$4))-1 -> 3 | M4: =INDEX(Assumptions!$O$22:$O$24,MATCH(G4,Assumptions!$N$22:$N$24,0)) -> 5 | N4: =IF(L4>M4,"SLA Breached","Within SLA") -> Within SLA | O4: Re-scored using model; CRM rating confirmed. Correction submitted to core banking.
A5: ISS-004 | B5: C017 | C5: =IFERROR(INDEX(Client_Master!$B$2:$B$41,MATCH(B5,Client_Master!$A$2:$A$41,0)),"UNKNOWN CLIENT") -> Evergreen Charitable Foundation | D5: DQ check | E5: UBO documentation missing | F5: Beneficial owner not identified on file; account active. | G5: High | H5: 46317 | J5: KYC Operations | K5: =IF(ISNUMBER(I5),"Closed","Open") -> Open | L5: =NETWORKDAYS(H5,IF(ISNUMBER(I5),I5,Assumptions!$B$4))-1 -> 2 | M5: =INDEX(Assumptions!$O$22:$O$24,MATCH(G5,Assumptions!$N$22:$N$24,0)) -> 2 | N5: =IF(L5>M5,"SLA Breached","Within SLA") -> Within SLA | O5: UBO declaration and ID requested via RM.
A6: ISS-005 | B6: C024 | C6: =IFERROR(INDEX(Client_Master!$B$2:$B$41,MATCH(B6,Client_Master!$A$2:$A$41,0)),"UNKNOWN CLIENT") -> Sunrise Auto Traders LLC | D6: DQ check | E6: Source of funds not evidenced | F6: No source-of-funds evidence on file and industry field is blank. | G6: Medium | H6: 46300 | J6: KYC Operations | K6: =IF(ISNUMBER(I6),"Closed","Open") -> Open | L6: =NETWORKDAYS(H6,IF(ISNUMBER(I6),I6,Assumptions!$B$4))-1 -> 15 | M6: =INDEX(Assumptions!$O$22:$O$24,MATCH(G6,Assumptions!$N$22:$N$24,0)) -> 5 | N6: =IF(L6>M6,"SLA Breached","Within SLA") -> SLA Breached | O6: Two reminders sent via RM; escalated to team lead.
A7: ISS-006 | B7: C033 | C7: =IFERROR(INDEX(Client_Master!$B$2:$B$41,MATCH(B7,Client_Master!$A$2:$A$41,0)),"UNKNOWN CLIENT") -> Lakeview Medical Supplies Inc | D7: DQ check | E7: Address proof outdated | F7: Address proof missing from file. | G7: Low | H7: 46309 | J7: KYC Operations | K7: =IF(ISNUMBER(I7),"Closed","Open") -> Open | L7: =NETWORKDAYS(H7,IF(ISNUMBER(I7),I7,Assumptions!$B$4))-1 -> 8 | M7: =INDEX(Assumptions!$O$22:$O$24,MATCH(G7,Assumptions!$N$22:$N$24,0)) -> 10 | N7: =IF(L7>M7,"SLA Breached","Within SLA") -> Within SLA | O7: Recent utility bill requested.
A8: ISS-007 | B8: C038 | C8: =IFERROR(INDEX(Client_Master!$B$2:$B$41,MATCH(B8,Client_Master!$A$2:$A$41,0)),"UNKNOWN CLIENT") -> Zenith Wellness Clinics Pvt Ltd | D8: DQ check | E8: New client documents outstanding | F8: CIP and UBO documents outstanding; sanctions screening not done. | G8: High | H8: 46314 | J8: KYC Operations | K8: =IF(ISNUMBER(I8),"Closed","Open") -> Open | L8: =NETWORKDAYS(H8,IF(ISNUMBER(I8),I8,Assumptions!$B$4))-1 -> 5 | M8: =INDEX(Assumptions!$O$22:$O$24,MATCH(G8,Assumptions!$N$22:$N$24,0)) -> 2 | N8: =IF(L8>M8,"SLA Breached","Within SLA") -> SLA Breached | O8: Documents chased; see ESC-008.
A9: ISS-008 | B9: C012 | C9: =IFERROR(INDEX(Client_Master!$B$2:$B$41,MATCH(B9,Client_Master!$A$2:$A$41,0)),"UNKNOWN CLIENT") -> Brightline Retail Holdings Inc | D9: Client query | E9: CTR clarification | F9: Client asked why its cash deposit was reported. | G9: Low | H9: 46316 | I9: 46317 | J9: Client Service | K9: =IF(ISNUMBER(I9),"Closed","Open") -> Closed | L9: =NETWORKDAYS(H9,IF(ISNUMBER(I9),I9,Assumptions!$B$4))-1 -> 1 | M9: =INDEX(Assumptions!$O$22:$O$24,MATCH(G9,Assumptions!$N$22:$N$24,0)) -> 10 | N9: =IF(L9>M9,"SLA Breached","Within SLA") -> Within SLA | O9: Explained that CTRs are a routine regulatory requirement for cash above the threshold and not an indication of wrongdoing. No internal assessments disclosed.
A10: ISS-009 | B10: C034 | C10: =IFERROR(INDEX(Client_Master!$B$2:$B$41,MATCH(B10,Client_Master!$A$2:$A$41,0)),"UNKNOWN CLIENT") -> Skyline Hospitality Group Ltd | D10: Recon - missing in core | E10: No core banking account | F10: Client onboarded in CRM but no account exists in core banking. | G10: Medium | H10: 46314 | J10: Client Data Ops | K10: =IF(ISNUMBER(I10),"Closed","Open") -> Open | L10: =NETWORKDAYS(H10,IF(ISNUMBER(I10),I10,Assumptions!$B$4))-1 -> 5 | M10: =INDEX(Assumptions!$O$22:$O$24,MATCH(G10,Assumptions!$N$22:$N$24,0)) -> 5 | N10: =IF(L10>M10,"SLA Breached","Within SLA") -> Within SLA | O10: RM to confirm whether account opening was cancelled.
A11: ISS-010 | B11: C021 | C11: =IFERROR(INDEX(Client_Master!$B$2:$B$41,MATCH(B11,Client_Master!$A$2:$A$41,0)),"UNKNOWN CLIENT") -> Kestrel Engineering Services Pte Ltd | D11: DQ check | E11: Date logic error | F11: Last KYC review date is earlier than onboarding date. | G11: Low | H11: 46315 | J11: KYC Quality | K11: =IF(ISNUMBER(I11),"Closed","Open") -> Open | L11: =NETWORKDAYS(H11,IF(ISNUMBER(I11),I11,Assumptions!$B$4))-1 -> 4 | M11: =INDEX(Assumptions!$O$22:$O$24,MATCH(G11,Assumptions!$N$22:$N$24,0)) -> 10 | N11: =IF(L11>M11,"SLA Breached","Within SLA") -> Within SLA | O11: Source documents requested to confirm the correct dates.
A12: ISS-011 | B12: C031 | C12: =IFERROR(INDEX(Client_Master!$B$2:$B$41,MATCH(B12,Client_Master!$A$2:$A$41,0)),"UNKNOWN CLIENT") -> Meridian Textile Exports Pvt Ltd | D12: DQ check | E12: Duplicate client record | F12: Same legal name as C006 under a different ID. | G12: Medium | H12: 46316 | J12: Client Data Ops | K12: =IF(ISNUMBER(I12),"Closed","Open") -> Open | L12: =NETWORKDAYS(H12,IF(ISNUMBER(I12),I12,Assumptions!$B$4))-1 -> 3 | M12: =INDEX(Assumptions!$O$22:$O$24,MATCH(G12,Assumptions!$N$22:$N$24,0)) -> 5 | N12: =IF(L12>M12,"SLA Breached","Within SLA") -> Within SLA | O12: Merge request raised; see ESC-010.
A13: ISS-012 | B13: C003 | C13: =IFERROR(INDEX(Client_Master!$B$2:$B$41,MATCH(B13,Client_Master!$A$2:$A$41,0)),"UNKNOWN CLIENT") -> Lotus Healthcare Systems Ltd | D13: Recon - txn break | E13: Statement discrepancy query | F13: Client queried the amount shown on its statement against its records. | G13: Medium | H13: 46307 | I13: 46309 | J13: Operations | K13: =IF(ISNUMBER(I13),"Closed","Open") -> Closed | L13: =NETWORKDAYS(H13,IF(ISNUMBER(I13),I13,Assumptions!$B$4))-1 -> 2 | M13: =INDEX(Assumptions!$O$22:$O$24,MATCH(G13,Assumptions!$N$22:$N$24,0)) -> 5 | N13: =IF(L13>M13,"SLA Breached","Within SLA") -> Within SLA | O13: Ledger confirmed correct; bank statement difference traced and correction requested (see Recon_Txn).
A14: ISS-013 | B14: C002 | C14: =IFERROR(INDEX(Client_Master!$B$2:$B$41,MATCH(B14,Client_Master!$A$2:$A$41,0)),"UNKNOWN CLIENT") -> Nordic Precision Manufacturing GmbH | D14: Client query | E14: Expired ID document | F14: Authorised signatory passport expired. | G14: Low | H14: 46303 | I14: 46315 | J14: KYC Operations | K14: =IF(ISNUMBER(I14),"Closed","Open") -> Closed | L14: =NETWORKDAYS(H14,IF(ISNUMBER(I14),I14,Assumptions!$B$4))-1 -> 8 | M14: =INDEX(Assumptions!$O$22:$O$24,MATCH(G14,Assumptions!$N$22:$N$24,0)) -> 10 | N14: =IF(L14>M14,"SLA Breached","Within SLA") -> Within SLA | O14: Renewed passport received, verified and filed.
A15: ISS-014 | B15: C011 | C15: =IFERROR(INDEX(Client_Master!$B$2:$B$41,MATCH(B15,Client_Master!$A$2:$A$41,0)),"UNKNOWN CLIENT") -> Coral Reef Gaming Ltd | D15: Periodic review | E15: KYC refresh overdue | F15: Periodic review is overdue; refresh documents requested. | G15: Medium | H15: 46317 | J15: KYC Operations | K15: =IF(ISNUMBER(I15),"Closed","Open") -> Open | L15: =NETWORKDAYS(H15,IF(ISNUMBER(I15),I15,Assumptions!$B$4))-1 -> 2 | M15: =INDEX(Assumptions!$O$22:$O$24,MATCH(G15,Assumptions!$N$22:$N$24,0)) -> 5 | N15: =IF(L15>M15,"SLA Breached","Within SLA") -> Within SLA | O15: Refresh pack sent to client via RM.
